Workbook

Sheet 01_21
A1: Tagesumsätze | H1: 44197
C3: Restaurant | E3: Terrasse | G3: Lounge | I3: Pavillon | K3: Bankett | M3: Seminar | O3: Hotel | Q3: TOTAL Gesamtbetrieb ohne Seebad | S3: Seebad | U3: TOTAL Gesamtbetrieb mit Seebad | W3: Info's
C4: IST | D4: Budget | E4: IST | F4: Budget | G4: IST | H4: Budget | I4: IST | J4: Budget | K4: IST | L4: Budget | M4: IST | N4: Budget | O4: IST | P4: Budget | Q4: IST | R4: Budget | S4: IST | T4: Budget | U4: IST | V4: Budget | W4: Wetter | X4: Temp. | Z4: Bemerkung
A5: 1 | B5: Fr | C5: 1620.2 | D5: 2096.7742 | E5: 0 | F5: 29.03225 | G5: 0 | H5: 56.4516 | I5: 0 | J5: 0 | K5: 0 | L5: 306.4516 | M5: 0 | N5: 137.0967 | O5: 1808 | P5: 385.4838 | Q5: =SUM(C5+E5+G5+I5+K5+M5+O5) -> 3428.2 | R5: =SUM(D5+F5+H5+J5+L5+N5+P5) -> 3011.2901 | U5: =SUM(Q5+S5) -> 3428.2 | V5: =SUM(R5+T5) -> 3011.2901 | Y5: °C | Z5: Rest. geschlossen Corona
A6: =SUM(A5+1) -> 2 | B6: Sa | C6: 872.9 | D6: 2096.7742 | E6: 0 | F6: 29.03225 | G6: 0 | H6: 56.4516 | I6: 0 | J6: 0 | K6: 0 | L6: 306.4516 | M6: 0 | N6: 137.0967 | O6: 1522 | P6: 385.4838 | Q6: =SUM(C6+E6+G6+I6+K6+M6+O6) -> 2394.9 | R6: =SUM(D6+F6+H6+J6+L6+N6+P6) -> 3011.2901 | U6: =SUM(Q6+S6) -> 2394.9 | V6: =SUM(R6+T6) -> 3011.2901 | Y6: °C | Z6: Rest. geschlossen Corona
A7: =SUM(A6+1) -> 3 | B7: So | C7: 0 | D7: 2096.7742 | E7: 0 | F7: 29.03225 | G7: 0 | H7: 56.4516 | I7: 0 | J7: 0 | K7: 0 | L7: 306.4516 | M7: 0 | N7: 137.0967 | O7: 257.6 | P7: 385.4838 | Q7: =SUM(C7+E7+G7+I7+K7+M7+O7) -> 257.6 | R7: =SUM(D7+F7+H7+J7+L7+N7+P7) -> 3011.2901 | U7: =SUM(Q7+S7) -> 257.6 | V7: =SUM(R7+T7) -> 3011.2901 | Y7: °C | Z7: Rest. geschlossen Corona
A8: KW | B8: 1 | C8: =SUM(C5:C7) -> 2493.1 | D8: =SUM(D5:D7) -> 6290.3226 | E8: =SUM(E5:E7) -> 0 | F8: =SUM(F5:F7) -> 87.09675 | G8: =SUM(G5:G7) -> 0 | H8: =SUM(H5:H7) -> 169.3548 | I8: =SUM(I5:I7) -> 0 | J8: =SUM(J5:J7) -> 0 | ... V8: =SUM(V5:V7) -> 9033.8704 | W8: Ø Temp | X8: =SUM(X5:X7)/5 -> 0 | Y8: °C
A9: =SUM(A7+1) -> 4 | B9: Mo | C9: 636.2 | D9: 2096.7742 | E9: 0 | F9: 29.03225 | G9: 0 | H9: 56.4516 | I9: 0 | J9: 0 | K9: 0 | L9: 306.4516 | M9: 0 | N9: 137.0967 | O9: 1240.2 | P9: 385.4838 | Q9: =SUM(C9+E9+G9+I9+K9+M9+O9) -> 1876.4 | R9: =SUM(D9+F9+H9+J9+L9+N9+P9) -> 3011.2901 | U9: =SUM(Q9+S9) -> 1876.4 | V9: =SUM(R9+T9) -> 3011.2901 | Y9: °C | Z9: Rest. geschlossen Corona
A10: =SUM(A9+1) -> 5 | B10: Di | C10: 694.5 | D10: 2096.7742 | E10: 0 | F10: 29.03225 | G10: 0 | H10: 56.4516 | I10: 0 | J10: 0 | K10: 0 | L10: 306.4516 | M10: 0 | N10: 137.0967 | O10: 1246.7 | P10: 385.4838 | Q10: =SUM(C10+E10+G10+I10+K10+M10+O10) -> 1941.2 | R10: =SUM(D10+F10+H10+J10+L10+N10+P10) -> 3011.2901 | U10: =SUM(Q10+S10) -> 1941.2 | V10: =SUM(R10+T10) -> 3011.2901 | Y10: °C | Z10: Rest. geschlossen Corona
A11: =SUM(A10+1) -> 6 | B11: Mi | C11: 378.3 | D11: 2096.7742 | E11: 0 | F11: 29.03225 | G11: 0 | H11: 56.4516 | I11: 0 | J11: 0 | K11: 0 | L11: 306.4516 | M11: 0 | N11: 137.0967 | O11: 942.6 | P11: 385.4838 | Q11: =SUM(C11+E11+G11+I11+K11+M11+O11) -> 1320.9 | R11: =SUM(D11+F11+H11+J11+L11+N11+P11) -> 3011.2901 | U11: =SUM(Q11+S11) -> 1320.9 | V11: =SUM(R11+T11) -> 3011.2901 | Y11: °C | Z11: Rest. geschlossen Corona
A12: =SUM(A11+1) -> 7 | B12: Do | C12: 388.4 | D12: 2096.7742 | E12: 0 | F12: 29.03225 | G12: 0 | H12: 56.4516 | I12: 0 | J12: 0 | K12: 0 | L12: 306.4516 | M12: 1508.3 | N12: 137.0967 | O12: 2089.2 | P12: 385.4838 | Q12: =SUM(C12+E12+G12+I12+K12+M12+O12) -> 3985.9 | R12: =SUM(D12+F12+H12+J12+L12+N12+P12) -> 3011.2901 | U12: =SUM(Q12+S12) -> 3985.9 | V12: =SUM(R12+T12) -> 3011.2901 | Y12: °C | Z12: Rest. geschlossen Corona
A13: =SUM(A12+1) -> 8 | B13: Fr | C13: 1768.3 | D13: 2096.7742 | E13: 0 | F13: 29.03225 | G13: 0 | H13: 56.4516 | I13: 0 | J13: 0 | K13: 0 | L13: 306.4516 | M13: 464.6 | N13: 137.0967 | O13: 1632.6 | P13: 385.4838 | Q13: =SUM(C13+E13+G13+I13+K13+M13+O13) -> 3865.5 | R13: =SUM(D13+F13+H13+J13+L13+N13+P13) -> 3011.2901 | U13: =SUM(Q13+S13) -> 3865.5 | V13: =SUM(R13+T13) -> 3011.2901 | Y13: °C | Z13: Rest. geschlossen Corona
A14: =SUM(A13+1) -> 9 | B14: Sa | C14: 1673.1 | D14: 2096.7742 | E14: 0 | F14: 29.03225 | G14: 0 | H14: 56.4516 | I14: 0 | J14: 0 | K14: 0 | L14: 306.4516 | M14: 0 | N14: 137.0967 | O14: 2297.4 | P14: 385.4838 | Q14: =SUM(C14+E14+G14+I14+K14+M14+O14) -> 3970.5 | R14: =SUM(D14+F14+H14+J14+L14+N14+P14) -> 3011.2901 | U14: =SUM(Q14+S14) -> 3970.5 | V14: =SUM(R14+T14) -> 3011.2901 | Y14: °C | Z14: Rest. geschlossen Corona
A15: =SUM(A14+1) -> 10 | B15: So | C15: 0 | D15: 2096.7742 | E15: 0 | F15: 29.03225 | G15: 0 | H15: 56.4516 | I15: 0 | J15: 0 | K15: 0 | L15: 306.4516 | M15: 0 | N15: 137.0967 | O15: 144.3 | P15: 385.4838 | Q15: =SUM(C15+E15+G15+I15+K15+M15+O15) -> 144.3 | R15: =SUM(D15+F15+H15+J15+L15+N15+P15) -> 3011.2901 | U15: =SUM(Q15+S15) -> 144.3 | V15: =SUM(R15+T15) -> 3011.2901 | Y15: °C | Z15: Rest. geschlossen Corona
A16: KW | B16: =SUM(B8+1) -> 2 | C16: =SUM(C9:C15) -> 5538.8 | D16: =SUM(D9:D15) -> 14677.419 | E16: =SUM(E9:E15) -> 0 | F16: =SUM(F9:F15) -> 203.22575 | G16: =SUM(G9:G15) -> 0 | H16: =SUM(H9:H15) -> 395.1612 | I16: =SUM(I9:I15) -> 0 | J16: 0 | K16: =SUM(K9:K15) -> 0 | L16: =SUM(L9:L15) -> 2145.1612 | M16: =SUM(M9:M15) -> 1972.9 | N16: =SUM(N9:N15) -> 959.6769 | O16: =SUM(O9:O15) -> 9593 | P16: =SUM(P9:P15) -> 2698.3866 | Q16: =SUM(Q9:Q15) -> 17104.7 | R16: =SUM(R9:R15) -> 21079.031 | ... V16: =SUM(V9:V15) -> 21079.031 | W16: Ø Temp | X16: =SUM(X9:X15)/7 -> 0 | Y16: °C
A17: =SUM(A15+1) -> 11 | B17: Mo | C17: 184.1 | D17: 2096.7742 | E17: 0 | F17: 29.03225 | G17: 0 | H17: 56.4516 | I17: 0 | J17: 0 | K17: 0 | L17: 306.4516 | M17: 0 | N17: 137.0967 | O17: 333.6 | P17: 385.4838 | Q17: =SUM(C17+E17+G17+I17+K17+M17+O17) -> 517.7 | R17: =SUM(D17+F17+H17+J17+L17+N17+P17) -> 3011.2901 | U17: =SUM(Q17+S17) -> 517.7 | V17: =SUM(R17+T17) -> 3011.2901 | Y17: °C | Z17: Rest. geschlossen Corona
A18: =SUM(A17+1) -> 12 | B18: Di | C18: 248.7 | D18: 2096.7742 | E18: 0 | F18: 29.03225 | G18: 0 | H18: 56.4516 | I18: 0 | J18: 0 | K18: 0 | L18: 306.4516 | M18: 0 | N18: 137.0967 | O18: 1215.1 | P18: 385.4838 | Q18: =SUM(C18+E18+G18+I18+K18+M18+O18) -> 1463.8 | R18: =SUM(D18+F18+H18+J18+L18+N18+P18) -> 3011.2901 | U18: =SUM(Q18+S18) -> 1463.8 | V18: =SUM(R18+T18) -> 3011.2901 | Y18: °C | Z18: Rest. geschlossen Corona
A19: =SUM(A18+1) -> 13 | B19: Mi | C19: 824 | D19: 2096.7742 | E19: 0 | F19: 29.03225 | G19: 0 | H19: 56.4516 | I19: 0 | J19: 0 | K19: 0 | L19: 306.4516 | M19: 0 | N19: 137.0967 | O19: 1623.7 | P19: 385.4838 | Q19: =SUM(C19+E19+G19+I19+K19+M19+O19) -> 2447.7 | R19: =SUM(D19+F19+H19+J19+L19+N19+P19) -> 3011.2901 | U19: =SUM(Q19+S19) -> 2447.7 | V19: =SUM(R19+T19) -> 3011.2901 | Y19: °C | Z19: Rest. geschlossen Corona
A20: =SUM(A19+1) -> 14 | B20: Do | C20: 76.9 | D20: 2096.7742 | E20: 0 | F20: 29.03225 | G20: 0 | H20: 56.4516 | I20: 0 | J20: 0 | K20: 0 | L20: 306.4516 | M20: 0 | N20: 137.0967 | O20: 596 | P20: 385.4838 | Q20: =SUM(C20+E20+G20+I20+K20+M20+O20) -> 672.9 | R20: =SUM(D20+F20+H20+J20+L20+N20+P20) -> 3011.2901 | U20: =SUM(Q20+S20) -> 672.9 | V20: =SUM(R20+T20) -> 3011.2901 | Y20: °C | Z20: Rest. geschlossen Corona
A21: =SUM(A20+1) -> 15 | B21: Fr | C21: 243.9 | D21: 2096.7742 | E21: 0 | F21: 29.03225 | G21: 0 | H21: 56.4516 | I21: 0 | J21: 0 | K21: 0 | L21: 306.4516 | M21: 0 | N21: 137.0967 | O21: 890.1 | P21: 385.4838 | Q21: =SUM(C21+E21+G21+I21+K21+M21+O21) -> 1134 | R21: =SUM(D21+F21+H21+J21+L21+N21+P21) -> 3011.2901 | U21: =SUM(Q21+S21) -> 1134 | V21: =SUM(R21+T21) -> 3011.2901 | Y21: °C | Z21: Rest. geschlossen Corona
A22: =SUM(A21+1) -> 16 | B22: Sa | C22: 1049.3 | D22: 2096.7742 | E22: 0 | F22: 29.03225 | G22: 0 | H22: 56.4516 | I22: 0 | J22: 0 | K22: 0 | L22: 306.4516 | M22: 0 | N22: 137.0967 | O22: 1775.4 | P22: 385.4838 | Q22: =SUM(C22+E22+G22+I22+K22+M22+O22) -> 2824.7 | R22: =SUM(D22+F22+H22+J22+L22+N22+P22) -> 3011.2901 | U22: =SUM(Q22+S22) -> 2824.7 | V22: =SUM(R22+T22) -> 3011.2901 | Y22: °C | Z22: Rest. geschlossen Corona
A23: =SUM(A22+1) -> 17 | B23: So | C23: 114.7 | D23: 2096.7742 | E23: 0 | F23: 29.03225 | G23: 0 | H23: 56.4516 | I23: 0 | J23: 0 | K23: 0 | L23: 306.4516 | M23: 0 | N23: 137.0967 | O23: 643 | P23: 385.4838 | Q23: =SUM(C23+E23+G23+I23+K23+M23+O23) -> 757.7 | R23: =SUM(D23+F23+H23+J23+L23+N23+P23) -> 3011.2901 | U23: =SUM(Q23+S23) -> 757.7 | V23: =SUM(R23+T23) -> 3011.2901 | Y23: °C | Z23: Rest. geschlossen Corona
A24: KW | B24: =SUM(B16+1) -> 3 | C24: =SUM(C17:C23) -> 2741.6 | D24: =SUM(D17:D23) -> 14677.419 | E24: =SUM(E17:E23) -> 0 | F24: =SUM(F17:F23) -> 203.22575 | G24: =SUM(G17:G23) -> 0 | H24: =SUM(H17:H23) -> 395.1612 | I24: =SUM(I17:I23) -> 0 | J24: 0 | K24: =SUM(K17:K23) -> 0 | L24: =SUM(L17:L23) -> 2145.1612 | M24: =SUM(M17:M23) -> 0 | N24: =SUM(N17:N23) -> 959.6769 | O24: =SUM(O17:O23) -> 7076.9 | P24: =SUM(P17:P23) -> 2698.3866 | Q24: =SUM(Q17:Q23) -> 9818.5 | R24: =SUM(R17:R23) -> 21079.031 | ... V24: =SUM(V17:V23) -> 21079.031 | W24: Ø Temp | X24: =SUM(X17:X23)/7 -> 0 | Y24: °C
A25: =SUM(A23+1) -> 18 | B25: Mo | C25: 831.1 | D25: 2096.7742 | E25: 0 | F25: 29.03225 | G25: 0 | H25: 56.4516 | I25: 0 | J25: 0 | K25: 0 | L25: 306.4516 | M25: 0 | N25: 137.0967 | O25: 1126.4 | P25: 385.4838 | Q25: =SUM(C25+E25+G25+I25+K25+M25+O25) -> 1957.5 | R25: =SUM(D25+F25+H25+J25+L25+N25+P25) -> 3011.2901 | U25: =SUM(Q25+S25) -> 1957.5 | V25: =SUM(R25+T25) -> 3011.2901 | Y25: °C | Z25: Rest. geschlossen Corona
A26: =SUM(A25+1) -> 19 | B26: Di | C26: 464.1 | D26: 2096.7742 | E26: 0 | F26: 29.03225 | G26: 0 | H26: 56.4516 | I26: 0 | J26: 0 | K26: 0 | L26: 306.4516 | M26: 0 | N26: 137.0967 | O26: 1004.6 | P26: 385.4838 | Q26: =SUM(C26+E26+G26+I26+K26+M26+O26) -> 1468.7 | R26: =SUM(D26+F26+H26+J26+L26+N26+P26) -> 3011.2901 | U26: =SUM(Q26+S26) -> 1468.7 | V26: =SUM(R26+T26) -> 3011.2901 | Y26: °C | Z26: Rest. geschlossen Corona
A27: =SUM(A26+1) -> 20 | B27: Mi | C27: 85.7 | D27: 2096.7742 | E27: 0 | F27: 29.03225 | G27: 0 | H27: 56.4516 | I27: 0 | J27: 0 | K27: 0 | L27: 306.4516 | M27: 0 | N27: 137.0967 | O27: 974.6 | P27: 385.4838 | Q27: =SUM(C27+E27+G27+I27+K27+M27+O27) -> 1060.3 | R27: =SUM(D27+F27+H27+J27+L27+N27+P27) -> 3011.2901 | U27: =SUM(Q27+S27) -> 1060.3 | V27: =SUM(R27+T27) -> 3011.2901 | Y27: °C | Z27: Rest. geschlossen Corona
A28: =SUM(A27+1) -> 21 | B28: Do | C28: 123.2 | D28: 2096.7742 | E28: 0 | F28: 29.03225 | G28: 0 | H28: 56.4516 | I28: 0 | J28: 0 | K28: 0 | L28: 306.4516 | M28: 0 | N28: 137.0967 | O28: 257.6 | P28: 385.4838 | Q28: =SUM(C28+E28+G28+I28+K28+M28+O28) -> 380.8 | R28: =SUM(D28+F28+H28+J28+L28+N28+P28) -> 3011.2901 | U28: =SUM(Q28+S28) -> 380.8 | V28: =SUM(R28+T28) -> 3011.2901 | Y28: °C | Z28: Rest. geschlossen Corona
A29: =SUM(A28+1) -> 22 | B29: Fr | C29: 123.2 | D29: 2096.7742 | E29: 0 | F29: 29.03225 | G29: 0 | H29: 56.4516 | I29: 0 | J29: 0 | K29: 0 | L29: 306.4516 | M29: 0 | N29: 137.0967 | O29: 255.6 | P29: 385.4838 | Q29: =SUM(C29+E29+G29+I29+K29+M29+O29) -> 378.8 | R29: =SUM(D29+F29+H29+J29+L29+N29+P29) -> 3011.2901 | U29: =SUM(Q29+S29) -> 378.8 | V29: =SUM(R29+T29) -> 3011.2901 | Y29: °C | Z29: Rest. geschlossen Corona
A30: =SUM(A29+1) -> 23 | B30: Sa | C30: 2673.2 | D30: 2096.7742 | E30: 0 | F30: 29.03225 | G30: 0 | H30: 56.4516 | I30: 0 | J30: 0 | K30: 0 | L30: 306.4516 | M30: 0 | N30: 137.0967 | O30: 2930.4 | P30: 385.4838 | Q30: =SUM(C30+E30+G30+I30+K30+M30+O30) -> 5603.6 | R30: =SUM(D30+F30+H30+J30+L30+N30+P30) -> 3011.2901 | U30: =SUM(Q30+S30) -> 5603.6 | V30: =SUM(R30+T30) -> 3011.2901 | Y30: °C | Z30: Rest. geschlossen Corona
A31: =SUM(A30+1) -> 24 | B31: So | C31: -300 | D31: 2096.7742 | E31: 0 | F31: 29.03225 | G31: 0 | H31: 56.4516 | I31: 0 | J31: 0 | K31: 0 | L31: 306.4516 | M31: 0 | N31: 137.0967 | O31: 117 | P31: 385.4838 | Q31: =SUM(C31+E31+G31+I31+K31+M31+O31) -> -183 | R31: =SUM(D31+F31+H31+J31+L31+N31+P31) -> 3011.2901 | U31: =SUM(Q31+S31) -> -183 | V31: =SUM(R31+T31) -> 3011.2901 | Y31: °C | Z31: Rest. geschlossen Corona
A32: KW | B32: =SUM(B24+1) -> 4 | C32: =SUM(C25:C31) -> 4000.5 | D32: =SUM(D25:D31) -> 14677.419 | E32: =SUM(E25:E31) -> 0 | F32: =SUM(F25:F31) -> 203.22575 | G32: =SUM(G25:G31) -> 0 | H32: =SUM(H25:H31) -> 395.1612 | I32: =SUM(I25:I31) -> 0 | J32: =SUM(J25:J31) -> 0 | ... V32: =SUM(V25:V31) -> 21079.031 | W32: Ø Temp | X32: =SUM(X25:X31)/7 -> 0 | Y32: °C
A33: =SUM(A31+1) -> 25 | B33: Mo | C33: 641 | D33: 2096.7742 | E33: 0 | F33: 29.03225 | G33: 0 | H33: 56.4516 | I33: 0 | J33: 0 | K33: 0 | L33: 306.4516 | M33: 0 | N33: 137.0967 | O33: 319.4 | P33: 385.4838 | Q33: =SUM(C33+E33+G33+I33+K33+M33+O33) -> 960.4 | R33: =SUM(D33+F33+H33+J33+L33+N33+P33) -> 3011.2901 | U33: =SUM(Q33+S33) -> 960.4 | V33: =SUM(R33+T33) -> 3011.2901 | Y33: °C | Z33: Rest. geschlossen Corona
A34: =SUM(A33+1) -> 26 | B34: Di | C34: 200.3 | D34: 2096.7742 | E34: 0 | F34: 29.03225 | G34: 0 | H34: 56.4516 | I34: 0 | J34: 0 | K34: 0 | L34: 306.4516 | M34: 0 | N34: 137.0967 | O34: 235.6 | P34: 385.4838 | Q34: =SUM(C34+E34+G34+I34+K34+M34+O34) -> 435.9 | R34: =SUM(D34+F34+H34+J34+L34+N34+P34) -> 3011.2901 | U34: =SUM(Q34+S34) -> 435.9 | V34: =SUM(R34+T34) -> 3011.2901 | Y34: °C | Z34: Rest. geschlossen Corona
A35: =SUM(A34+1) -> 27 | B35: Mi | C35: 712.1 | D35: 2096.7742 | E35: 0 | F35: 29.03225 | G35: 0 | H35: 56.4516 | I35: 0 | J35: 0 | K35: 0 | L35: 306.4516 | M35: 0 | N35: 137.0967 | O35: 956.6 | P35: 385.4838 | Q35: =SUM(C35+E35+G35+I35+K35+M35+O35) -> 1668.7 | R35: =SUM(D35+F35+H35+J35+L35+N35+P35) -> 3011.2901 | U35: =SUM(Q35+S35) -> 1668.7 | V35: =SUM(R35+T35) -> 3011.2901 | Y35: °C | Z35: Rest. geschlossen Corona
A36: =SUM(A35+1) -> 28 | B36: Do | C36: 670 | D36: 2096.7742 | E36: 0 | F36: 29.03225 | G36: 0 | H36: 56.4516 | I36: 0 | J36: 0 | K36: 0 | L36: 306.4516 | M36: 0 | N36: 137.0967 | O36: 250.1 | P36: 385.4838 | Q36: =SUM(C36+E36+G36+I36+K36+M36+O36) -> 920.1 | R36: =SUM(D36+F36+H36+J36+L36+N36+P36) -> 3011.2901 | U36: =SUM(Q36+S36) -> 920.1 | V36: =SUM(R36+T36) -> 3011.2901 | Y36: °C | Z36: Rest. geschlossen Corona
A37: =SUM(A36+1) -> 29 | B37: Fr | C37: 774 | D37: 2096.7742 | E37: 0 | F37: 29.03225 | G37: 0 | H37: 56.4516 | I37: 0 | J37: 0 | K37: 0 | L37: 306.4516 | M37: 0 | N37: 137.0967 | O37: 1151.9 | P37: 385.4838 | Q37: =SUM(C37+E37+G37+I37+K37+M37+O37) -> 1925.9 | R37: =SUM(D37+F37+H37+J37+L37+N37+P37) -> 3011.2901 | U37: =SUM(Q37+S37) -> 1925.9 | V37: =SUM(R37+T37) -> 3011.2901 | Y37: °C | Z37: Rest. geschlossen Corona
A38: =SUM(A37+1) -> 30 | B38: Sa | C38: 1863.1 | D38: 2096.7742 | E38: 0 | F38: 29.03225 | G38: 0 | H38: 56.4516 | I38: 0 | J38: 0 | K38: 0 | L38: 306.4516 | M38: 0 | N38: 137.0967 | O38: 2771.6 | P38: 385.4838 | Q38: =SUM(C38+E38+G38+I38+K38+M38+O38) -> 4634.7 | R38: =SUM(D38+F38+H38+J38+L38+N38+P38) -> 3011.2901 | U38: =SUM(Q38+S38) -> 4634.7 | V38: =SUM(R38+T38) -> 3011.2901 | Y38: °C | Z38: Rest. geschlossen Corona
A39: =SUM(A38+1) -> 31 | B39: So | C39: -136.6 | D39: 2096.7742 | E39: 0 | F39: 29.03225 | G39: 0 | H39: 56.4516 | I39: 0 | J39: 0 | K39: 0 | L39: 306.4516 | M39: 0 | N39: 137.0967 | O39: 0 | P39: 385.4838 | Q39: =SUM(C39+E39+G39+I39+K39+M39+O39) -> -136.6 | R39: =SUM(D39+F39+H39+J39+L39+N39+P39) -> 3011.2901 | U39: =SUM(Q39+S39) -> -136.6 | V39: =SUM(R39+T39) -> 3011.2901 | Y39: °C | Z39: Rest. geschlossen Corona
A40: KW | B40: =SUM(B32+1) -> 5 | C40: =SUM(C33:C39) -> 4723.9 | D40: =SUM(D33:D39) -> 14677.419 | E40: =SUM(E33:E39) -> 0 | F40: =SUM(F33:F39) -> 203.22575 | G40: =SUM(G33:G39) -> 0 | H40: =SUM(H33:H39) -> 395.1612 | I40: =SUM(I33:I39) -> 0 | J40: 0 | K40: =SUM(K33:K39) -> 0 | L40: =SUM(L33:L39) -> 2145.1612 | M40: =SUM(M33:M39) -> 0 | N40: =SUM(N33:N39) -> 959.6769 | O40: =SUM(O33:O39) -> 5685.2 | P40: =SUM(P33:P39) -> 2698.3866 | Q40: =SUM(Q33:Q39) -> 10409.1 | R40: =SUM(R33:R39) -> 21079.031 | ... V40: =SUM(V33:V39) -> 21079.031 | W40: Ø Temp | X40: =SUM(X33:X39)/7 -> 0 | Y40: °C
A41: Umsatz kumuliert | C41: =SUM(C8+C16+C24+C32+C40) -> 19497.9 | D41: =SUM(D8+D16+D24+D32+D40) -> 65000 | E41: =SUM(E8+E16+E24+E32+E40) -> 0 | F41: =SUM(F8+F16+F24+F32+F40) -> 899.99975 | G41: =SUM(G8+G16+G24+G32+G40) -> 0 | H41: =SUM(H8+H16+H24+H32+H40) -> 1749.9996 | I41: =SUM(I8+I16+I24+I32+I40) -> 0 | J41: =SUM(J8+J16+J24+J32+J40) -> 0 | ... Q41: =SUM(Q8+Q16+Q24+Q32+Q40) -> 54079.7 | R41: =SUM(D41+F41+H41+J41+L41+N41+P41) -> 93349.994 | S41: =SUM(S8+S16+S24+S32+S40) -> 0 | T41: =SUM(T8+T16+T24+T32+T40) -> 0 | U41: =SUM(U8+U16+U24+U32+U40) -> 54079.7 | V41: =SUM(V8+V16+V24+V32+V40) -> 93349.994 | W41: Umsatz kumuliert
A42: Umsatz Forecast | C42: =IF(MONTH($H$1)<>MONTH(TODAY()),C41,SUM(C5:C7,C9:C15,C17:C23,C25:C31,C33:C39)/DAY(TODAY())*DAY(DATE(YEAR($H$1),MONTH($H$1)+1,1)-1)) -> 19497.9 | D42: =IF(MONTH($H$1)<>MONTH(TODAY()),D41,SUM(D5:D7,D9:D15,D17:D23,D25:D31,D33:D39)/DAY(TODAY())*DAY(DATE(YEAR($H$1),MONTH($H$1)+1,1)-1)) -> 65000 | E42: =IF(MONTH($H$1)<>MONTH(TODAY()),E41,SUM(E5:E7,E9:E15,E17:E23,E25:E31,E33:E39)/DAY(TODAY())*DAY(DATE(YEAR($H$1),MONTH($H$1)+1,1)-1)) -> 0 | F42: =IF(MONTH($H$1)<>MONTH(TODAY()),F41,SUM(F5:F7,F9:F15,F17:F23,F25:F31,F33:F39)/DAY(TODAY())*DAY(DATE(YEAR($H$1),MONTH($H$1)+1,1)-1)) -> 899.99975 | G42: =IF(MONTH($H$1)<>MONTH(TODAY()),G41,SUM(G5:G7,G9:G15,G17:G23,G25:G31,G33:G39)/DAY(TODAY())*DAY(DATE(YEAR($H$1),MONTH($H$1)+1,1)-1)) -> 0 | H42: =IF(MONTH($H$1)<>MONTH(TODAY()),H41,SUM(H5:H7,H9:H15,H17:H23,H25:H31,H33:H39)/DAY(TODAY())*DAY(DATE(YEAR($H$1),MONTH($H$1)+1,1)-1)) -> 1749.9996 | I42: =IF(MONTH($H$1)<>MONTH(TODAY()),I41,SUM(I5:I7,I9:I15,I17:I23,I25:I31,I33:I39)/DAY(TODAY())*DAY(DATE(YEAR($H$1),MONTH($H$1)+1,1)-1)) -> 0 | J42: =IF(MONTH($H$1)<>MONTH(TODAY()),J41,SUM(J5:J7,J9:J15,J17:J23,J25:J31,J33:J39)/DAY(TODAY())*DAY(DATE(YEAR($H$1),MONTH($H$1)+1,1)-1)) -> 0 | ... V42: =IF(MONTH($H$1)<>MONTH(TODAY()),V41,SUM(V5:V7,V9:V15,V17:V23,V25:V31,V33:V39)/DAY(TODAY())*DAY(DATE(YEAR($H$1),MONTH($H$1)+1,1)-1)) -> 93349.994 | W42: Umsatz Forecast
A43: Umsatz pro Tag | C43: =C41/31 -> 628.96452 | D43: =D41/31 -> 2096.7742 | E43: =E41/31 -> 0 | F43: =F41/31 -> 29.03225 | G43: =G41/31 -> 0 | H43: =H41/31 -> 56.4516 | I43: =I41/31 -> 0 | J43: =J41/31 -> 0 | ... V43: =V41/31 -> 3011.2901 | W43: Budget pro Tag
A44: Diff. zu Budget | C44: =SUM(C41-D41) -> -45502.1 | E44: =SUM(E41-F41) -> -899.99975 | G44: =SUM(G41-H41) -> -1749.9996 | I44: =SUM(I41-J41) -> 0 | K44: =SUM(K41-L41) -> -9499.9996 | M44: =SUM(M41-N41) -> -2277.0977 | O44: =SUM(O41-P41) -> 20658.902 | Q44: =SUM(Q41-R41) -> -39270.294 | S44: =SUM(S41-T41) -> 0 | U44: =SUM(U41-V41) -> -39270.294
A45: Index | C45: =SUM(100/D41*C41) -> 29.996769 | E45: =SUM(100/F41*E41) -> 0 | G45: =SUM(100/H41*G41) -> 0 | I45: =SUM(100/J41*I41) -> #DIV/0! | K45: =SUM(100/L41*K41) -> 0 | M45: =SUM(100/N41*M41) -> 46.421202 | O45: =SUM(100/P41*O41) -> 272.87787 | Q45: =SUM(100/R41*Q41) -> 57.932194 | S45: =SUM(100/T41*S41) -> #DIV/0! | U45: =SUM(100/V41*U41) -> 57.932194

Sheet 02_21
A1: Tagesumsätze | H1: 44228
C3: Restaurant | E3: Terrasse | G3: Lounge | I3: Pavillon | K3: Bankett | M3: Seminar | O3: Hotel | Q3: TOTAL Gesamtbetrieb ohne Seebad | S3: Seebad | U3: TOTAL Gesamtbetrieb mit Seebad | W3: Info's
C4: IST | D4: Budget | E4: IST | F4: Budget | G4: IST | H4: Budget | I4: IST | J4: Budget | K4: IST | L4: Budget | M4: IST | N4: Budget | O4: IST | P4: Budget | Q4: IST | R4: Budget | S4: IST | T4: Budget | U4: IST | V4: Budget | W4: Wetter | X4: Temp. | Z4: Bemerkung
A5: 1 | B5: Mo | C5: 93.8 | D5: 1000 | E5: 0 | F5: 142.85714 | G5: 0 | H5: 142.85714 | I5: 0 | J5: 0 | K5: 0 | L5: 571.42857 | M5: 0 | N5: 571.42857 | O5: 273.6 | P5: 757.85714 | Q5: =SUM(C5+E5+G5+I5+K5+M5+O5) -> 367.4 | R5: =SUM(D5+F5+H5+J5+L5+N5+P5) -> 3186.4286 | S5: 0 | T5: 0 | U5: =SUM(Q5+S5) -> 367.4 | V5: =SUM(R5+T5) -> 3186.4286 | Y5: °C
A6: =SUM(A5+1) -> 2 | B6: Di | C6: 205.4 | D6: 1000 | E6: 0 | F6: 142.85714 | G6: 0 | H6: 142.85714 | I6: 0 | J6: 0 | K6: 0 | L6: 571.42857 | M6: 0 | N6: 571.42857 | O6: 235.6 | P6: 757.85714 | Q6: =SUM(C6+E6+G6+I6+K6+M6+O6) -> 441 | R6: =SUM(D6+F6+H6+J6+L6+N6+P6) -> 3186.4286 | S6: 0 | T6: 0 | U6: =SUM(Q6+S6) -> 441 | V6: =SUM(R6+T6) -> 3186.4286 | Y6: °C
A7: =SUM(A6+1) -> 3 | B7: Mi | C7: 0 | D7: 1000 | E7: 0 | F7: 142.85714 | G7: 0 | H7: 142.85714 | I7: 0 | J7: 0 | K7: 0 | L7: 571.42857 | M7: 0 | N7: 571.42857 | O7: 0 | P7: 757.85714 | Q7: =SUM(C7+E7+G7+I7+K7+M7+O7) -> 0 | R7: =SUM(D7+F7+H7+J7+L7+N7+P7) -> 3186.4286 | S7: 0 | T7: 0 | U7: =SUM(Q7+S7) -> 0 | V7: =SUM(R7+T7) -> 3186.4286 | Y7: °C
A8: =SUM(A7+1) -> 4 | B8: Do | C8: 1411 | D8: 1000 | E8: 0 | F8: 142.85714 | G8: 0 | H8: 142.85714 | I8: 0 | J8: 0 | K8: 0 | L8: 571.42857 | M8: 0 | N8: 571.42857 | O8: 1298 | P8: 757.85714 | Q8: =SUM(C8+E8+G8+I8+K8+M8+O8) -> 2709 | R8: =SUM(D8+F8+H8+J8+L8+N8+P8) -> 3186.4286 | S8: 0 | T8: 0 | U8: =SUM(Q8+S8) -> 2709 | V8: =SUM(R8+T8) -> 3186.4286 | Y8: °C
A9: =SUM(A8+1) -> 5 | B9: Fr | C9: 1680.9 | D9: 1000 | E9: 0 | F9: 142.85714 | G9: 0 | H9: 142.85714 | I9: 0 | J9: 0 | K9: 0 | L9: 571.42857 | M9: 1133.7 | N9: 571.42857 | O9: 1972.6 | P9: 757.85714 | Q9: =SUM(C9+E9+G9+I9+K9+M9+O9) -> 4787.2 | R9: =SUM(D9+F9+H9+J9+L9+N9+P9) -> 3186.4286 | S9: 0 | T9: 0 | U9: =SUM(Q9+S9) -> 4787.2 | V9: =SUM(R9+T9) -> 3186.4286 | Y9: °C
A10: =SUM(A9+1) -> 6 | B10: Sa | C10: 2955.6 | D10: 1000 | E10: 0 | F10: 142.85714 | G10: 0 | H10: 142.85714 | I10: 0 | J10: 0 | K10: 378.8 | L10: 571.42857 | M10: 19 | N10: 571.42857 | O10: 3673.8 | P10: 757.85714 | Q10: =SUM(C10+E10+G10+I10+K10+M10+O10) -> 7027.2 | R10: =SUM(D10+F10+H10+J10+L10+N10+P10) -> 3186.4286 | S10: 0 | T10: 0 | U10: =SUM(Q10+S10) -> 7027.2 | V10: =SUM(R10+T10) -> 3186.4286 | Y10: °C
A11: =SUM(A10+1) -> 7 | B11: So | C11: 30 | D11: 1000 | E11: 0 | F11: 142.85714 | G11: 0 | H11: 142.85714 | I11: 0 | J11: 0 | K11: 0 | L11: 571.42857 | M11: 150 | N11: 571.42857 | O11: 48.5 | P11: 757.85714 | Q11: =SUM(C11+E11+G11+I11+K11+M11+O11) -> 228.5 | R11: =SUM(D11+F11+H11+J11+L11+N11+P11) -> 3186.4286 | S11: 0 | T11: 0 | U11: =SUM(Q11+S11) -> 228.5 | V11: =SUM(R11+T11) -> 3186.4286 | Y11: °C
A12: KW | B12: 6 | C12: =SUM(C5:C11) -> 6376.7 | D12: =SUM(D5:D11) -> 7000 | E12: =SUM(E5:E11) -> 0 | F12: =SUM(F5:F11) -> 999.99998 | G12: =SUM(G5:G11) -> 0 | H12: =SUM(H5:H11) -> 999.99998 | I12: =SUM(I5:I11) -> 0 | J12: =SUM(J5:J11) -> 0 | ... V12: =SUM(V5:V11) -> 22305 | W12: Ø Temp | X12: =SUM(X5:X11)/7 -> 0 | Y12: °C | Z12: Hotel geschlossen
A13: =SUM(A11+1) -> 8 | B13: Mo | Q13: =SUM(C13+E13+G13+I13+K13+M13+O13) -> 0 | R13: =SUM(D13+F13+H13+J13+L13+N13+P13) -> 0 | U13: =SUM(Q13+S13) -> 0 | V13: =SUM(R13+T13) -> 0 | Y13: °C | Z13: Hotel geschlossen
A14: =SUM(A13+1) -> 9 | B14: Di | Q14: =SUM(C14+E14+G14+I14+K14+M14+O14) -> 0 | R14: =SUM(D14+F14+H14+J14+L14+N14+P14) -> 0 | U14: =SUM(Q14+S14) -> 0 | V14: =SUM(R14+T14) -> 0 | Y14: °C | Z14: Hotel geschlossen
A15: =SUM(A14+1) -> 10 | B15: Mi | Q15: =SUM(C15+E15+G15+I15+K15+M15+O15) -> 0 | R15: =SUM(D15+F15+H15+J15+L15+N15+P15) -> 0 | U15: =SUM(Q15+S15) -> 0 | V15: =SUM(R15+T15) -> 0 | Y15: °C | Z15: Hotel geschlossen
A16: =SUM(A15+1) -> 11 | B16: Do | Q16: =SUM(C16+E16+G16+I16+K16+M16+O16) -> 0 | R16: =SUM(D16+F16+H16+J16+L16+N16+P16) -> 0 | U16: =SUM(Q16+S16) -> 0 | V16: =SUM(R16+T16) -> 0 | Y16: °C | Z16: Hotel geschlossen
A17: =SUM(A16+1) -> 12 | B17: Fr | Q17: =SUM(C17+E17+G17+I17+K17+M17+O17) -> 0 | R17: =SUM(D17+F17+H17+J17+L17+N17+P17) -> 0 | U17: =SUM(Q17+S17) -> 0 | V17: =SUM(R17+T17) -> 0 | Y17: °C | Z17: Hotel geschlossen
A18: =SUM(A17+1) -> 13 | B18: Sa | Q18: =SUM(C18+E18+G18+I18+K18+M18+O18) -> 0 | R18: =SUM(D18+F18+H18+J18+L18+N18+P18) -> 0 | U18: =SUM(Q18+S18) -> 0 | V18: =SUM(R18+T18) -> 0 | Y18: °C | Z18: Hotel geschlossen
A19: =SUM(A18+1) -> 14 | B19: So | Q19: =SUM(C19+E19+G19+I19+K19+M19+O19) -> 0 | R19: =SUM(D19+F19+H19+J19+L19+N19+P19) -> 0 | U19: =SUM(Q19+S19) -> 0 | V19: =SUM(R19+T19) -> 0 | Y19: °C | Z19: Hotel geschlossen
A20: KW | B20: =SUM(B12+1) -> 7 | C20: =SUM(C13:C19) -> 0 | D20: =SUM(D13:D19) -> 0 | E20: =SUM(E13:E19) -> 0 | F20: =SUM(F13:F19) -> 0 | G20: =SUM(G13:G19) -> 0 | H20: =SUM(H13:H19) -> 0 | I20: =SUM(I13:I19) -> 0 | J20: =SUM(J13:J19) -> 0 | ... V20: =SUM(V13:V19) -> 0 | W20: Ø Temp | X20: =SUM(X13:X19)/7 -> 0 | Y20: °C | Z20: Hotel geschlossen
A21: =SUM(A19+1) -> 15 | B21: Mo | Q21: =SUM(C21+E21+G21+I21+K21+M21+O21) -> 0 | R21: =SUM(D21+F21+H21+J21+L21+N21+P21) -> 0 | U21: =SUM(Q21+S21) -> 0 | V21: =SUM(R21+T21) -> 0 | Y21: °C | Z21: Hotel geschlossen
A22: =SUM(A21+1) -> 16 | B22: Di | Q22: =SUM(C22+E22+G22+I22+K22+M22+O22) -> 0 | R22: =SUM(D22+F22+H22+J22+L22+N22+P22) -> 0 | U22: =SUM(Q22+S22) -> 0 | V22: =SUM(R22+T22) -> 0 | Y22: °C | Z22: Hotel geschlossen
A23: =SUM(A22+1) -> 17 | B23: Mi | Q23: =SUM(C23+E23+G23+I23+K23+M23+O23) -> 0 | R23: =SUM(D23+F23+H23+J23+L23+N23+P23) -> 0 | U23: =SUM(Q23+S23) -> 0 | V23: =SUM(R23+T23) -> 0 | Y23: °C | Z23: Hotel geschlossen
A24: =SUM(A23+1) -> 18 | B24: Do | Q24: =SUM(C24+E24+G24+I24+K24+M24+O24) -> 0 | R24: =SUM(D24+F24+H24+J24+L24+N24+P24) -> 0 | U24: =SUM(Q24+S24) -> 0 | V24: =SUM(R24+T24) -> 0 | Y24: °C | Z24: Hotel geschlossen
A25: =SUM(A24+1) -> 19 | B25: Fr | Q25: =SUM(C25+E25+G25+I25+K25+M25+O25) -> 0 | R25: =SUM(D25+F25+H25+J25+L25+N25+P25) -> 0 | U25: =SUM(Q25+S25) -> 0 | V25: =SUM(R25+T25) -> 0 | Y25: °C | Z25: Hotel geschlossen
A26: =SUM(A25+1) -> 20 | B26: Sa | Q26: =SUM(C26+E26+G26+I26+K26+M26+O26) -> 0 | R26: =SUM(D26+F26+H26+J26+L26+N26+P26) -> 0 | U26: =SUM(Q26+S26) -> 0 | V26: =SUM(R26+T26) -> 0 | Y26: °C | Z26: Hotel geschlossen
A27: =SUM(A26+1) -> 21 | B27: So | Q27: =SUM(C27+E27+G27+I27+K27+M27+O27) -> 0 | R27: =SUM(D27+F27+H27+J27+L27+N27+P27) -> 0 | U27: =SUM(Q27+S27) -> 0 | V27: =SUM(R27+T27) -> 0 | Y27: °C | Z27: Hotel geschlossen
A28: KW | B28: =SUM(B20+1) -> 8 | C28: =SUM(C21:C27) -> 0 | D28: =SUM(D21:D27) -> 0 | E28: =SUM(E21:E27) -> 0 | F28: =SUM(F21:F27) -> 0 | G28: =SUM(G21:G27) -> 0 | H28: =SUM(H21:H27) -> 0 | I28: =SUM(I21:I27) -> 0 | J28: =SUM(J21:J27) -> 0 | ... V28: =SUM(V21:V27) -> 0 | W28: Ø Temp | X28: =SUM(X21:X27)/7 -> 0 | Y28: °C | Z28: Hotel geschlossen
A29: =SUM(A27+1) -> 22 | B29: Mo | Q29: =SUM(C29+E29+G29+I29+K29+M29+O29) -> 0 | R29: =SUM(D29+F29+H29+J29+L29+N29+P29) -> 0 | U29: =SUM(Q29+S29) -> 0 | V29: =SUM(R29+T29) -> 0 | Y29: °C | Z29: Hotel geschlossen
A30: =SUM(A29+1) -> 23 | B30: Di | Q30: =SUM(C30+E30+G30+I30+K30+M30+O30) -> 0 | R30: =SUM(D30+F30+H30+J30+L30+N30+P30) -> 0 | U30: =SUM(Q30+S30) -> 0 | V30: =SUM(R30+T30) -> 0 | Y30: °C | Z30: Hotel geschlossen
A31: =SUM(A30+1) -> 24 | B31: Mi | Q31: =SUM(C31+E31+G31+I31+K31+M31+O31) -> 0 | R31: =SUM(D31+F31+H31+J31+L31+N31+P31) -> 0 | U31: =SUM(Q31+S31) -> 0 | V31: =SUM(R31+T31) -> 0 | Y31: °C | Z31: Hotel geschlossen
A32: =SUM(A31+1) -> 25 | B32: Do | Q32: =SUM(C32+E32+G32+I32+K32+M32+O32) -> 0 | R32: =SUM(D32+F32+H32+J32+L32+N32+P32) -> 0 | U32: =SUM(Q32+S32) -> 0 | V32: =SUM(R32+T32) -> 0 | Y32: °C | Z32: Hotel geschlossen
A33: =SUM(A32+1) -> 26 | B33: Fr | Q33: =SUM(C33+E33+G33+I33+K33+M33+O33) -> 0 | R33: =SUM(D33+F33+H33+J33+L33+N33+P33) -> 0 | U33: =SUM(Q33+S33) -> 0 | V33: =SUM(R33+T33) -> 0 | Y33: °C | Z33: Hotel geschlossen
A34: =SUM(A33+1) -> 27 | B34: Sa | Q34: =SUM(C34+E34+G34+I34+K34+M34+O34) -> 0 | R34: =SUM(D34+F34+H34+J34+L34+N34+P34) -> 0 | U34: =SUM(Q34+S34) -> 0 | V34: =SUM(R34+T34) -> 0 | Y34: °C | Z34: Hotel geschlossen
A35: =SUM(A34+1) -> 28 | B35: So | O35: -175.68 | Q35: =SUM(C35+E35+G35+I35+K35+M35+O35) -> -175.68 | R35: =SUM(D35+F35+H35+J35+L35+N35+P35) -> 0 | U35: =SUM(Q35+S35) -> -175.68 | V35: =SUM(R35+T35) -> 0 | Y35: °C | Z35: Hotel geschlossen
A36: KW | B36: =SUM(B28+1) -> 9 | C36: =SUM(C33:C35) -> 0 | D36: =SUM(D33:D35) -> 0 | E36: =SUM(E33:E35) -> 0 | F36: =SUM(F33:F35) -> 0 | G36: =SUM(G33:G35) -> 0 | H36: =SUM(H33:H35) -> 0 | I36: =SUM(I33:I35) -> 0 | J36: =SUM(J33:J35) -> 0 | ... V36: =SUM(V33:V35) -> 0 | W36: Ø Temp | X36: =SUM(X29:X35)/7 -> 0 | Y36: °C | Z36: Hotel geschlossen
A37: Umsatz kumuliert | C37: =SUM(C12+C20+C28+C36) -> 6376.7 | D37: =SUM(D12+D20+D28+D36) -> 7000 | E37: =SUM(E12+E20+E28+E36) -> 0 | F37: =SUM(F12+F20+F28+F36) -> 999.99998 | G37: =SUM(G12+G20+G28+G36) -> 0 | H37: =SUM(H12+H20+H28+H36) -> 999.99998 | I37: =SUM(I12+I20+I28+I36) -> 0 | J37: =SUM(J12+J20+J28+J36) -> 0 | ... V37: =SUM(V12+V20+V28+V36) -> 22305 | W37: Umsatz kumuliert
A38: Umsatz Forecast | C38: =IF(MONTH($H$1)<>MONTH(TODAY()),C37,SUM(C5:C11,C13:C19,C21:C27,C29:C35)/DAY(TODAY())*DAY(DATE(YEAR($H$1),MONTH($H$1)+1,1)-1)) -> 6376.7 | D38: =IF(MONTH($H$1)<>MONTH(TODAY()),D37,SUM(D5:D11,D13:D19,D21:D27,D29:D35)/DAY(TODAY())*DAY(DATE(YEAR($H$1),MONTH($H$1)+1,1)-1)) -> 7000 | E38: =IF(MONTH($H$1)<>MONTH(TODAY()),E37,SUM(E5:E11,E13:E19,E21:E27,E29:E35)/DAY(TODAY())*DAY(DATE(YEAR($H$1),MONTH($H$1)+1,1)-1)) -> 0 | F38: =IF(MONTH($H$1)<>MONTH(TODAY()),F37,SUM(F5:F11,F13:F19,F21:F27,F29:F35)/DAY(TODAY())*DAY(DATE(YEAR($H$1),MONTH($H$1)+1,1)-1)) -> 999.99998 | G38: =IF(MONTH($H$1)<>MONTH(TODAY()),G37,SUM(G5:G11,G13:G19,G21:G27,G29:G35)/DAY(TODAY())*DAY(DATE(YEAR($H$1),MONTH($H$1)+1,1)-1)) -> 0 | H38: =IF(MONTH($H$1)<>MONTH(TODAY()),H37,SUM(H5:H11,H13:H19,H21:H27,H29:H35)/DAY(TODAY())*DAY(DATE(YEAR($H$1),MONTH($H$1)+1,1)-1)) -> 999.99998 | I38: =IF(MONTH($H$1)<>MONTH(TODAY()),I37,SUM(I5:I11,I13:I19,I21:I27,I29:I35)/DAY(TODAY())*DAY(DATE(YEAR($H$1),MONTH($H$1)+1,1)-1)) -> 0 | J38: =IF(MONTH($H$1)<>MONTH(TODAY()),J37,SUM(J5:J11,J13:J19,J21:J27,J29:J35)/DAY(TODAY())*DAY(DATE(YEAR($H$1),MONTH($H$1)+1,1)-1)) -> 0 | ... V38: =IF(MONTH($H$1)<>MONTH(TODAY()),V37,SUM(V5:V11,V13:V19,V21:V27,V29:V35)/DAY(TODAY())*DAY(DATE(YEAR($H$1),MONTH($H$1)+1,1)-1)) -> 22305 | W38: Umsatz Forecast
A39: Umsatz pro Tag | C39: =C37/28 -> 227.73929 | D39: =D37/28 -> 250 | E39: =E37/28 -> 0 | F39: =F37/28 -> 35.714285 | G39: =G37/28 -> 0 | H39: =H37/28 -> 35.714285 | I39: =I37/28 -> 0 | J39: =J37/28 -> 0 | ... V39: =V37/28 -> 796.60714 | W39: Budget pro Tag
A40: Diff. zu Budget | C40: =SUM(C37-D37) -> -623.3 | E40: =SUM(E37-F37) -> -999.99998 | G40: =SUM(G37-H37) -> -999.99998 | I40: =SUM(I37-J37) -> 0 | K40: =SUM(K37-L37) -> -3621.2 | M40: =SUM(M37-N37) -> -2697.3 | O40: =SUM(O37-P37) -> 2021.42 | Q40: =SUM(Q37-R37) -> -6920.3799 | S40: =SUM(S37-T37) -> 0 | U40: =SUM(U37-V37) -> -6920.3799
A41: Index | C41: =SUM(100/D37*C37) -> 91.095714 | E41: =SUM(100/F37*E37) -> 0 | G41: =SUM(100/H37*G37) -> 0 | I41: =SUM(100/J37*I37) -> #DIV/0! | K41: =SUM(100/L37*K37) -> 9.47 | M41: =SUM(100/N37*M37) -> 32.5675 | O41: =SUM(100/P37*O37) -> 138.10405 | Q41: =SUM(100/R37*Q37) -> 68.973863 | S41: =SUM(100/T37*S37) -> #DIV/0! | U41: =SUM(100/V37*U37) -> 68.973863

Sheet 03_21
A1: Tagesumsätze | H1: 44256
C3: Restaurant | E3: Terrasse | G3: Lounge | I3: Pavillon | K3: Bankett | M3: Seminar | O3: Hotel | Q3: TOTAL Gesamtbetrieb ohne Seebad | S3: Seebad | U3: TOTAL Gesamtbetrieb mit Seebad | W3: Info's
C4: IST | D4: Budget | E4: IST | F4: Budget | G4: IST | H4: Budget | I4: IST | J4: Budget | K4: IST | L4: Budget | M4: IST | N4: Budget | O4: IST | P4: Budget | Q4: IST | R4: Budget | S4: IST | T4: Budget | U4: IST | V4: Budget | W4: Wetter | X4: Temp. | Z4: Bemerkung
A5: 1 | B5: Mo | D5: 4516.129 | F5: 1129.0322 | H5: 483.87096 | L5: 967.74194 | N5: 645.16129 | P5: 947.74194 | Q5: =SUM(C5+E5+G5+I5+K5+M5+O5) -> 0 | R5: =SUM(D5+F5+H5+J5+L5+N5+P5) -> 8689.6774 | U5: =SUM(Q5+S5) -> 0 | V5: =SUM(R5+T5) -> 8689.6774 | Y5: °C | Z5: Hotel geschlossen
A6: =SUM(A5+1) -> 2 | B6: Di | D6: 4516.129 | F6: 1129.0322 | H6: 483.87096 | L6: 967.74194 | N6: 645.16129 | P6: 947.74194 | Q6: =SUM(C6+E6+G6+I6+K6+M6+O6) -> 0 | R6: =SUM(D6+F6+H6+J6+L6+N6+P6) -> 8689.6774 | U6: =SUM(Q6+S6) -> 0 | V6: =SUM(R6+T6) -> 8689.6774 | Y6: °C | Z6: Hotel geschlossen
A7: =SUM(A6+1) -> 3 | B7: Mi | D7: 4516.129 | F7: 1129.0322 | H7: 483.87096 | L7: 967.74194 | N7: 645.16129 | P7: 947.74194 | Q7: =SUM(C7+E7+G7+I7+K7+M7+O7) -> 0 | R7: =SUM(D7+F7+H7+J7+L7+N7+P7) -> 8689.6774 | U7: =SUM(Q7+S7) -> 0 | V7: =SUM(R7+T7) -> 8689.6774 | Y7: °C | Z7: Hotel geschlossen
A8: =SUM(A7+1) -> 4 | B8: Do | D8: 4516.129 | F8: 1129.0322 | H8: 483.87096 | L8: 967.74194 | N8: 645.16129 | P8: 947.74194 | Q8: =SUM(C8+E8+G8+I8+K8+M8+O8) -> 0 | R8: =SUM(D8+F8+H8+J8+L8+N8+P8) -> 8689.6774 | U8: =SUM(Q8+S8) -> 0 | V8: =SUM(R8+T8) -> 8689.6774 | Y8: °C | Z8: Hotel geschlossen
A9: =SUM(A8+1) -> 5 | B9: Fr | C9: 1655.5 | D9: 4516.129 | F9: 1129.0322 | H9: 483.87096 | L9: 967.74194 | N9: 645.16129 | O9: 2262.8 | P9: 947.74194 | Q9: =SUM(C9+E9+G9+I9+K9+M9+O9) -> 3918.3 | R9: =SUM(D9+F9+H9+J9+L9+N9+P9) -> 8689.6774 | U9: =SUM(Q9+S9) -> 3918.3 | V9: =SUM(R9+T9) -> 8689.6774 | W9: bewölkt | X9: 5 | Y9: °C
A10: =SUM(A9+1) -> 6 | B10: Sa | C10: 3281.2 | D10: 4516.129 | F10: 1129.0322 | H10: 483.87096 | K10: 864.7 | L10: 967.74194 | N10: 645.16129 | O10: 3815.8 | P10: 947.74194 | Q10: =SUM(C10+E10+G10+I10+K10+M10+O10) -> 7961.7 | R10: =SUM(D10+F10+H10+J10+L10+N10+P10) -> 8689.6774 | U10: =SUM(Q10+S10) -> 7961.7 | V10: =SUM(R10+T10) -> 8689.6774 | W10: bewölkt | X10: 8 | Y10: °C
A11: =SUM(A10+1) -> 7 | B11: So | C11: -118 | D11: 4516.129 | F11: 1129.0322 | H11: 483.87096 | L11: 967.74194 | N11: 645.16129 | O11: 487.9 | P11: 947.74194 | Q11: =SUM(C11+E11+G11+I11+K11+M11+O11) -> 369.9 | R11: =SUM(D11+F11+H11+J11+L11+N11+P11) -> 8689.6774 | U11: =SUM(Q11+S11) -> 369.9 | V11: =SUM(R11+T11) -> 8689.6774 | W11: ziemlich sonnig | X11: 10 | Y11: °C
A12: KW | B12: 10 | C12: =SUM(C5:C11) -> 4818.7 | D12: =SUM(D5:D11) -> 31612.903 | E12: =SUM(E5:E11) -> 0 | F12: =SUM(F5:F11) -> 7903.2258 | G12: =SUM(G5:G11) -> 0 | H12: =SUM(H5:H11) -> 3387.0967 | I12: =SUM(I5:I11) -> 0 | J12: =SUM(J5:J11) -> 0 | ... V12: =SUM(V5:V11) -> 60827.742 | W12: Ø Temp | X12: =SUM(X5:X11)/7 -> 3.2857143 | Y12: °C
A13: =SUM(A11+1) -> 8 | B13: Mo | C13: 416.7 | D13: 4516.129 | F13: 1129.0322 | H13: 483.87096 | L13: 967.74194 | N13: 645.16129 | O13: 683 | P13: 947.74194 | Q13: =SUM(C13+E13+G13+I13+K13+M13+O13) -> 1099.7 | R13: =SUM(D13+F13+H13+J13+L13+N13+P13) -> 8689.6774 | U13: =SUM(Q13+S13) -> 1099.7 | V13: =SUM(R13+T13) -> 8689.6774 | W13: ziemlich sonnig | X13: 5 | Y13: °C
A14: =SUM(A13+1) -> 9 | B14: Di | C14: 1371 | D14: 4516.129 | F14: 1129.0322 | H14: 483.87096 | L14: 967.74194 | N14: 645.16129 | O14: 2208.8 | P14: 947.74194 | Q14: =SUM(C14+E14+G14+I14+K14+M14+O14) -> 3579.8 | R14: =SUM(D14+F14+H14+J14+L14+N14+P14) -> 8689.6774 | U14: =SUM(Q14+S14) -> 3579.8 | V14: =SUM(R14+T14) -> 8689.6774 | W14: bewölkt | X14: 6 | Y14: °C
A15: =SUM(A14+1) -> 10 | B15: Mi | C15: 1484 | D15: 4516.129 | F15: 1129.0322 | H15: 483.87096 | L15: 967.74194 | N15: 645.16129 | O15: 2123.2 | P15: 947.74194 | Q15: =SUM(C15+E15+G15+I15+K15+M15+O15) -> 3607.2 | R15: =SUM(D15+F15+H15+J15+L15+N15+P15) -> 8689.6774 | U15: =SUM(Q15+S15) -> 3607.2 | V15: =SUM(R15+T15) -> 8689.6774 | W15: sonnig | X15: 8 | Y15: °C
A16: =SUM(A15+1) -> 11 | B16: Do | C16: 502.1 | D16: 4516.129 | F16: 1129.0322 | H16: 483.87096 | L16: 967.74194 | N16: 645.16129 | O16: 985.4 | P16: 947.74194 | Q16: =SUM(C16+E16+G16+I16+K16+M16+O16) -> 1487.5 | R16: =SUM(D16+F16+H16+J16+L16+N16+P16) -> 8689.6774 | U16: =SUM(Q16+S16) -> 1487.5 | V16: =SUM(R16+T16) -> 8689.6774 | W16: bewölkt | X16: 5 | Y16: °C
A17: =SUM(A16+1) -> 12 | B17: Fr | C17: 2236.4 | D17: 4516.129 | F17: 1129.0322 | H17: 483.87096 | K17: 1529.5 | L17: 967.74194 | N17: 645.16129 | O17: 3286.4 | P17: 947.74194 | Q17: =SUM(C17+E17+G17+I17+K17+M17+O17) -> 7052.3 | R17: =SUM(D17+F17+H17+J17+L17+N17+P17) -> 8689.6774 | U17: =SUM(Q17+S17) -> 7052.3 | V17: =SUM(R17+T17) -> 8689.6774 | W17: sonnig | X17: 6 | Y17: °C
A18: =SUM(A17+1) -> 13 | B18: Sa | C18: 3418 | D18: 4516.129 | F18: 1129.0322 | H18: 483.87096 | K18: 303 | L18: 967.74194 | N18: 645.16129 | O18: 4408.9 | P18: 947.74194 | Q18: =SUM(C18+E18+G18+I18+K18+M18+O18) -> 8129.9 | R18: =SUM(D18+F18+H18+J18+L18+N18+P18) -> 8689.6774 | U18: =SUM(Q18+S18) -> 8129.9 | V18: =SUM(R18+T18) -> 8689.6774 | W18: sonnig | X18: 12 | Y18: °C
A19: =SUM(A18+1) -> 14 | B19: So | C19: 645.8 | D19: 4516.129 | F19: 1129.0322 | H19: 483.87096 | L19: 967.74194 | N19: 645.16129 | O19: 1190.4 | P19: 947.74194 | Q19: =SUM(C19+E19+G19+I19+K19+M19+O19) -> 1836.2 | R19: =SUM(D19+F19+H19+J19+L19+N19+P19) -> 8689.6774 | U19: =SUM(Q19+S19) -> 1836.2 | V19: =SUM(R19+T19) -> 8689.6774 | W19: Schneeschauer | X19: 5 | Y19: °C
A20: KW | B20: =SUM(B12+1) -> 11 | C20: =SUM(C13:C19) -> 10074 | D20: =SUM(D13:D19) -> 31612.903 | E20: =SUM(E13:E19) -> 0 | F20: =SUM(F13:F19) -> 7903.2258 | G20: =SUM(G13:G19) -> 0 | H20: =SUM(H13:H19) -> 3387.0967 | I20: =SUM(I13:I19) -> 0 | J20: =SUM(J13:J19) -> 0 | ... V20: =SUM(V13:V19) -> 60827.742 | W20: Ø Temp | X20: =SUM(X13:X19)/7 -> 6.7142857 | Y20: °C
A21: =SUM(A19+1) -> 15 | B21: Mo | C21: 707.4 | D21: 4516.129 | F21: 1129.0322 | H21: 483.87096 | K21: 48 | L21: 967.74194 | M21: 1995.8 | N21: 645.16129 | O21: 1791.8 | P21: 947.74194 | Q21: =SUM(C21+E21+G21+I21+K21+M21+O21) -> 4543 | R21: =SUM(D21+F21+H21+J21+L21+N21+P21) -> 8689.6774 | U21: =SUM(Q21+S21) -> 4543 | V21: =SUM(R21+T21) -> 8689.6774 | W21: Schneeschauer | X21: 5 | Y21: °C
A22: =SUM(A21+1) -> 16 | B22: Di | C22: 786.5 | D22: 4516.129 | E22: 0 | F22: 1129.0322 | G22: 0 | H22: 483.87096 | I22: 0 | K22: 0 | L22: 967.74194 | M22: 3140.6 | N22: 645.16129 | O22: 3612 | P22: 947.74194 | Q22: =SUM(C22+E22+G22+I22+K22+M22+O22) -> 7539.1 | R22: =SUM(D22+F22+H22+J22+L22+N22+P22) -> 8689.6774 | U22: =SUM(Q22+S22) -> 7539.1 | V22: =SUM(R22+T22) -> 8689.6774 | W22: Schneeschauer | X22: 5 | Y22: °C
A23: =SUM(A22+1) -> 17 | B23: Mi | C23: 644.2 | D23: 4516.129 | E23: 0 | F23: 1129.0322 | G23: 0 | H23: 483.87096 | I23: 0 | K23: 0 | L23: 967.74194 | M23: 1519.2 | N23: 645.16129 | O23: 1683.3 | P23: 947.74194 | Q23: =SUM(C23+E23+G23+I23+K23+M23+O23) -> 3846.7 | R23: =SUM(D23+F23+H23+J23+L23+N23+P23) -> 8689.6774 | U23: =SUM(Q23+S23) -> 3846.7 | V23: =SUM(R23+T23) -> 8689.6774 | W23: Schneeschauer | X23: 3 | Y23: °C
A24: =SUM(A23+1) -> 18 | B24: Do | C24: 117.1 | D24: 4516.129 | E24: 0 | F24: 1129.0322 | G24: 0 | H24: 483.87096 | I24: 0 | K24: 0 | L24: 967.74194 | M24: 0 | N24: 645.16129 | O24: 529.2 | P24: 947.74194 | Q24: =SUM(C24+E24+G24+I24+K24+M24+O24) -> 646.3 | R24: =SUM(D24+F24+H24+J24+L24+N24+P24) -> 8689.6774 | U24: =SUM(Q24+S24) -> 646.3 | V24: =SUM(R24+T24) -> 8689.6774 | W24: Schneeschauer | X24: 3 | Y24: °C
A25: =SUM(A24+1) -> 19 | B25: Fr | C25: 2053.7 | D25: 4516.129 | E25: 0 | F25: 1129.0322 | G25: 0 | H25: 483.87096 | I25: 0 | K25: 0 | L25: 967.74194 | M25: 0 | N25: 645.16129 | O25: 2768.2 | P25: 947.74194 | Q25: =SUM(C25+E25+G25+I25+K25+M25+O25) -> 4821.9 | R25: =SUM(D25+F25+H25+J25+L25+N25+P25) -> 8689.6774 | U25: =SUM(Q25+S25) -> 4821.9 | V25: =SUM(R25+T25) -> 8689.6774 | W25: sonnig | X25: 3 | Y25: °C
A26: =SUM(A25+1) -> 20 | B26: Sa | C26: 3643.7 | D26: 4516.129 | E26: 0 | F26: 1129.0322 | G26: 31.8 | H26: 483.87096 | I26: 0 | K26: 606.7 | L26: 967.74194 | M26: 0 | N26: 645.16129 | O26: 5595.8 | P26: 947.74194 | Q26: =SUM(C26+E26+G26+I26+K26+M26+O26) -> 9878 | R26: =SUM(D26+F26+H26+J26+L26+N26+P26) -> 8689.6774 | U26: =SUM(Q26+S26) -> 9878 | V26: =SUM(R26+T26) -> 8689.6774 | W26: sonnig | X26: 3 | Y26: °C
A27: =SUM(A26+1) -> 21 | B27: So | C27: 288.8 | D27: 4516.129 | E27: 0 | F27: 1129.0322 | G27: 0 | H27: 483.87096 | I27: 0 | K27: 0 | L27: 967.74194 | M27: 0 | N27: 645.16129 | O27: 1043.3 | P27: 947.74194 | Q27: =SUM(C27+E27+G27+I27+K27+M27+O27) -> 1332.1 | R27: =SUM(D27+F27+H27+J27+L27+N27+P27) -> 8689.6774 | U27: =SUM(Q27+S27) -> 1332.1 | V27: =SUM(R27+T27) -> 8689.6774 | W27: bewölkt | X27: 5 | Y27: °C
A28: KW | B28: =SUM(B20+1) -> 12 | C28: =SUM(C21:C27) -> 8241.4 | D28: =SUM(D21:D27) -> 31612.903 | E28: =SUM(E21:E27) -> 0 | F28: =SUM(F21:F27) -> 7903.2258 | G28: =SUM(G21:G27) -> 31.8 | H28: =SUM(H21:H27) -> 3387.0967 | I28: =SUM(I21:I27) -> 0 | J28: =SUM(J21:J27) -> 0 | ... V28: =SUM(V21:V27) -> 60827.742 | W28: Ø Temp | X28: =SUM(X21:X27)/7 -> 3.8571429 | Y28: °C
A29: =SUM(A27+1) -> 22 | B29: Mo | C29: 1266.7 | D29: 4516.129 | E29: 0 | F29: 1129.0322 | G29: 0 | H29: 483.87096 | I29: 0 | K29: 0 | L29: 967.74194 | M29: 2916.4 | N29: 645.16129 | O29: 1837.45 | P29: 947.74194 | Q29: =SUM(C29+E29+G29+I29+K29+M29+O29) -> 6020.55 | R29: =SUM(D29+F29+H29+J29+L29+N29+P29) -> 8689.6774 | U29: =SUM(Q29+S29) -> 6020.55 | V29: =SUM(R29+T29) -> 8689.6774 | W29: bewölkt | X29: 5 | Y29: °C
A30: =SUM(A29+1) -> 23 | B30: Di | C30: 1362.3 | D30: 4516.129 | E30: 22.7 | F30: 1129.0322 | G30: 0 | H30: 483.87096 | I30: 0 | K30: 0 | L30: 967.74194 | M30: 991.8 | N30: 645.16129 | O30: 2304.8 | P30: 947.74194 | Q30: =SUM(C30+E30+G30+I30+K30+M30+O30) -> 4681.6 | R30: =SUM(D30+F30+H30+J30+L30+N30+P30) -> 8689.6774 | U30: =SUM(Q30+S30) -> 4681.6 | V30: =SUM(R30+T30) -> 8689.6774 | W30: sonnig | X30: 10 | Y30: °C
A31: =SUM(A30+1) -> 24 | B31: Mi | C31: 508.5 | D31: 4516.129 | E31: 0 | F31: 1129.0322 | G31: 0 | H31: 483.87096 | I31: 0 | K31: 0 | L31: 967.74194 | M31: 13.5 | N31: 645.16129 | O31: 1268.4 | P31: 947.74194 | Q31: =SUM(C31+E31+G31+I31+K31+M31+O31) -> 1790.4 | R31: =SUM(D31+F31+H31+J31+L31+N31+P31) -> 8689.6774 | U31: =SUM(Q31+S31) -> 1790.4 | V31: =SUM(R31+T31) -> 8689.6774 | W31: sonnig | X31: 16 | Y31: °C
A32: =SUM(A31+1) -> 25 | B32: Do | C32: 1632.2 | D32: 4516.129 | E32: 0 | F32: 1129.0322 | G32: 0 | H32: 483.87096 | I32: 0 | K32: 23 | L32: 967.74194 | M32: 0 | N32: 645.16129 | O32: 2897.2 | P32: 947.74194 | Q32: =SUM(C32+E32+G32+I32+K32+M32+O32) -> 4552.4 | R32: =SUM(D32+F32+H32+J32+L32+N32+P32) -> 8689.6774 | U32: =SUM(Q32+S32) -> 4552.4 | V32: =SUM(R32+T32) -> 8689.6774 | W32: sonnig | X32: 16 | Y32: °C
A33: =SUM(A32+1) -> 26 | B33: Fr | C33: 2343.8 | D33: 4516.129 | E33: 15.2 | F33: 1129.0322 | G33: 21.6 | H33: 483.87096 | I33: 0 | K33: 2987.1 | L33: 967.74194 | M33: 42 | N33: 645.16129 | O33: 5112.2 | P33: 947.74194 | Q33: =SUM(C33+E33+G33+I33+K33+M33+O33) -> 10521.9 | R33: =SUM(D33+F33+H33+J33+L33+N33+P33) -> 8689.6774 | U33: =SUM(Q33+S33) -> 10521.9 | V33: =SUM(R33+T33) -> 8689.6774 | W33: sonnig | X33: 16 | Y33: °C
A34: =SUM(A33+1) -> 27 | B34: Sa | C34: 4511.2 | D34: 4516.129 | E34: 61.5 | F34: 1129.0322 | G34: 17 | H34: 483.87096 | I34: 0 | K34: 540.3 | L34: 967.74194 | M34: 0 | N34: 645.16129 | O34: 5519.2 | P34: 947.74194 | Q34: =SUM(C34+E34+G34+I34+K34+M34+O34) -> 10649.2 | R34: =SUM(D34+F34+H34+J34+L34+N34+P34) -> 8689.6774 | U34: =SUM(Q34+S34) -> 10649.2 | V34: =SUM(R34+T34) -> 8689.6774 | W34: wechselnd bewölkt | X34: 10 | Y34: °C
A35: =SUM(A34+1) -> 28 | B35: So | C35: 1932.6 | D35: 4516.129 | E35: 0 | F35: 1129.0322 | G35: 198.9 | H35: 483.87096 | I35: 0 | K35: 0 | L35: 967.74194 | M35: 0 | N35: 645.16129 | O35: 2595.8 | P35: 947.74194 | Q35: =SUM(C35+E35+G35+I35+K35+M35+O35) -> 4727.3 | R35: =SUM(D35+F35+H35+J35+L35+N35+P35) -> 8689.6774 | U35: =SUM(Q35+S35) -> 4727.3 | V35: =SUM(R35+T35) -> 8689.6774 | W35: sonnig | X35: 15 | Y35: °C
A36: KW | B36: =SUM(B28+1) -> 13 | C36: =SUM(C29:C35) -> 13557.3 | D36: =SUM(D29:D35) -> 31612.903 | E36: =SUM(E29:E35) -> 99.4 | F36: =SUM(F29:F35) -> 7903.2258 | G36: =SUM(G29:G35) -> 237.5 | H36: =SUM(H29:H35) -> 3387.0967 | I36: =SUM(I29:I35) -> 0 | J36: =SUM(J29:J35) -> 0 | ... V36: =SUM(V29:V35) -> 60827.742 | W36: Ø Temp | X36: =SUM(X29:X35)/7 -> 12.571429 | Y36: °C
A37: =SUM(A35+1) -> 29 | B37: Mo | C37: 1841.6 | D37: 4516.129 | E37: 27.1 | F37: 1129.0322 | G37: 27.9 | H37: 483.87096 | I37: 0 | K37: 0 | L37: 967.74194 | M37: 0 | N37: 645.16129 | O37: 3271.7 | P37: 947.74194 | Q37: =SUM(C37+E37+G37+I37+K37+M37+O37) -> 5168.3 | R37: =SUM(D37+F37+H37+J37+L37+N37+P37) -> 8689.6774 | U37: =SUM(Q37+S37) -> 5168.3 | V37: =SUM(R37+T37) -> 8689.6774 | W37: sonnig | X37: 16 | Y37: °C
A38: =SUM(A37+1) -> 30 | B38: Di | C38: 1556 | D38: 4516.129 | E38: 26.8 | F38: 1129.0322 | G38: 27.2 | H38: 483.87096 | I38: 0 | K38: 0 | L38: 967.74194 | M38: 0 | N38: 645.16129 | O38: 2588.5 | P38: 947.74194 | Q38: =SUM(C38+E38+G38+I38+K38+M38+O38) -> 4198.5 | R38: =SUM(D38+F38+H38+J38+L38+N38+P38) -> 8689.6774 | U38: =SUM(Q38+S38) -> 4198.5 | V38: =SUM(R38+T38) -> 8689.6774 | W38: sonnig | X38: 18 | Y38: °C
A39: =SUM(A38+1) -> 31 | B39: Mi | C39: 2210.1 | D39: 4516.129 | E39: 0 | F39: 1129.0322 | G39: 157.2 | H39: 483.87096 | I39: 0 | K39: 147.2 | L39: 967.74194 | M39: 0 | N39: 645.16129 | O39: 3747.8 | P39: 947.74194 | Q39: =SUM(C39+E39+G39+I39+K39+M39+O39) -> 6262.3 | R39: =SUM(D39+F39+H39+J39+L39+N39+P39) -> 8689.6774 | U39: =SUM(Q39+S39) -> 6262.3 | V39: =SUM(R39+T39) -> 8689.6774 | W39: sonnig | X39: 23 | Y39: °C
A40: KW | B40: =SUM(B36+1) -> 14 | C40: =SUM(C37:C39) -> 5607.7 | D40: =SUM(D37:D39) -> 13548.387 | E40: =SUM(E37:E39) -> 53.9 | F40: =SUM(F37:F39) -> 3387.0967 | G40: =SUM(G37:G39) -> 212.3 | H40: =SUM(H37:H39) -> 1451.6129 | I40: =SUM(I37:I39) -> 0 | J40: =SUM(J37:J39) -> 0 | ... U40: =SUM(U37:U39) -> 15629.1 | V40: =SUM(V33:V35) -> 26069.032 | W40: Ø Temp | X40: =SUM(X37:X39)/3 -> 19 | Y40: °C
A41: Umsatz kumuliert | C41: =SUM(C12+C20+C28+C36+C40) -> 42299.1 | D41: =SUM(D12+D20+D28+D36+D40) -> 140000 | E41: =SUM(E12+E20+E28+E36+E40) -> 153.3 | F41: =SUM(F12+F20+F28+F36+F40) -> 35000 | G41: =SUM(G12+G20+G28+G36+G40) -> 481.6 | H41: =SUM(H12+H20+H28+H36+H40) -> 15000 | I41: =SUM(I12+I20+I28+I40) -> 0 | J41: =SUM(J12+J20+J28+J40) -> 0 | K41: =SUM(K12+K20+K28+K36+K40) -> 7049.5 | L41: =SUM(L12+L20+L28+L36+L40) -> 30000 | M41: =SUM(M12+M20+M28+M36+M40) -> 10619.3 | N41: =SUM(N12+N20+N28+N36+N40) -> 20000 | O41: =SUM(O12+O20+O28+O36+O40) -> 69619.25 | P41: =SUM(P12+P20+P28+P36+P40) -> 29380 | Q41: =SUM(Q12+Q20+Q28+Q36+Q40) -> 130222.05 | R41: =SUM(R12+R20+R28+R36+R40) -> 269380 | ... V41: =SUM(V12+V20+V28+V36+V40) -> 269380 | W41: Umsatz kumuliert
A42: Umsatz Forecast | C42: =IF(MONTH($H$1)<>MONTH(TODAY()),C41,SUM(C5:C11,C13:C19,C21:C27,C29:C35,C37:C39)/DAY(TODAY())*DAY(DATE(YEAR($H$1),MONTH($H$1)+1,1)-1)) -> 42299.1 | D42: =IF(MONTH($H$1)<>MONTH(TODAY()),D41,SUM(D5:D11,D13:D19,D21:D27,D29:D35,D37:D39)/DAY(TODAY())*DAY(DATE(YEAR($H$1),MONTH($H$1)+1,1)-1)) -> 140000 | E42: =IF(MONTH($H$1)<>MONTH(TODAY()),E41,SUM(E5:E11,E13:E19,E21:E27,E29:E35,E37:E39)/DAY(TODAY())*DAY(DATE(YEAR($H$1),MONTH($H$1)+1,1)-1)) -> 153.3 | F42: =IF(MONTH($H$1)<>MONTH(TODAY()),F41,SUM(F5:F11,F13:F19,F21:F27,F29:F35,F37:F39)/DAY(TODAY())*DAY(DATE(YEAR($H$1),MONTH($H$1)+1,1)-1)) -> 35000 | G42: =IF(MONTH($H$1)<>MONTH(TODAY()),G41,SUM(G5:G11,G13:G19,G21:G27,G29:G35,G37:G39)/DAY(TODAY())*DAY(DATE(YEAR($H$1),MONTH($H$1)+1,1)-1)) -> 481.6 | H42: =IF(MONTH($H$1)<>MONTH(TODAY()),H41,SUM(H5:H11,H13:H19,H21:H27,H29:H35,H37:H39)/DAY(TODAY())*DAY(DATE(YEAR($H$1),MONTH($H$1)+1,1)-1)) -> 15000 | I42: =IF(MONTH($H$1)<>MONTH(TODAY()),I41,SUM(I5:I11,I13:I19,I21:I27,I29:I35,I37:I39)/DAY(TODAY())*DAY(DATE(YEAR($H$1),MONTH($H$1)+1,1)-1)) -> 0 | J42: =IF(MONTH($H$1)<>MONTH(TODAY()),J41,SUM(J5:J11,J13:J19,J21:J27,J29:J35,J37:J39)/DAY(TODAY())*DAY(DATE(YEAR($H$1),MONTH($H$1)+1,1)-1)) -> 0 | ... V42: =IF(MONTH($H$1)<>MONTH(TODAY()),V41,SUM(V5:V11,V13:V19,V21:V27,V29:V35,V37:V39)/DAY(TODAY())*DAY(DATE(YEAR($H$1),MONTH($H$1)+1,1)-1)) -> 269380 | W42: Umsatz Forecast
A43: Umsatz pro Tag | C43: =C41/31 -> 1364.4871 | D43: =D41/31 -> 4516.129 | E43: =E41/31 -> 4.9451613 | F43: =F41/31 -> 1129.0322 | G43: =G41/31 -> 15.535484 | H43: =H41/31 -> 483.87096 | I43: =I41/31 -> 0 | J43: =J41/31 -> 0 | ... V43: =V41/31 -> 8689.6774 | W43: Budget pro Tag
A44: Diff. zu Budget | C44: =SUM(C41-D41) -> -97700.9 | E44: =SUM(E41-F41) -> -34846.7 | G44: =SUM(G41-H41) -> -14518.4 | I44: =SUM(I41-J41) -> 0 | K44: =SUM(K41-L41) -> -22950.5 | M44: =SUM(M41-N41) -> -9380.7 | O44: =SUM(O41-P41) -> 40239.25 | Q44: =SUM(Q41-R41) -> -139157.95 | S44: =SUM(S41-T41) -> 0 | U44: =SUM(U41-V41) -> -139157.95
A45: Index | C45: =SUM(100/D41*C41) -> 30.213643 | E45: =SUM(100/F41*E41) -> 0.438 | G45: =SUM(100/H41*G41) -> 3.2106667 | I45: =SUM(100/J41*I41) -> #DIV/0! | K45: =SUM(100/L41*K41) -> 23.498333 | M45: =SUM(100/N41*M41) -> 53.0965 | O45: =SUM(100/P41*O41) -> 236.96137 | Q45: =SUM(100/R41*Q41) -> 48.341395 | S45: =SUM(100/T41*S41) -> #DIV/0! | U45: =SUM(100/V41*U41) -> 48.341395

Sheet 04_21
A1: Tagesumsätze | H1: 44287
C3: Restaurant | E3: Terrasse | G3: Lounge | I3: Pavillon | K3: Bankett | M3: Seminar | O3: Hotel | Q3: TOTAL Gesamtbetrieb ohne Seebad | S3: Seebad | U3: TOTAL Gesamtbetrieb mit Seebad | W3: Info's
C4: IST | D4: Budget | E4: IST | F4: Budget | G4: IST | H4: Budget | I4: IST | J4: Budget | K4: IST | L4: Budget | M4: IST | N4: Budget | O4: IST | P4: Budget | Q4: IST | R4: Budget | S4: IST | T4: Budget | U4: IST | V4: Budget | W4: Wetter | X4: Temp. | Z4: Bemerkung
A5: 1 | B5: Do | C5: 2514.6 | D5: 5000 | E5: 14 | F5: 2666.6667 | G5: 111.6 | H5: 833.33333 | I5: 0 | K5: 0 | L5: 2166.6667 | M5: 0 | N5: 1000 | O5: 4668.5 | P5: 1958.3333 | Q5: =SUM(C5+E5+G5+I5+K5+M5+O5) -> 7308.7 | R5: =SUM(D5+F5+H5+J5+L5+N5+P5) -> 13625 | S5: 0 | T5: 66.66666 | U5: =SUM(Q5+S5) -> 7308.7 | V5: =SUM(R5+T5) -> 13691.667 | W5: sonnig | X5: 22 | Y5: °C
A6: =SUM(A5+1) -> 2 | B6: Fr | C6: 3415 | D6: 5000 | E6: 15 | F6: 2666.6667 | G6: 329.9 | H6: 833.33333 | I6: 0 | K6: 982.3 | L6: 2166.6667 | M6: 0 | N6: 1000 | O6: 5809.8 | P6: 1958.3333 | Q6: =SUM(C6+E6+G6+I6+K6+M6+O6) -> 10552 | R6: =SUM(D6+F6+H6+J6+L6+N6+P6) -> 13625 | S6: 0 | T6: 66.66666 | U6: =SUM(Q6+S6) -> 10552 | V6: =SUM(R6+T6) -> 13691.667 | W6: sonnig | X6: 22 | Y6: °C | Z6: Karfreitag
A7: =SUM(A6+1) -> 3 | B7: Sa | C7: 4237.8 | D7: 5000 | E7: 0 | F7: 2666.6667 | G7: 26 | H7: 833.33333 | I7: 0 | K7: 820.7 | L7: 2166.6667 | M7: 0 | N7: 1000 | O7: 5888.6 | P7: 1958.3333 | Q7: =SUM(C7+E7+G7+I7+K7+M7+O7) -> 10973.1 | R7: =SUM(D7+F7+H7+J7+L7+N7+P7) -> 13625 | S7: 0 | T7: 66.66666 | U7: =SUM(Q7+S7) -> 10973.1 | V7: =SUM(R7+T7) -> 13691.667 | W7: bewölkt | X7: 10 | Y7: °C
A8: =SUM(A7+1) -> 4 | B8: So | C8: 2594.1 | D8: 5000 | E8: 0 | F8: 2666.6667 | G8: 303.4 | H8: 833.33333 | I8: 0 | K8: 552.8 | L8: 2166.6667 | M8: 0 | N8: 1000 | O8: 4898 | P8: 1958.3333 | Q8: =SUM(C8+E8+G8+I8+K8+M8+O8) -> 8348.3 | R8: =SUM(D8+F8+H8+J8+L8+N8+P8) -> 13625 | S8: 0 | T8: 66.66666 | U8: =SUM(Q8+S8) -> 8348.3 | V8: =SUM(R8+T8) -> 13691.667 | W8: sonnig | X8: 18 | Y8: °C | Z8: Ostern
A9: KW | B9: 14 | C9: =SUM(C5:C8) -> 12761.5 | D9: =SUM(D5:D8) -> 20000 | E9: =SUM(E5:E8) -> 29 | F9: =SUM(F5:F8) -> 10666.667 | G9: =SUM(G5:G8) -> 770.9 | H9: =SUM(H5:H8) -> 3333.3333 | I9: =SUM(I5:I8) -> 0 | J9: =SUM(J5:J8) -> 0 | ... V9: =SUM(V5:V8) -> 54766.667 | W9: Ø Temp | X9: =SUM(X5:X8)/4 -> 18 | Y9: °C
A10: =SUM(A8+1) -> 5 | B10: Mo | C10: 839.5 | D10: 5000 | E10: 0 | F10: 2666.6667 | G10: 0 | H10: 833.33333 | I10: 0 | K10: 21 | L10: 2166.6667 | M10: 0 | N10: 1000 | O10: 1330.5 | P10: 1958.3333 | Q10: =SUM(C10+E10+G10+I10+K10+M10+O10) -> 2191 | R10: =SUM(D10+F10+H10+J10+L10+N10+P10) -> 13625 | S10: 0 | T10: 66.66666 | U10: =SUM(Q10+S10) -> 2191 | V10: =SUM(R10+T10) -> 13691.667 | W10: Schneeschauer | X10: 2 | Y10: °C | Z10: Ostermontag
A11: =SUM(A10+1) -> 6 | B11: Di | C11: 1141 | D11: 5000 | E11: 0 | F11: 2666.6667 | G11: 0 | H11: 833.33333 | I11: 0 | K11: 0 | L11: 2166.6667 | M11: 0 | N11: 1000 | O11: 2662.4 | P11: 1958.3333 | Q11: =SUM(C11+E11+G11+I11+K11+M11+O11) -> 3803.4 | R11: =SUM(D11+F11+H11+J11+L11+N11+P11) -> 13625 | S11: 0 | T11: 66.66666 | U11: =SUM(Q11+S11) -> 3803.4 | V11: =SUM(R11+T11) -> 13691.667 | W11: Schneeschauer | X11: 1 | Y11: °C
A12: =SUM(A11+1) -> 7 | B12: Mi | C12: 2290.6 | D12: 5000 | E12: 0 | F12: 2666.6667 | G12: 0 | H12: 833.33333 | I12: 0 | K12: 862 | L12: 2166.6667 | M12: 0 | N12: 1000 | O12: 5101.8 | P12: 1958.3333 | Q12: =SUM(C12+E12+G12+I12+K12+M12+O12) -> 8254.4 | R12: =SUM(D12+F12+H12+J12+L12+N12+P12) -> 13625 | S12: 0 | T12: 66.66666 | U12: =SUM(Q12+S12) -> 8254.4 | V12: =SUM(R12+T12) -> 13691.667 | W12: Schneeschauer | X12: 1 | Y12: °C
A13: =SUM(A12+1) -> 8 | B13: Do | C13: 2349.8 | D13: 5000 | E13: 0 | F13: 2666.6667 | G13: 83.8 | H13: 833.33333 | I13: 0 | K13: 647.4 | L13: 2166.6667 | M13: 0 | N13: 1000 | O13: 4965.6 | P13: 1958.3333 | Q13: =SUM(C13+E13+G13+I13+K13+M13+O13) -> 8046.6 | R13: =SUM(D13+F13+H13+J13+L13+N13+P13) -> 13625 | S13: 0 | T13: 66.66666 | U13: =SUM(Q13+S13) -> 8046.6 | V13: =SUM(R13+T13) -> 13691.667 | W13: sonnig | X13: 9 | Y13: °C
A14: =SUM(A13+1) -> 9 | B14: Fr | C14: 2336.8 | D14: 5000 | E14: 0 | F14: 2666.6667 | G14: 0 | H14: 833.33333 | I14: 0 | K14: 374.4 | L14: 2166.6667 | M14: 1661.8 | N14: 1000 | O14: 4431.7 | P14: 1958.3333 | Q14: =SUM(C14+E14+G14+I14+K14+M14+O14) -> 8804.7 | R14: =SUM(D14+F14+H14+J14+L14+N14+P14) -> 13625 | S14: 0 | T14: 66.66666 | U14: =SUM(Q14+S14) -> 8804.7 | V14: =SUM(R14+T14) -> 13691.667 | W14: leicht bewölkt | X14: 10 | Y14: °C
A15: =SUM(A14+1) -> 10 | B15: Sa | C15: 4317.8 | D15: 5000 | E15: 184 | F15: 2666.6667 | G15: 127.1 | H15: 833.33333 | I15: 0 | K15: 616.2 | L15: 2166.6667 | M15: 441.9 | N15: 1000 | O15: 6164.7 | P15: 1958.3333 | Q15: =SUM(C15+E15+G15+I15+K15+M15+O15) -> 11851.7 | R15: =SUM(D15+F15+H15+J15+L15+N15+P15) -> 13625 | S15: 0 | T15: 66.66666 | U15: =SUM(Q15+S15) -> 11851.7 | V15: =SUM(R15+T15) -> 13691.667 | W15: bewölkt | X15: 8 | Y15: °C
A16: =SUM(A15+1) -> 11 | B16: So | C16: 1135.8 | D16: 5000 | E16: 0 | F16: 2666.6667 | G16: 0 | H16: 833.33333 | I16: 0 | K16: 0 | L16: 2166.6667 | M16: 0 | N16: 1000 | O16: 1420.5 | P16: 1958.3333 | Q16: =SUM(C16+E16+G16+I16+K16+M16+O16) -> 2556.3 | R16: =SUM(D16+F16+H16+J16+L16+N16+P16) -> 13625 | S16: 0 | T16: 66.66666 | U16: =SUM(Q16+S16) -> 2556.3 | V16: =SUM(R16+T16) -> 13691.667 | W16: sonnig | X16: 10 | Y16: °C
A17: KW | B17: =SUM(B9+1) -> 15 | C17: =SUM(C10:C16) -> 14411.3 | D17: =SUM(D10:D16) -> 35000 | E17: =SUM(E10:E16) -> 184 | F17: =SUM(F10:F16) -> 18666.667 | G17: =SUM(G10:G16) -> 210.9 | H17: =SUM(H10:H16) -> 5833.3333 | I17: =SUM(I10:I16) -> 0 | J17: =SUM(J10:J16) -> 0 | ... V17: =SUM(V10:V16) -> 95841.666 | W17: Ø Temp | X17: =SUM(X10:X16)/7 -> 5.8571429 | Y17: °C
A18: =SUM(A16+1) -> 12 | B18: Mo | C18: 968.8 | D18: 5000 | E18: 0 | F18: 2666.6667 | G18: 0 | H18: 833.33333 | I18: 0 | K18: 0 | L18: 2166.6667 | M18: 1271 | N18: 1000 | O18: 2121.3 | P18: 1958.3333 | Q18: =SUM(C18+E18+G18+I18+K18+M18+O18) -> 4361.1 | R18: =SUM(D18+F18+H18+J18+L18+N18+P18) -> 13625 | S18: 0 | T18: 66.66666 | U18: =SUM(Q18+S18) -> 4361.1 | V18: =SUM(R18+T18) -> 13691.667 | W18: leicht bewölkt | X18: 10 | Y18: °C
A19: =SUM(A18+1) -> 13 | B19: Di | C19: 1512.6 | D19: 5000 | E19: 0 | F19: 2666.6667 | G19: 0 | H19: 833.33333 | I19: 0 | K19: 0 | L19: 2166.6667 | M19: 5314.6 | N19: 1000 | O19: 2237.3 | P19: 1958.3333 | Q19: =SUM(C19+E19+G19+I19+K19+M19+O19) -> 9064.5 | R19: =SUM(D19+F19+H19+J19+L19+N19+P19) -> 13625 | S19: 0 | T19: 66.66666 | U19: =SUM(Q19+S19) -> 9064.5 | V19: =SUM(R19+T19) -> 13691.667 | W19: leicht bewölkt | X19: 10 | Y19: °C
A20: =SUM(A19+1) -> 14 | B20: Mi | C20: 2695.8 | D20: 5000 | E20: 0 | F20: 2666.6667 | G20: 0 | H20: 833.33333 | I20: 0 | K20: 382.3 | L20: 2166.6667 | M20: 900.9 | N20: 1000 | O20: 4611.2 | P20: 1958.3333 | Q20: =SUM(C20+E20+G20+I20+K20+M20+O20) -> 8590.2 | R20: =SUM(D20+F20+H20+J20+L20+N20+P20) -> 13625 | S20: 0 | T20: 66.66666 | U20: =SUM(Q20+S20) -> 8590.2 | V20: =SUM(R20+T20) -> 13691.667 | W20: leicht bewölkt | X20: 10 | Y20: °C
A21: =SUM(A20+1) -> 15 | B21: Do | C21: 2551.5 | D21: 5000 | E21: 0 | F21: 2666.6667 | G21: 0 | H21: 833.33333 | I21: 0 | K21: 0 | L21: 2166.6667 | M21: 0 | N21: 1000 | O21: 3836.8 | P21: 1958.3333 | Q21: =SUM(C21+E21+G21+I21+K21+M21+O21) -> 6388.3 | R21: =SUM(D21+F21+H21+J21+L21+N21+P21) -> 13625 | S21: 0 | T21: 66.66666 | U21: =SUM(Q21+S21) -> 6388.3 | V21: =SUM(R21+T21) -> 13691.667 | W21: leicht bewölkt | X21: 10 | Y21: °C
A22: =SUM(A21+1) -> 16 | B22: Fr | C22: 3818.7 | D22: 5000 | E22: 0 | F22: 2666.6667 | G22: 96.8 | H22: 833.33333 | I22: 0 | K22: 783.4 | L22: 2166.6667 | M22: 0 | N22: 1000 | O22: 6768 | P22: 1958.3333 | Q22: =SUM(C22+E22+G22+I22+K22+M22+O22) -> 11466.9 | R22: =SUM(D22+F22+H22+J22+L22+N22+P22) -> 13625 | S22: 0 | T22: 66.66666 | U22: =SUM(Q22+S22) -> 11466.9 | V22: =SUM(R22+T22) -> 13691.667 | W22: ziemlich sonnig | X22: 10 | Y22: °C
A23: =SUM(A22+1) -> 17 | B23: Sa | C23: 3990.1 | D23: 5000 | E23: 0 | F23: 2666.6667 | G23: 96 | H23: 833.33333 | I23: 0 | K23: 1856.8 | L23: 2166.6667 | M23: 0 | N23: 1000 | O23: 5666.4 | P23: 1958.3333 | Q23: =SUM(C23+E23+G23+I23+K23+M23+O23) -> 11609.3 | R23: =SUM(D23+F23+H23+J23+L23+N23+P23) -> 13625 | S23: 0 | T23: 66.66666 | U23: =SUM(Q23+S23) -> 11609.3 | V23: =SUM(R23+T23) -> 13691.667 | W23: ziemlich sonnig | X23: 10 | Y23: °C
A24: =SUM(A23+1) -> 18 | B24: So | C24: 425 | D24: 5000 | E24: 0 | F24: 2666.6667 | G24: 0 | H24: 833.33333 | I24: 0 | K24: 0 | L24: 2166.6667 | M24: 0 | N24: 1000 | O24: 943 | P24: 1958.3333 | Q24: =SUM(C24+E24+G24+I24+K24+M24+O24) -> 1368 | R24: =SUM(D24+F24+H24+J24+L24+N24+P24) -> 13625 | S24: 0 | T24: 66.66666 | U24: =SUM(Q24+S24) -> 1368 | V24: =SUM(R24+T24) -> 13691.667 | W24: ziemlich sonnig | X24: 12 | Y24: °C
A25: KW | B25: =SUM(B17+1) -> 16 | C25: =SUM(C18:C24) -> 15962.5 | D25: =SUM(D18:D24) -> 35000 | E25: =SUM(E18:E24) -> 0 | F25: =SUM(F18:F24) -> 18666.667 | G25: =SUM(G18:G24) -> 192.8 | H25: =SUM(H18:H24) -> 5833.3333 | I25: =SUM(I18:I24) -> 0 | J25: =SUM(J18:J24) -> 0 | ... V25: =SUM(V18:V24) -> 95841.666 | W25: Ø Temp | X25: =SUM(X18:X24)/7 -> 10.285714 | Y25: °C
A26: =SUM(A24+1) -> 19 | B26: Mo | C26: 1810.4 | D26: 5000 | E26: 1205.3 | F26: 2666.6667 | G26: 337.3 | H26: 833.33333 | I26: 0 | K26: 0 | L26: 2166.6667 | M26: 0 | N26: 1000 | O26: 2736.2 | P26: 1958.3333 | Q26: =SUM(C26+E26+G26+I26+K26+M26+O26) -> 6089.2 | R26: =SUM(D26+F26+H26+J26+L26+N26+P26) -> 13625 | S26: 0 | T26: 66.66666 | U26: =SUM(Q26+S26) -> 6089.2 | V26: =SUM(R26+T26) -> 13691.667 | W26: ziemlich sonnig | X26: 10 | Y26: °C
A27: =SUM(A26+1) -> 20 | B27: Di | C27: 1106.4 | D27: 5000 | E27: 4474.3 | F27: 2666.6667 | G27: 1301.7 | H27: 833.33333 | I27: 0 | K27: 0 | L27: 2166.6667 | M27: 1033.2 | N27: 1000 | O27: 3777 | P27: 1958.3333 | Q27: =SUM(C27+E27+G27+I27+K27+M27+O27) -> 11692.6 | R27: =SUM(D27+F27+H27+J27+L27+N27+P27) -> 13625 | S27: 0 | T27: 66.66666 | U27: =SUM(Q27+S27) -> 11692.6 | V27: =SUM(R27+T27) -> 13691.667 | W27: sonnig | X27: 14 | Y27: °C
A28: =SUM(A27+1) -> 21 | B28: Mi | C28: 1791.8 | D28: 5000 | E28: 3697.5 | F28: 2666.6667 | G28: 956.9 | H28: 833.33333 | I28: 0 | K28: 0 | L28: 2166.6667 | M28: 3225.8 | N28: 1000 | O28: 2302.1 | P28: 1958.3333 | Q28: =SUM(C28+E28+G28+I28+K28+M28+O28) -> 11974.1 | R28: =SUM(D28+F28+H28+J28+L28+N28+P28) -> 13625 | S28: 0 | T28: 66.66666 | U28: =SUM(Q28+S28) -> 11974.1 | V28: =SUM(R28+T28) -> 13691.667 | W28: sonnig | X28: 14 | Y28: °C
A29: =SUM(A28+1) -> 22 | B29: Do | C29: 2331.8 | D29: 5000 | E29: 4333.7 | F29: 2666.6667 | G29: 1052.7 | H29: 833.33333 | I29: 0 | K29: 0 | L29: 2166.6667 | M29: 4370.4 | N29: 1000 | O29: 3435.8 | P29: 1958.3333 | Q29: =SUM(C29+E29+G29+I29+K29+M29+O29) -> 15524.4 | R29: =SUM(D29+F29+H29+J29+L29+N29+P29) -> 13625 | S29: 0 | T29: 66.66666 | U29: =SUM(Q29+S29) -> 15524.4 | V29: =SUM(R29+T29) -> 13691.667 | W29: sonnig | X29: 16 | Y29: °C
A30: =SUM(A29+1) -> 23 | B30: Fr | C30: 2801.9 | D30: 5000 | E30: 10392.7 | F30: 2666.6667 | G30: 2161.8 | H30: 833.33333 | I30: 0 | K30: 0 | L30: 2166.6667 | M30: 1792.4 | N30: 1000 | O30: 6528.6 | P30: 1958.3333 | Q30: =SUM(C30+E30+G30+I30+K30+M30+O30) -> 23677.4 | R30: =SUM(D30+F30+H30+J30+L30+N30+P30) -> 13625 | S30: 0 | T30: 66.66666 | U30: =SUM(Q30+S30) -> 23677.4 | V30: =SUM(R30+T30) -> 13691.667 | W30: sonnig | X30: 18 | Y30: °C
A31: =SUM(A30+1) -> 24 | B31: Sa | C31: 2982.8 | D31: 5000 | E31: 14734.1 | F31: 2666.6667 | G31: 2534.5 | H31: 833.33333 | I31: 0 | K31: 688.2 | L31: 2166.6667 | M31: 0 | N31: 1000 | O31: 6181.9 | P31: 1958.3333 | Q31: =SUM(C31+E31+G31+I31+K31+M31+O31) -> 27121.5 | R31: =SUM(D31+F31+H31+J31+L31+N31+P31) -> 13625 | S31: 0 | T31: 66.66666 | U31: =SUM(Q31+S31) -> 27121.5 | V31: =SUM(R31+T31) -> 13691.667 | W31: sonnig | X31: 19 | Y31: °C
A32: =SUM(A31+1) -> 25 | B32: So | C32: 1697.5 | D32: 5000 | E32: 15650.6 | F32: 2666.6667 | G32: 2539.8 | H32: 833.33333 | I32: 0 | K32: 0 | L32: 2166.6667 | M32: 0 | N32: 1000 | O32: 3577.3 | P32: 1958.3333 | Q32: =SUM(C32+E32+G32+I32+K32+M32+O32) -> 23465.2 | R32: =SUM(D32+F32+H32+J32+L32+N32+P32) -> 13625 | S32: 0 | T32: 66.66666 | U32: =SUM(Q32+S32) -> 23465.2 | V32: =SUM(R32+T32) -> 13691.667 | W32: sonnig | X32: 19 | Y32: °C
A33: KW | B33: =SUM(B25+1) -> 17 | C33: =SUM(C26:C32) -> 14522.6 | D33: =SUM(D26:D32) -> 35000 | E33: =SUM(E26:E32) -> 54488.2 | F33: =SUM(F26:F32) -> 18666.667 | G33: =SUM(G26:G32) -> 10884.7 | H33: =SUM(H26:H32) -> 5833.3333 | I33: =SUM(I26:I32) -> 0 | J33: =SUM(J26:J32) -> 0 | ... V33: =SUM(V26:V32) -> 95841.666 | W33: Ø Temp | X33: =SUM(X26:X32)/7 -> 15.714286 | Y33: °C
A34: =SUM(A32+1) -> 26 | B34: Mo | C34: 1859.3 | D34: 5000 | E34: 4711.7 | F34: 2666.6667 | G34: 279.1 | H34: 833.33333 | I34: 0 | K34: 0 | L34: 2166.6667 | M34: 0 | N34: 1000 | O34: 3051.7 | P34: 1958.3333 | Q34: =SUM(C34+E34+G34+I34+K34+M34+O34) -> 9901.8 | R34: =SUM(D34+F34+H34+J34+L34+N34+P34) -> 13625 | S34: 0 | T34: 66.66666 | U34: =SUM(Q34+S34) -> 9901.8 | V34: =SUM(R34+T34) -> 13691.667 | W34: leicht bewölkt | X34: 16 | Y34: °C
A35: =SUM(A34+1) -> 27 | B35: Di | C35: 2104.8 | D35: 5000 | E35: 7550.9 | F35: 2666.6667 | G35: 306.7 | H35: 833.33333 | I35: 0 | K35: 0 | L35: 2166.6667 | M35: 61 | N35: 1000 | O35: 2484.5 | P35: 1958.3333 | Q35: =SUM(C35+E35+G35+I35+K35+M35+O35) -> 12507.9 | R35: =SUM(D35+F35+H35+J35+L35+N35+P35) -> 13625 | S35: 0 | T35: 66.66666 | U35: =SUM(Q35+S35) -> 12507.9 | V35: =SUM(R35+T35) -> 13691.667 | W35: sonnig | X35: 16 | Y35: °C
A36: =SUM(A35+1) -> 28 | B36: Mi | C36: 1100.4 | D36: 5000 | E36: 3493 | F36: 2666.6667 | G36: 344.5 | H36: 833.33333 | I36: 0 | K36: 0 | L36: 2166.6667 | M36: 0 | N36: 1000 | O36: 2049.6 | P36: 1958.3333 | Q36: =SUM(C36+E36+G36+I36+K36+M36+O36) -> 6987.5 | R36: =SUM(D36+F36+H36+J36+L36+N36+P36) -> 13625 | S36: 0 | T36: 66.66666 | U36: =SUM(Q36+S36) -> 6987.5 | V36: =SUM(R36+T36) -> 13691.667 | W36: ziemlich sonnig | X36: 20 | Y36: °C
A37: =SUM(A36+1) -> 29 | B37: Do | C37: 1848.4 | D37: 5000 | E37: 1240.9 | F37: 2666.6667 | G37: 44.2 | H37: 833.33333 | I37: 0 | K37: 0 | L37: 2166.6667 | M37: 0 | N37: 1000 | O37: 3197.2 | P37: 1958.3333 | Q37: =SUM(C37+E37+G37+I37+K37+M37+O37) -> 6330.7 | R37: =SUM(D37+F37+H37+J37+L37+N37+P37) -> 13625 | S37: 0 | T37: 66.66666 | U37: =SUM(Q37+S37) -> 6330.7 | V37: =SUM(R37+T37) -> 13691.667 | W37: Regenschauer | X37: 14 | Y37: °C
A38: =SUM(A37+1) -> 30 | B38: Fr | C38: 2724.7 | D38: 5000 | E38: 728.8 | F38: 2666.6667 | G38: 4.6 | H38: 833.33333 | I38: 0 | K38: 2237.7 | L38: 2166.6667 | M38: 0 | N38: 1000 | O38: 6260.9 | P38: 1958.3333 | Q38: =SUM(C38+E38+G38+I38+K38+M38+O38) -> 11956.7 | R38: =SUM(D38+F38+H38+J38+L38+N38+P38) -> 13625 | S38: 0 | T38: 66.66666 | U38: =SUM(Q38+S38) -> 11956.7 | V38: =SUM(R38+T38) -> 13691.667 | W38: bewölkt | X38: 14 | Y38: °C
A39: KW | B39: =SUM(B33+1) -> 18 | C39: =SUM(C34:C38) -> 9637.6 | D39: =SUM(D34:D38) -> 25000 | E39: =SUM(E34:E38) -> 17725.3 | F39: =SUM(F34:F38) -> 13333.333 | G39: =SUM(G34:G38) -> 979.1 | H39: =SUM(H34:H38) -> 4166.6667 | I39: =SUM(I34:I38) -> 0 | J39: =SUM(J34:J38) -> 0 | ... V39: =SUM(V34:V38) -> 68458.333 | W39: Ø Temp | X39: =SUM(X34:X38)/5 -> 16 | Y39: °C
A40: Umsatz kumuliert | C40: =SUM(C9+C17+C25+C33+C39) -> 67295.5 | D40: =SUM(D9+D17+D25+D33+D39) -> 150000 | E40: =SUM(E9+E17+E25+E33+E39) -> 72426.5 | F40: =SUM(F9+F17+F25+F33+F39) -> 80000 | G40: =SUM(G9+G17+G25+G33+G39) -> 13038.4 | H40: =SUM(H9+H17+H25+H33+H39) -> 25000 | I40: =SUM(I9+I17+I25+I33+I39) -> 0 | J40: =SUM(J9+J17+J25+J33+J39) -> 0 | ... V40: =SUM(V9+V17+V25+V33+V39) -> 410750 | W40: Umsatz kumuliert
A41: Umsatz Forecast | C41: =IF(MONTH($H$1)<>MONTH(TODAY()),C40,SUM(C5:C8,C10:C16,C18:C24,C26:C32,C34:C38)/DAY(TODAY())*DAY(DATE(YEAR($H$1),MONTH($H$1)+1,1)-1)) -> 67295.5 | D41: =IF(MONTH($H$1)<>MONTH(TODAY()),D40,SUM(D5:D8,D10:D16,D18:D24,D26:D32,D34:D38)/DAY(TODAY())*DAY(DATE(YEAR($H$1),MONTH($H$1)+1,1)-1)) -> 150000 | E41: =IF(MONTH($H$1)<>MONTH(TODAY()),E40,SUM(E5:E8,E10:E16,E18:E24,E26:E32,E34:E38)/DAY(TODAY())*DAY(DATE(YEAR($H$1),MONTH($H$1)+1,1)-1)) -> 72426.5 | F41: =IF(MONTH($H$1)<>MONTH(TODAY()),F40,SUM(F5:F8,F10:F16,F18:F24,F26:F32,F34:F38)/DAY(TODAY())*DAY(DATE(YEAR($H$1),MONTH($H$1)+1,1)-1)) -> 80000 | G41: =IF(MONTH($H$1)<>MONTH(TODAY()),G40,SUM(G5:G8,G10:G16,G18:G24,G26:G32,G34:G38)/DAY(TODAY())*DAY(DATE(YEAR($H$1),MONTH($H$1)+1,1)-1)) -> 13038.4 | H41: =IF(MONTH($H$1)<>MONTH(TODAY()),H40,SUM(H5:H8,H10:H16,H18:H24,H26:H32,H34:H38)/DAY(TODAY())*DAY(DATE(YEAR($H$1),MONTH($H$1)+1,1)-1)) -> 25000 | I41: =IF(MONTH($H$1)<>MONTH(TODAY()),I40,SUM(I5:I8,I10:I16,I18:I24,I26:I32,I34:I38)/DAY(TODAY())*DAY(DATE(YEAR($H$1),MONTH($H$1)+1,1)-1)) -> 0 | J41: =IF(MONTH($H$1)<>MONTH(TODAY()),J40,SUM(J5:J8,J10:J16,J18:J24,J26:J32,J34:J38)/DAY(TODAY())*DAY(DATE(YEAR($H$1),MONTH($H$1)+1,1)-1)) -> 0 | ... V41: =IF(MONTH($H$1)<>MONTH(TODAY()),V40,SUM(V5:V8,V10:V16,V18:V24,V26:V32,V34:V38)/DAY(TODAY())*DAY(DATE(YEAR($H$1),MONTH($H$1)+1,1)-1)) -> 410750 | W41: Umsatz Forecast
A42: Umsatz pro Tag | C42: =C40/30 -> 2243.1833 | D42: =D40/30 -> 5000 | E42: =E40/30 -> 2414.2167 | F42: =F40/30 -> 2666.6667 | G42: =G40/30 -> 434.61333 | H42: =H40/30 -> 833.33333 | I42: =I40/30 -> 0 | J42: =J40/30 -> 0 | ... V42: =V40/30 -> 13691.667 | W42: Budget pro Tag
A43: Diff. zu Budget | C43: =SUM(C40-D40) -> -82704.5 | E43: =SUM(E40-F40) -> -7573.4998 | G43: =SUM(G40-H40) -> -11961.6 | I43: =SUM(I40-J40) -> 0 | K43: =SUM(K40-L40) -> -54174.8 | M43: =SUM(M40-N40) -> -9927 | O43: =SUM(O40-P40) -> 60358.9 | Q43: =SUM(Q40-R40) -> -105982.5 | S43: =SUM(S40-T40) -> -1999.9998 | U43: =SUM(U40-V40) -> -107982.5
A44: Index | C44: =SUM(100/D40*C40) -> 44.863667 | E44: =SUM(100/F40*E40) -> 90.533125 | G44: =SUM(100/H40*G40) -> 52.1536 | I44: =SUM(100/J40*I40) -> #DIV/0! | K44: =SUM(100/L40*K40) -> 16.654154 | M44: =SUM(100/N40*M40) -> 66.91 | O44: =SUM(100/P40*O40) -> 202.73855 | Q44: =SUM(100/R40*Q40) -> 74.07156 | S44: =SUM(100/T40*S40) -> 0 | U44: =SUM(100/V40*U40) -> 73.710895

Sheet 05_21
A1: Tagesumsätze | H1: 44317
C3: Restaurant | E3: Terrasse | G3: Lounge | I3: Pavillon | K3: Bankett | M3: Seminar | O3: Hotel | Q3: TOTAL Gesamtbetrieb ohne Seebad | S3: Seebad | U3: TOTAL Gesamtbetrieb mit Seebad | W3: Info's
C4: IST | D4: Budget | E4: IST | F4: Budget | G4: IST | H4: Budget | I4: IST | J4: Budget | K4: IST | L4: Budget | M4: IST | N4: Budget | O4: IST | P4: Budget | Q4: IST | R4: Budget | S4: IST | T4: Budget | U4: IST | V4: Budget | W4: Wetter | X4: Temp. | Z4: Bemerkung
A5: 1 | B5: Sa | C5: 4661 | D5: 3709.6774 | E5: 440 | F5: 5322.5806 | G5: 131.7 | H5: 1129.0323 | I5: 0 | J5: 374.19355 | K5: 1135.2 | L5: 2935.4839 | M5: 0 | N5: 1129.0323 | O5: 6430.6 | P5: 2903.2258 | Q5: =SUM(C5+E5+G5+I5+K5+M5+O5) -> 12798.5 | R5: =SUM(D5+F5+H5+J5+L5+N5+P5) -> 17503.226 | S5: 0 | T5: 967.74194 | U5: =SUM(Q5+S5) -> 12798.5 | V5: =SUM(R5+T5) -> 18470.968 | W5: Regen | X5: 10 | Y5: °C
A6: =SUM(A5+1) -> 2 | B6: So | C6: 1756.6 | D6: 3709.6774 | E6: 0 | F6: 5322.5806 | G6: 63 | H6: 1129.0323 | I6: 0 | J6: 374.19355 | K6: 0 | L6: 2935.4839 | M6: 0 | N6: 1129.0323 | O6: 2918.3 | P6: 2903.2258 | Q6: =SUM(C6+E6+G6+I6+K6+M6+O6) -> 4737.9 | R6: =SUM(D6+F6+H6+J6+L6+N6+P6) -> 17503.226 | S6: 0 | T6: 967.74194 | U6: =SUM(Q6+S6) -> 4737.9 | V6: =SUM(R6+T6) -> 18470.968 | W6: Regen | X6: 8 | Y6: °C
A7: KW | B7: 18 | C7: =SUM(C5:C6) -> 6417.6 | D7: =SUM(D5:D6) -> 7419.3548 | E7: =SUM(E5:E6) -> 440 | F7: =SUM(F5:F6) -> 10645.161 | G7: =SUM(G5:G6) -> 194.7 | H7: =SUM(H5:H6) -> 2258.0645 | I7: =SUM(I5:I6) -> 0 | J7: =SUM(J5:J6) -> 748.3871 | ... V7: =SUM(V5:V6) -> 36941.935 | W7: Ø Temp | X7: =SUM(X5:X6)/2 -> 9 | Y7: °C
A8: =SUM(A6+1) -> 3 | B8: Mo | C8: 797.9 | D8: 3709.6774 | E8: 5067.6 | F8: 5322.5806 | G8: 463 | H8: 1129.0323 | I8: 0 | J8: 374.19355 | K8: 0 | L8: 2935.4839 | M8: 0 | N8: 1129.0323 | O8: 3414.4 | P8: 2903.2258 | Q8: =SUM(C8+E8+G8+I8+K8+M8+O8) -> 9742.9 | R8: =SUM(D8+F8+H8+J8+L8+N8+P8) -> 17503.226 | S8: 0 | T8: 967.74194 | U8: =SUM(Q8+S8) -> 9742.9 | V8: =SUM(R8+T8) -> 18470.968 | W8: sonnig | X8: 14 | Y8: °C
A9: =SUM(A8+1) -> 4 | B9: Di | C9: 2218.5 | D9: 3709.6774 | E9: 831.7 | F9: 5322.5806 | G9: 284.8 | H9: 1129.0323 | I9: 0 | J9: 374.19355 | K9: 0 | L9: 2935.4839 | M9: 162 | N9: 1129.0323 | O9: 4041.8 | P9: 2903.2258 | Q9: =SUM(C9+E9+G9+I9+K9+M9+O9) -> 7538.8 | R9: =SUM(D9+F9+H9+J9+L9+N9+P9) -> 17503.226 | S9: 0 | T9: 967.74194 | U9: =SUM(Q9+S9) -> 7538.8 | V9: =SUM(R9+T9) -> 18470.968 | W9: ziemlich sonnig | X9: 16 | Y9: °C
A10: =SUM(A9+1) -> 5 | B10: Mi | C10: 2022 | D10: 3709.6774 | E10: 103.7 | F10: 5322.5806 | G10: 124.3 | H10: 1129.0323 | I10: 0 | J10: 374.19355 | K10: 0 | L10: 2935.4839 | M10: 40.6 | N10: 1129.0323 | O10: 3467.4 | P10: 2903.2258 | Q10: =SUM(C10+E10+G10+I10+K10+M10+O10) -> 5758 | R10: =SUM(D10+F10+H10+J10+L10+N10+P10) -> 17503.226 | S10: 0 | T10: 967.74194 | U10: =SUM(Q10+S10) -> 5758 | V10: =SUM(R10+T10) -> 18470.968 | W10: Regen | X10: 8 | Y10: °C
A11: =SUM(A10+1) -> 6 | B11: Do | C11: 2963.4 | D11: 3709.6774 | E11: 89.9 | F11: 5322.5806 | G11: 35.4 | H11: 1129.0323 | I11: 0 | J11: 374.19355 | K11: 0 | L11: 2935.4839 | M11: 0 | N11: 1129.0323 | O11: 4026.2 | P11: 2903.2258 | Q11: =SUM(C11+E11+G11+I11+K11+M11+O11) -> 7114.9 | R11: =SUM(D11+F11+H11+J11+L11+N11+P11) -> 17503.226 | S11: 0 | T11: 967.74194 | U11: =SUM(Q11+S11) -> 7114.9 | V11: =SUM(R11+T11) -> 18470.968 | W11: bewölkt | X11: 10 | Y11: °C
A12: =SUM(A11+1) -> 7 | B12: Fr | C12: 3631.3 | D12: 3709.6774 | E12: 1731.5 | F12: 5322.5806 | G12: 161.8 | H12: 1129.0323 | I12: 0 | J12: 374.19355 | K12: 331.7 | L12: 2935.4839 | M12: 0 | N12: 1129.0323 | O12: 5274.2 | P12: 2903.2258 | Q12: =SUM(C12+E12+G12+I12+K12+M12+O12) -> 11130.5 | R12: =SUM(D12+F12+H12+J12+L12+N12+P12) -> 17503.226 | S12: 0 | T12: 967.74194 | U12: =SUM(Q12+S12) -> 11130.5 | V12: =SUM(R12+T12) -> 18470.968 | W12: Regen | X12: 10 | Y12: °C
A13: =SUM(A12+1) -> 8 | B13: Sa | C13: 2271.2 | D13: 3709.6774 | E13: 14910.6 | F13: 5322.5806 | G13: 1546.9 | H13: 1129.0323 | I13: 0 | J13: 374.19355 | K13: 480 | L13: 2935.4839 | M13: 0 | N13: 1129.0323 | O13: 6752.2 | P13: 2903.2258 | Q13: =SUM(C13+E13+G13+I13+K13+M13+O13) -> 25960.9 | R13: =SUM(D13+F13+H13+J13+L13+N13+P13) -> 17503.226 | S13: 1428.4 | T13: 967.74194 | U13: =SUM(Q13+S13) -> 27389.3 | V13: =SUM(R13+T13) -> 18470.968 | W13: sonnig | X13: 18 | Y13: °C
A14: =SUM(A13+1) -> 9 | B14: So | C14: 890.1 | D14: 3709.6774 | E14: 18189.7 | F14: 5322.5806 | G14: 1770.7 | H14: 1129.0323 | I14: 0 | J14: 374.19355 | K14: 0 | L14: 2935.4839 | M14: 0 | N14: 1129.0323 | O14: 3248.6 | P14: 2903.2258 | Q14: =SUM(C14+E14+G14+I14+K14+M14+O14) -> 24099.1 | R14: =SUM(D14+F14+H14+J14+L14+N14+P14) -> 17503.226 | S14: 2995.3 | T14: 967.74194 | U14: =SUM(Q14+S14) -> 27094.4 | V14: =SUM(R14+T14) -> 18470.968 | W14: sonnig | X14: 25 | Y14: °C
A15: KW | B15: =SUM(B7+1) -> 19 | C15: =SUM(C8:C14) -> 14794.4 | D15: =SUM(D8:D14) -> 25967.742 | E15: =SUM(E8:E14) -> 40924.7 | F15: =SUM(F8:F14) -> 37258.064 | G15: =SUM(G8:G14) -> 4386.9 | H15: =SUM(H8:H14) -> 7903.2258 | I15: =SUM(I8:I14) -> 0 | J15: =SUM(J8:J14) -> 2619.3548 | ... V15: =SUM(V8:V14) -> 129296.77 | W15: Ø Temp | X15: =SUM(X8:X14)/7 -> 14.428571 | Y15: °C
A16: =SUM(A14+1) -> 10 | B16: Mo | C16: 1965.3 | D16: 3709.6774 | E16: 5091.2 | F16: 5322.5806 | G16: 270.7 | H16: 1129.0323 | I16: 0 | J16: 374.19355 | K16: 0 | L16: 2935.4839 | M16: 0 | N16: 1129.0323 | O16: 3637 | P16: 2903.2258 | Q16: =SUM(C16+E16+G16+I16+K16+M16+O16) -> 10964.2 | R16: =SUM(D16+F16+H16+J16+L16+N16+P16) -> 17503.226 | S16: 75 | T16: 967.74194 | U16: =SUM(Q16+S16) -> 11039.2 | V16: =SUM(R16+T16) -> 18470.968 | W16: ziemlich sonnig | X16: 14 | Y16: °C
A17: =SUM(A16+1) -> 11 | B17: Di | C17: 1486.5 | D17: 3709.6774 | E17: 177.8 | F17: 5322.5806 | G17: 99.6 | H17: 1129.0323 | I17: 0 | J17: 374.19355 | K17: 0 | L17: 2935.4839 | M17: 0 | N17: 1129.0323 | O17: 1834.3 | P17: 2903.2258 | Q17: =SUM(C17+E17+G17+I17+K17+M17+O17) -> 3598.2 | R17: =SUM(D17+F17+H17+J17+L17+N17+P17) -> 17503.226 | S17: 0 | T17: 967.74194 | U17: =SUM(Q17+S17) -> 3598.2 | V17: =SUM(R17+T17) -> 18470.968 | W17: Regenschauer | X17: 12 | Y17: °C
A18: =SUM(A17+1) -> 12 | B18: Mi | C18: 1969.9 | D18: 3709.6774 | E18: 2688 | F18: 5322.5806 | G18: 192.7 | H18: 1129.0323 | I18: 0 | J18: 374.19355 | K18: 1683.8 | L18: 2935.4839 | M18: 25 | N18: 1129.0323 | O18: 5606.5 | P18: 2903.2258 | Q18: =SUM(C18+E18+G18+I18+K18+M18+O18) -> 12165.9 | R18: =SUM(D18+F18+H18+J18+L18+N18+P18) -> 17503.226 | S18: 0 | T18: 967.74194 | U18: =SUM(Q18+S18) -> 12165.9 | V18: =SUM(R18+T18) -> 18470.968 | W18: leicht bewölkt | X18: 14 | Y18: °C
A19: =SUM(A18+1) -> 13 | B19: Do | C19: 3045.8 | D19: 3709.6774 | E19: 2748.8 | F19: 5322.5806 | G19: 521.3 | H19: 1129.0323 | I19: 0 | J19: 374.19355 | K19: 704.6 | L19: 2935.4839 | M19: 4.2 | N19: 1129.0323 | O19: 6564.6 | P19: 2903.2258 | Q19: =SUM(C19+E19+G19+I19+K19+M19+O19) -> 13589.3 | R19: =SUM(D19+F19+H19+J19+L19+N19+P19) -> 17503.226 | S19: 0 | T19: 967.74194 | U19: =SUM(Q19+S19) -> 13589.3 | V19: =SUM(R19+T19) -> 18470.968 | W19: Regenschauer | X19: 13 | Y19: °C | Z19: Auffahrt
A20: =SUM(A19+1) -> 14 | B20: Fr | C20: 3530.9 | D20: 3709.6774 | E20: 5488.6 | F20: 5322.5806 | G20: 821.9 | H20: 1129.0323 | I20: 0 | J20: 374.19355 | K20: 912.5 | L20: 2935.4839 | M20: 0 | N20: 1129.0323 | O20: 6408.4 | P20: 2903.2258 | Q20: =SUM(C20+E20+G20+I20+K20+M20+O20) -> 17162.3 | R20: =SUM(D20+F20+H20+J20+L20+N20+P20) -> 17503.226 | S20: 0 | T20: 967.74194 | U20: =SUM(Q20+S20) -> 17162.3 | V20: =SUM(R20+T20) -> 18470.968 | W20: ziemlich sonnig | X20: 15 | Y20: °C
A21: =SUM(A20+1) -> 15 | B21: Sa | C21: 4532.6 | D21: 3709.6774 | E21: 3054 | F21: 5322.5806 | G21: 1047.7 | H21: 1129.0323 | I21: 0 | J21: 374.19355 | K21: 2095.9 | L21: 2935.4839 | M21: 0 | N21: 1129.0323 | O21: 5967.6 | P21: 2903.2258 | Q21: =SUM(C21+E21+G21+I21+K21+M21+O21) -> 16697.8 | R21: =SUM(D21+F21+H21+J21+L21+N21+P21) -> 17503.226 | S21: 0 | T21: 967.74194 | U21: =SUM(Q21+S21) -> 16697.8 | V21: =SUM(R21+T21) -> 18470.968 | W21: Regen | X21: 13 | Y21: °C
A22: =SUM(A21+1) -> 16 | B22: So | C22: 1464.6 | D22: 3709.6774 | E22: 743.2 | F22: 5322.5806 | G22: 81.8 | H22: 1129.0323 | I22: 0 | J22: 374.19355 | K22: 0 | L22: 2935.4839 | M22: 0 | N22: 1129.0323 | O22: 2638.4 | P22: 2903.2258 | Q22: =SUM(C22+E22+G22+I22+K22+M22+O22) -> 4928 | R22: =SUM(D22+F22+H22+J22+L22+N22+P22) -> 17503.226 | S22: 0 | T22: 967.74194 | U22: =SUM(Q22+S22) -> 4928 | V22: =SUM(R22+T22) -> 18470.968 | W22: Regen | X22: 12 | Y22: °C
A23: KW | B23: =SUM(B15+1) -> 20 | C23: =SUM(C16:C22) -> 17995.6 | D23: =SUM(D16:D22) -> 25967.742 | E23: =SUM(E16:E22) -> 19991.6 | F23: =SUM(F16:F22) -> 37258.064 | G23: =SUM(G16:G22) -> 3035.7 | H23: =SUM(H16:H22) -> 7903.2258 | I23: =SUM(I16:I22) -> 0 | J23: =SUM(J16:J22) -> 2619.3548 | ... V23: =SUM(V16:V22) -> 129296.77 | W23: Ø Temp | X23: =SUM(X16:X22)/7 -> 13.285714 | Y23: °C
A24: =SUM(A22+1) -> 17 | B24: Mo | C24: 3068.7 | D24: 3709.6774 | E24: 1302.7 | F24: 5322.5806 | G24: 17.6 | H24: 1129.0323 | I24: 0 | J24: 374.19355 | K24: 0 | L24: 2935.4839 | M24: 775.6 | N24: 1129.0323 | O24: 5256.4 | P24: 2903.2258 | Q24: =SUM(C24+E24+G24+I24+K24+M24+O24) -> 10421 | R24: =SUM(D24+F24+H24+J24+L24+N24+P24) -> 17503.226 | S24: 0 | T24: 967.74194 | U24: =SUM(Q24+S24) -> 10421 | V24: =SUM(R24+T24) -> 18470.968 | W24: Regenschauer | X24: 12 | Y24: °C
A25: =SUM(A24+1) -> 18 | B25: Di | C25: 1712.2 | D25: 3709.6774 | E25: 1823.5 | F25: 5322.5806 | G25: 246.2 | H25: 1129.0323 | I25: 0 | J25: 374.19355 | K25: 18.7 | L25: 2935.4839 | M25: 100 | N25: 1129.0323 | O25: 3777.1 | P25: 2903.2258 | Q25: =SUM(C25+E25+G25+I25+K25+M25+O25) -> 7677.7 | R25: =SUM(D25+F25+H25+J25+L25+N25+P25) -> 17503.226 | S25: 0 | T25: 967.74194 | U25: =SUM(Q25+S25) -> 7677.7 | V25: =SUM(R25+T25) -> 18470.968 | W25: Regenschauer | X25: 12 | Y25: °C
A26: =SUM(A25+1) -> 19 | B26: Mi | C26: 2121.9 | D26: 3709.6774 | E26: 1219.5 | F26: 5322.5806 | G26: 14.2 | H26: 1129.0323 | I26: 0 | J26: 374.19355 | K26: 1154.4 | L26: 2935.4839 | M26: 0 | N26: 1129.0323 | O26: 4846 | P26: 2903.2258 | Q26: =SUM(C26+E26+G26+I26+K26+M26+O26) -> 9356 | R26: =SUM(D26+F26+H26+J26+L26+N26+P26) -> 17503.226 | S26: 0 | T26: 967.74194 | U26: =SUM(Q26+S26) -> 9356 | V26: =SUM(R26+T26) -> 18470.968 | W26: veränderlich | X26: 12 | Y26: °C
A27: =SUM(A26+1) -> 20 | B27: Do | C27: 1488.9 | D27: 3709.6774 | E27: 3913.8 | F27: 5322.5806 | G27: 975 | H27: 1129.0323 | I27: 0 | J27: 374.19355 | K27: 442.6 | L27: 2935.4839 | M27: 1017.8 | N27: 1129.0323 | O27: 5291.1 | P27: 2903.2258 | Q27: =SUM(C27+E27+G27+I27+K27+M27+O27) -> 13129.2 | R27: =SUM(D27+F27+H27+J27+L27+N27+P27) -> 17503.226 | S27: 0 | T27: 967.74194 | U27: =SUM(Q27+S27) -> 13129.2 | V27: =SUM(R27+T27) -> 18470.968 | W27: bewölkt | X27: 12 | Y27: °C
A28: =SUM(A27+1) -> 21 | B28: Fr | C28: 1834.6 | D28: 3709.6774 | E28: 1507.3 | F28: 5322.5806 | G28: 146 | H28: 1129.0323 | I28: 0 | J28: 374.19355 | K28: 0 | L28: 2935.4839 | M28: 0 | N28: 1129.0323 | O28: 4681.5 | P28: 2903.2258 | Q28: =SUM(C28+E28+G28+I28+K28+M28+O28) -> 8169.4 | R28: =SUM(D28+F28+H28+J28+L28+N28+P28) -> 17503.226 | S28: 0 | T28: 967.74194 | U28: =SUM(Q28+S28) -> 8169.4 | V28: =SUM(R28+T28) -> 18470.968 | W28: bewölkt | X28: 14 | Y28: °C
A29: =SUM(A28+1) -> 22 | B29: Sa | C29: 2808.7 | D29: 3709.6774 | E29: 7581.2 | F29: 5322.5806 | G29: 1146.5 | H29: 1129.0323 | I29: 150 | J29: 374.19355 | K29: 4069.2 | L29: 2935.4839 | M29: 0 | N29: 1129.0323 | O29: 6993.5 | P29: 2903.2258 | Q29: =SUM(C29+E29+G29+I29+K29+M29+O29) -> 22749.1 | R29: =SUM(D29+F29+H29+J29+L29+N29+P29) -> 17503.226 | S29: 0 | T29: 967.74194 | U29: =SUM(Q29+S29) -> 22749.1 | V29: =SUM(R29+T29) -> 18470.968 | W29: ziemlich sonnig | X29: 14 | Y29: °C
A30: =SUM(A29+1) -> 23 | B30: So | C30: 3669.7 | D30: 3709.6774 | E30: 13185.8 | F30: 5322.5806 | G30: 931.6 | H30: 1129.0323 | I30: 0 | J30: 374.19355 | K30: 1124.9 | L30: 2935.4839 | M30: 0 | N30: 1129.0323 | O30: 6447.7 | P30: 2903.2258 | Q30: =SUM(C30+E30+G30+I30+K30+M30+O30) -> 25359.7 | R30: =SUM(D30+F30+H30+J30+L30+N30+P30) -> 17503.226 | S30: 554.1 | T30: 967.74194 | U30: =SUM(Q30+S30) -> 25913.8 | V30: =SUM(R30+T30) -> 18470.968 | W30: sonnig | X30: 18 | Y30: °C
A31: KW | B31: =SUM(B23+1) -> 21 | C31: =SUM(C24:C30) -> 16704.7 | D31: =SUM(D24:D30) -> 25967.742 | E31: =SUM(E24:E30) -> 30533.8 | F31: =SUM(F24:F30) -> 37258.064 | G31: =SUM(G24:G30) -> 3477.1 | H31: =SUM(H24:H30) -> 7903.2258 | I31: =SUM(I24:I30) -> 150 | J31: =SUM(J24:J30) -> 2619.3548 | ... V31: =SUM(V24:V30) -> 129296.77 | W31: Ø Temp | X31: =SUM(X24:X30)/7 -> 13.428571 | Y31: °C | Z31: Pfingsten
A32: =SUM(A30+1) -> 24 | B32: Mo | C32: 1347.5 | D32: 3709.6774 | E32: 3239 | F32: 5322.5806 | G32: 635.7 | H32: 1129.0323 | I32: 0 | J32: 374.19355 | K32: 0 | L32: 2935.4839 | M32: 0 | N32: 1129.0323 | O32: 2650 | P32: 2903.2258 | Q32: =SUM(C32+E32+G32+I32+K32+M32+O32) -> 7872.2 | R32: =SUM(D32+F32+H32+J32+L32+N32+P32) -> 17503.226 | S32: 0 | T32: 967.74194 | U32: =SUM(Q32+S32) -> 7872.2 | V32: =SUM(R32+T32) -> 18470.968 | W32: veränderlich | X32: 16 | Y32: °C | Z32: Pfingstmontag
A33: =SUM(A32+1) -> 25 | B33: Di | C33: 1648.1 | D33: 3709.6774 | E33: 2633 | F33: 5322.5806 | G33: 369.6 | H33: 1129.0323 | I33: 0 | J33: 374.19355 | K33: 0 | L33: 2935.4839 | M33: 100 | N33: 1129.0323 | O33: 2638.7 | P33: 2903.2258 | Q33: =SUM(C33+E33+G33+I33+K33+M33+O33) -> 7389.4 | R33: =SUM(D33+F33+H33+J33+L33+N33+P33) -> 17503.226 | S33: 0 | T33: 967.74194 | U33: =SUM(Q33+S33) -> 7389.4 | V33: =SUM(R33+T33) -> 18470.968 | W33: veränderlich | X33: 14 | Y33: °C
A34: =SUM(A33+1) -> 26 | B34: Mi | C34: 1144 | D34: 3709.6774 | E34: 1948.6 | F34: 5322.5806 | G34: 261.3 | H34: 1129.0323 | I34: 0 | J34: 374.19355 | K34: 0 | L34: 2935.4839 | M34: 0 | N34: 1129.0323 | O34: 1498 | P34: 2903.2258 | Q34: =SUM(C34+E34+G34+I34+K34+M34+O34) -> 4851.9 | R34: =SUM(D34+F34+H34+J34+L34+N34+P34) -> 17503.226 | S34: 0 | T34: 967.74194 | U34: =SUM(Q34+S34) -> 4851.9 | V34: =SUM(R34+T34) -> 18470.968 | W34: veränderlich | X34: 15 | Y34: °C
A35: =SUM(A34+1) -> 27 | B35: Do | C35: 1244.6 | D35: 3709.6774 | E35: 2565 | F35: 5322.5806 | G35: 214.8 | H35: 1129.0323 | I35: 0 | J35: 374.19355 | K35: 0 | L35: 2935.4839 | M35: 0 | N35: 1129.0323 | O35: 1873.9 | P35: 2903.2258 | Q35: =SUM(C35+E35+G35+I35+K35+M35+O35) -> 5898.3 | R35: =SUM(D35+F35+H35+J35+L35+N35+P35) -> 17503.226 | S35: 0 | T35: 967.74194 | U35: =SUM(Q35+S35) -> 5898.3 | V35: =SUM(R35+T35) -> 18470.968 | W35: veränderlich | X35: 15 | Y35: °C
A36: =SUM(A35+1) -> 28 | B36: Fr | C36: 4436.1 | D36: 3709.6774 | E36: 10249.65 | F36: 5322.5806 | G36: 1076.1 | H36: 1129.0323 | I36: 0 | J36: 374.19355 | K36: 0 | L36: 2935.4839 | M36: 0 | N36: 1129.0323 | O36: 7748.3 | P36: 2903.2258 | Q36: =SUM(C36+E36+G36+I36+K36+M36+O36) -> 23510.15 | R36: =SUM(D36+F36+H36+J36+L36+N36+P36) -> 17503.226 | S36: 707.2 | T36: 967.74194 | U36: =SUM(Q36+S36) -> 24217.35 | V36: =SUM(R36+T36) -> 18470.968 | W36: Hochnebel | X36: 16 | Y36: °C
A37: =SUM(A36+1) -> 29 | B37: Sa | C37: 2056.6 | D37: 3709.6774 | E37: 13024.2 | F37: 5322.5806 | G37: 1413.2 | H37: 1129.0323 | I37: 0 | J37: 374.19355 | K37: 127 | L37: 2935.4839 | M37: 0 | N37: 1129.0323 | O37: 8965.7 | P37: 2903.2258 | Q37: =SUM(C37+E37+G37+I37+K37+M37+O37) -> 25586.7 | R37: =SUM(D37+F37+H37+J37+L37+N37+P37) -> 17503.226 | S37: 808.8 | T37: 967.74194 | U37: =SUM(Q37+S37) -> 26395.5 | V37: =SUM(R37+T37) -> 18470.968 | W37: bewölkt | X37: 18 | Y37: °C
A38: =SUM(A37+1) -> 30 | B38: So | C38: 664.2 | D38: 3709.6774 | E38: 15348.4 | F38: 5322.5806 | G38: 1778.9 | H38: 1129.0323 | I38: 0 | J38: 374.19355 | K38: 0 | L38: 2935.4839 | M38: 0 | N38: 1129.0323 | O38: 4402.4 | P38: 2903.2258 | Q38: =SUM(C38+E38+G38+I38+K38+M38+O38) -> 22193.9 | R38: =SUM(D38+F38+H38+J38+L38+N38+P38) -> 17503.226 | S38: 2409.4 | T38: 967.74194 | U38: =SUM(Q38+S38) -> 24603.3 | V38: =SUM(R38+T38) -> 18470.968 | W38: sonnig | X38: 19 | Y38: °C
A39: KW | B39: =SUM(B31+1) -> 22 | C39: =SUM(C32:C38) -> 12541.1 | D39: =SUM(D32:D38) -> 25967.742 | E39: =SUM(E32:E38) -> 49007.85 | F39: =SUM(F32:F38) -> 37258.064 | G39: =SUM(G32:G38) -> 5749.6 | H39: =SUM(H32:H38) -> 7903.2258 | I39: =SUM(I32:I38) -> 0 | J39: =SUM(J32:J38) -> 2619.3548 | ... V39: =SUM(V32:V38) -> 129296.77 | W39: Ø Temp | X39: =SUM(X32:X38)/7 -> 16.142857 | Y39: °C
A40: =SUM(A38+1) -> 31 | B40: Mo | C40: 1550.2 | D40: 3709.6774 | E40: 10350.05 | F40: 5322.5806 | G40: 792 | H40: 1129.0323 | I40: 0 | J40: 374.19355 | K40: 0 | L40: 2935.4839 | M40: 0 | N40: 1129.0323 | O40: 3549.28 | P40: 2903.2258 | Q40: =SUM(C40+E40+G40+I40+K40+M40+O40) -> 16241.53 | R40: =SUM(D40+F40+H40+J40+L40+N40+P40) -> 17503.226 | S40: 580.1 | T40: 967.74194 | U40: =Q40+S40 -> 16821.63 | V40: =SUM(R40+T40) -> 18470.968 | W40: sonnig | X40: 18 | Y40: °C
A41: Umsatz kumuliert | C41: =SUM(C7+C15+C23+C31+C39+C40) -> 70003.6 | D41: =SUM(D7+D15+D23+D31+D39+D40) -> 115000 | E41: =SUM(E7+E15+E23+E31+E39+E40) -> 151248 | F41: =SUM(F7+F15+F23+F31+F39+F40) -> 165000 | G41: =SUM(G7+G15+G23+G31+G39+G40) -> 17636 | H41: =SUM(H7+H15+H23+H31+H39+H40) -> 35000 | I41: =SUM(I7+I15+I23+I31+I39+I40) -> 150 | J41: =SUM(J7+J15+J23+J31+J39+J40) -> 11600 | ... V41: =SUM(V7+V15+V23+V31+V39+V40) -> 572600 | W41: Umsatz kumuliert
A42: Umsatz Forecast | C42: =IF(MONTH($H$1)<>MONTH(TODAY()),C41,SUM(C5:C6,C8:C14,C16:C22,C24:C30,C32:C38,C40)/DAY(TODAY())*DAY(DATE(YEAR($H$1),MONTH($H$1)+1,1)-1)) -> 70003.6 | D42: =IF(MONTH($H$1)<>MONTH(TODAY()),D41,SUM(D5:D6,D8:D14,D16:D22,D24:D30,D32:D38,D40)/DAY(TODAY())*DAY(DATE(YEAR($H$1),MONTH($H$1)+1,1)-1)) -> 115000 | E42: =IF(MONTH($H$1)<>MONTH(TODAY()),E41,SUM(E5:E6,E8:E14,E16:E22,E24:E30,E32:E38,E40)/DAY(TODAY())*DAY(DATE(YEAR($H$1),MONTH($H$1)+1,1)-1)) -> 151248 | F42: =IF(MONTH($H$1)<>MONTH(TODAY()),F41,SUM(F5:F6,F8:F14,F16:F22,F24:F30,F32:F38,F40)/DAY(TODAY())*DAY(DATE(YEAR($H$1),MONTH($H$1)+1,1)-1)) -> 165000 | G42: =IF(MONTH($H$1)<>MONTH(TODAY()),G41,SUM(G5:G6,G8:G14,G16:G22,G24:G30,G32:G38,G40)/DAY(TODAY())*DAY(DATE(YEAR($H$1),MONTH($H$1)+1,1)-1)) -> 17636 | H42: =IF(MONTH($H$1)<>MONTH(TODAY()),H41,SUM(H5:H6,H8:H14,H16:H22,H24:H30,H32:H38,H40)/DAY(TODAY())*DAY(DATE(YEAR($H$1),MONTH($H$1)+1,1)-1)) -> 35000 | I42: =IF(MONTH($H$1)<>MONTH(TODAY()),I41,SUM(I5:I6,I8:I14,I16:I22,I24:I30,I32:I38,I40)/DAY(TODAY())*DAY(DATE(YEAR($H$1),MONTH($H$1)+1,1)-1)) -> 150 | J42: =IF(MONTH($H$1)<>MONTH(TODAY()),J41,SUM(J5:J6,J8:J14,J16:J22,J24:J30,J32:J38,J40)/DAY(TODAY())*DAY(DATE(YEAR($H$1),MONTH($H$1)+1,1)-1)) -> 11600 | ... T42: =IF(MONTH($H$1)<>MONTH(TODAY()),T41,SUM(T5:T6,T8:T14,T16:T22,T24:T30,T32:T38,T40)/DAY(TODAY())*DAY(DATE(YEAR($H$1),MONTH($H$1)+1,1)-1)) -> 30000 | U42: =IF(MONTH($H$1)<>MONTH(TODAY()),U41,SUM(U6:U9,U11:U17,U19:U25,U27:U33,U35:U39)/DAY(TODAY())*DAY(DATE(YEAR($H$1),MONTH($H$1)+1,1)-1)) -> 407951.68 | V42: =IF(MONTH($H$1)<>MONTH(TODAY()),V41,SUM(V6:V9,V11:V17,V19:V25,V27:V33,V35:V39)/DAY(TODAY())*DAY(DATE(YEAR($H$1),MONTH($H$1)+1,1)-1)) -> 572600 | W42: Umsatz Forecast
A43: Umsatz pro Tag | C43: =C41/31 -> 2258.1806 | D43: =D41/31 -> 3709.6774 | E43: =E41/31 -> 4878.9677 | F43: =F41/31 -> 5322.5806 | G43: =G41/31 -> 568.90323 | H43: =H41/31 -> 1129.0323 | I43: =I41/31 -> 4.8387097 | J43: =J41/31 -> 374.19355 | ... V43: =V41/31 -> 18470.968 | W43: Budget pro Tag
A44: Diff. zu Budget | C44: =SUM(C41-D41) -> -44996.4 | E44: =SUM(E41-F41) -> -13752 | G44: =SUM(G41-H41) -> -17364 | I44: =SUM(I41-J41) -> -11450 | K44: =SUM(K41-L41) -> -76719.5 | M44: =SUM(M41-N41) -> -32774.8 | O44: =SUM(O41-P41) -> 52850.08 | Q44: =SUM(Q41-R41) -> -144206.62 | S44: =SUM(S41-T41) -> -20441.7 | U44: =SUM(U41-V41) -> -164648.32
A45: Index | C45: =SUM(100/D41*C41) -> 60.872696 | E45: =SUM(100/F41*E41) -> 91.665455 | G45: =SUM(100/H41*G41) -> 50.388571 | I45: =SUM(100/J41*I41) -> 1.2931034 | K45: =SUM(100/L41*K41) -> 15.692857 | M45: =SUM(100/N41*M41) -> 6.3577143 | O45: =SUM(100/P41*O41) -> 158.72231 | Q45: =SUM(100/R41*Q41) -> 73.423034 | S45: =SUM(100/T41*S41) -> 31.861 | U45: =SUM(100/V41*U41) -> 71.245491

Sheet 06_21
A1: Tagesumsätze | H1: 44348
C3: Restaurant | E3: Terrasse | G3: Lounge | I3: Pavillon | K3: Bankett | M3: Seminar | O3: Hotel | Q3: TOTAL Gesamtbetrieb ohne Seebad | S3: Seebad | U3: TOTAL Gesamtbetrieb mit Seebad | W3: Info's
C4: IST | D4: Budget | E4: IST | F4: Budget | G4: IST | H4: Budget | I4: IST | J4: Budget | K4: IST | L4: Budget | M4: IST | N4: Budget | O4: IST | P4: Budget | Q4: IST | R4: Budget | S4: IST | T4: Budget | U4: IST | V4: Budget | W4: Wetter | X4: Temp. | Z4: Bemerkung
A5: 1 | B5: Di | C5: 3672.2 | D5: 2833.3333 | E5: 11755.5 | F5: 8666.6667 | G5: 1534.2 | H5: 1666.6667 | I5: 0 | J5: 993.33333 | K5: 0 | L5: 2586.6667 | M5: 0 | N5: 1100 | O5: 4738 | P5: 3713.3333 | Q5: =SUM(C5+E5+G5+I5+K5+M5+O5) -> 21699.9 | R5: =SUM(D5+F5+H5+J5+L5+N5+P5) -> 21560 | S5: 1943.6 | T5: 2000 | U5: =SUM(Q5+S5) -> 23643.5 | V5: =SUM(R5+T5) -> 23560 | W5: sonnig | X5: 20 | Y5: °C
A6: =SUM(A5+1) -> 2 | B6: Mi | C6: 2861.9 | D6: 2833.3333 | E6: 4589.4 | F6: 8666.6667 | G6: 879.8 | H6: 1666.6667 | I6: 0 | J6: 993.33333 | K6: 2775.6 | L6: 2586.6667 | M6: 616.1 | N6: 1100 | O6: 4137.2 | P6: 3713.3333 | Q6: =SUM(C6+E6+G6+I6+K6+M6+O6) -> 15860 | R6: =SUM(D6+F6+H6+J6+L6+N6+P6) -> 21560 | S6: 461 | T6: 2000 | U6: =SUM(Q6+S6) -> 16321 | V6: =SUM(R6+T6) -> 23560 | W6: veränderlich | X6: 18 | Y6: °C
A7: =SUM(A6+1) -> 3 | B7: Do | C7: 1116.6 | D7: 2833.3333 | E7: 14412 | F7: 8666.6667 | G7: 1435.8 | H7: 1666.6667 | I7: 0 | J7: 993.33333 | K7: 0 | L7: 2586.6667 | M7: 0 | N7: 1100 | O7: 4332.9 | P7: 3713.3333 | Q7: =SUM(C7+E7+G7+I7+K7+M7+O7) -> 21297.3 | R7: =SUM(D7+F7+H7+J7+L7+N7+P7) -> 21560 | S7: 1626.8 | T7: 2000 | U7: =SUM(Q7+S7) -> 22924.1 | V7: =SUM(R7+T7) -> 23560 | W7: sonnig | X7: 20 | Y7: °C
A8: =SUM(A7+1) -> 4 | B8: Fr | C8: 3058.4 | D8: 2833.3333 | E8: 12899.2 | F8: 8666.6667 | G8: 883.7 | H8: 1666.6667 | I8: 0 | J8: 993.33333 | K8: 513.9 | L8: 2586.6667 | M8: 0 | N8: 1100 | O8: 5772.3 | P8: 3713.3333 | Q8: =SUM(C8+E8+G8+I8+K8+M8+O8) -> 23127.5 | R8: =SUM(D8+F8+H8+J8+L8+N8+P8) -> 21560 | S8: 318.9 | T8: 2000 | U8: =SUM(Q8+S8) -> 23446.4 | V8: =SUM(R8+T8) -> 23560 | W8: veränderlich | X8: 20 | Y8: °C
A9: =SUM(A8+1) -> 5 | B9: Sa | C9: 5434.3 | D9: 2833.3333 | E9: 938.2 | F9: 8666.6667 | G9: 731.6 | H9: 1666.6667 | I9: 408 | J9: 993.33333 | K9: 5966.9 | L9: 2586.6667 | M9: 0 | N9: 1100 | O9: 4464.2 | P9: 3713.3333 | Q9: =SUM(C9+E9+G9+I9+K9+M9+O9) -> 17943.2 | R9: =SUM(D9+F9+H9+J9+L9+N9+P9) -> 21560 | S9: 0 | T9: 2000 | U9: =SUM(Q9+S9) -> 17943.2 | V9: =SUM(R9+T9) -> 23560 | W9: bewölkt | X9: 16 | Y9: °C
A10: =SUM(A9+1) -> 6 | B10: So | C10: 5750.5 | D10: 2833.3333 | E10: 7329.8 | F10: 8666.6667 | G10: 805.3 | H10: 1666.6667 | I10: 0 | J10: 993.33333 | K10: 2782.7 | L10: 2586.6667 | M10: 0 | N10: 1100 | O10: 1893.2 | P10: 3713.3333 | Q10: =SUM(C10+E10+G10+I10+K10+M10+O10) -> 18561.5 | R10: =SUM(D10+F10+H10+J10+L10+N10+P10) -> 21560 | S10: 0 | T10: 2000 | U10: =SUM(Q10+S10) -> 18561.5 | V10: =SUM(R10+T10) -> 23560 | W10: veränderlich | X10: 18 | Y10: °C
A11: KW | B11: 23 | C11: =SUM(C5:C10) -> 21893.9 | D11: =SUM(D5:D10) -> 17000 | E11: =SUM(E5:E10) -> 51924.1 | F11: =SUM(F5:F10) -> 52000 | G11: =SUM(G5:G10) -> 6270.4 | H11: =SUM(H5:H10) -> 10000 | I11: =SUM(I5:I10) -> 408 | J11: =SUM(J5:J10) -> 5960 | ... V11: =SUM(V5:V10) -> 141360 | W11: Ø Temp | X11: =SUM(X5:X10)/6 -> 18.666667 | Y11: °C
A12: =SUM(A10+1) -> 7 | B12: Mo | C12: 3624.5 | D12: 2833.3333 | E12: 450.3 | F12: 8666.6667 | G12: 152.7 | H12: 1666.6667 | I12: 0 | J12: 993.33333 | K12: 1776.8 | L12: 2586.6667 | M12: 1857.3 | N12: 1100 | O12: 2810.7 | P12: 3713.3333 | Q12: =SUM(C12+E12+G12+I12+K12+M12+O12) -> 10672.3 | R12: =SUM(D12+F12+H12+J12+L12+N12+P12) -> 21560 | S12: 0 | T12: 2000 | U12: =SUM(Q12+S12) -> 10672.3 | V12: =SUM(R12+T12) -> 23560 | W12: bewölkt | X12: 16 | Y12: °C
A13: =SUM(A12+1) -> 8 | B13: Di | C13: 3961.7 | D13: 2833.3333 | E13: 3141.9 | F13: 8666.6667 | G13: 341.1 | H13: 1666.6667 | I13: 0 | J13: 993.33333 | K13: 1741.2 | L13: 2586.6667 | M13: 901 | N13: 1100 | O13: 2397 | P13: 3713.3333 | Q13: =SUM(C13+E13+G13+I13+K13+M13+O13) -> 12483.9 | R13: =SUM(D13+F13+H13+J13+L13+N13+P13) -> 21560 | S13: 0 | T13: 2000 | U13: =SUM(Q13+S13) -> 12483.9 | V13: =SUM(R13+T13) -> 23560 | W13: ziemlich sonnig | X13: 18 | Y13: °C
A14: =SUM(A13+1) -> 9 | B14: Mi | C14: 251 | D14: 2833.3333 | E14: 7061.4 | F14: 8666.6667 | G14: 212.9 | H14: 1666.6667 | I14: 0 | J14: 993.33333 | K14: 0 | L14: 2586.6667 | M14: 5331.6 | N14: 1100 | O14: 1997.2 | P14: 3713.3333 | Q14: =SUM(C14+E14+G14+I14+K14+M14+O14) -> 14854.1 | R14: =SUM(D14+F14+H14+J14+L14+N14+P14) -> 21560 | S14: 71.2 | T14: 2000 | U14: =SUM(Q14+S14) -> 14925.3 | V14: =SUM(R14+T14) -> 23560 | W14: ziemlich sonnig | X14: 20 | Y14: °C
A15: =SUM(A14+1) -> 10 | B15: Do | C15: 1717.4 | D15: 2833.3333 | E15: 9249 | F15: 8666.6667 | G15: 1301.9 | H15: 1666.6667 | I15: 0 | J15: 993.33333 | K15: 0 | L15: 2586.6667 | M15: 4944.2 | N15: 1100 | O15: 2431.3 | P15: 3713.3333 | Q15: =SUM(C15+E15+G15+I15+K15+M15+O15) -> 19643.8 | R15: =SUM(D15+F15+H15+J15+L15+N15+P15) -> 21560 | S15: 1253.7 | T15: 2000 | U15: =SUM(Q15+S15) -> 20897.5 | V15: =SUM(R15+T15) -> 23560 | W15: sonnig | X15: 24 | Y15: °C
A16: =SUM(A15+1) -> 11 | B16: Fr | C16: 2270 | D16: 2833.3333 | E16: 12516.5 | F16: 8666.6667 | G16: 1444.8 | H16: 1666.6667 | I16: 3040.6 | J16: 993.33333 | K16: 1344.8 | L16: 2586.6667 | M16: 2427.9 | N16: 1100 | O16: 5923.2 | P16: 3713.3333 | Q16: =SUM(C16+E16+G16+I16+K16+M16+O16) -> 28967.8 | R16: =SUM(D16+F16+H16+J16+L16+N16+P16) -> 21560 | S16: 2676 | T16: 2000 | U16: =SUM(Q16+S16) -> 31643.8 | V16: =SUM(R16+T16) -> 23560 | W16: sonnig | X16: 26 | Y16: °C
A17: =SUM(A16+1) -> 12 | B17: Sa | C17: 3907.2 | D17: 2833.3333 | E17: 15967.5 | F17: 8666.6667 | G17: 1715.5 | H17: 1666.6667 | I17: 484.4 | J17: 993.33333 | K17: 2925.6 | L17: 2586.6667 | M17: 0 | N17: 1100 | O17: 6281.2 | P17: 3713.3333 | Q17: =SUM(C17+E17+G17+I17+K17+M17+O17) -> 31281.4 | R17: =SUM(D17+F17+H17+J17+L17+N17+P17) -> 21560 | S17: 4286.6 | T17: 2000 | U17: =SUM(Q17+S17) -> 35568 | V17: =SUM(R17+T17) -> 23560 | W17: sonnig | X17: 26 | Y17: °C
A18: =SUM(A17+1) -> 13 | B18: So | C18: 3742.6 | D18: 2833.3333 | E18: 17126.5 | F18: 8666.6667 | G18: 1522.9 | H18: 1666.6667 | I18: 0 | J18: 993.33333 | K18: 0 | L18: 2586.6667 | M18: 0 | N18: 1100 | O18: 3701.4 | P18: 3713.3333 | Q18: =SUM(C18+E18+G18+I18+K18+M18+O18) -> 26093.4 | R18: =SUM(D18+F18+H18+J18+L18+N18+P18) -> 21560 | S18: 6502.6 | T18: 2000 | U18: =SUM(Q18+S18) -> 32596 | V18: =SUM(R18+T18) -> 23560 | W18: sonnig | X18: 26 | Y18: °C
A19: KW | B19: =SUM(B11+1) -> 24 | C19: =SUM(C12:C18) -> 19474.4 | D19: =SUM(D12:D18) -> 19833.333 | E19: =SUM(E12:E18) -> 65513.1 | F19: =SUM(F12:F18) -> 60666.667 | G19: =SUM(G12:G18) -> 6691.8 | H19: =SUM(H12:H18) -> 11666.667 | I19: =SUM(I12:I18) -> 3525 | J19: =SUM(J12:J18) -> 6953.3333 | ... V19: =SUM(V12:V18) -> 164920 | W19: Ø Temp | X19: =SUM(X12:X18)/7 -> 22.285714 | Y19: °C
A20: =SUM(A18+1) -> 14 | B20: Mo | C20: 413.6 | D20: 2833.3333 | E20: 10622.3 | F20: 8666.6667 | G20: 988.5 | H20: 1666.6667 | I20: 0 | J20: 993.33333 | K20: 0 | L20: 2586.6667 | M20: 0 | N20: 1100 | O20: 5127.6 | P20: 3713.3333 | Q20: =SUM(C20+E20+G20+I20+K20+M20+O20) -> 17152 | R20: =SUM(D20+F20+H20+J20+L20+N20+P20) -> 21560 | S20: 3587.7 | T20: 2000 | U20: =SUM(Q20+S20) -> 20739.7 | V20: =SUM(R20+T20) -> 23560 | W20: sonnig | X20: 28 | Y20: °C
A21: =SUM(A20+1) -> 15 | B21: Di | C21: 1720.7 | D21: 2833.3333 | E21: 11367.98 | F21: 8666.6667 | G21: 1199.3 | H21: 1666.6667 | I21: 0 | J21: 993.33333 | K21: 135.8 | L21: 2586.6667 | M21: 0 | N21: 1100 | O21: 4667.1 | P21: 3713.3333 | Q21: =SUM(C21+E21+G21+I21+K21+M21+O21) -> 19090.88 | R21: =SUM(D21+F21+H21+J21+L21+N21+P21) -> 21560 | S21: 4218.7 | T21: 2000 | U21: =SUM(Q21+S21) -> 23309.58 | V21: =SUM(R21+T21) -> 23560 | W21: sonnig | X21: 28 | Y21: °C
A22: =SUM(A21+1) -> 16 | B22: Mi | C22: 1661.2 | D22: 2833.3333 | E22: 10939.22 | F22: 8666.6667 | G22: 1245.7 | H22: 1666.6667 | I22: 0 | J22: 993.33333 | K22: 0 | L22: 2586.6667 | M22: 0 | N22: 1100 | O22: 4813.5 | P22: 3713.3333 | Q22: =SUM(C22+E22+G22+I22+K22+M22+O22) -> 18659.62 | R22: =SUM(D22+F22+H22+J22+L22+N22+P22) -> 21560 | S22: 5237.6 | T22: 2000 | U22: =SUM(Q22+S22) -> 23897.22 | V22: =SUM(R22+T22) -> 23560 | W22: sonnig | X22: 31 | Y22: °C
A23: =SUM(A22+1) -> 17 | B23: Do | C23: 1488.8 | D23: 2833.3333 | E23: 10986.5 | F23: 8666.6667 | G23: 939.2 | H23: 1666.6667 | I23: 0 | J23: 993.33333 | K23: 0 | L23: 2586.6667 | M23: 0 | N23: 1100 | O23: 3688.1 | P23: 3713.3333 | Q23: =SUM(C23+E23+G23+I23+K23+M23+O23) -> 17102.6 | R23: =SUM(D23+F23+H23+J23+L23+N23+P23) -> 21560 | S23: 4417.2 | T23: 2000 | U23: =SUM(Q23+S23) -> 21519.8 | V23: =SUM(R23+T23) -> 23560 | W23: sonnig | X23: 30 | Y23: °C
A24: =SUM(A23+1) -> 18 | B24: Fr | C24: 592.4 | D24: 2833.3333 | E24: 11927.8 | F24: 8666.6667 | G24: 1355.6 | H24: 1666.6667 | I24: 0 | J24: 993.33333 | K24: 3504.3 | L24: 2586.6667 | M24: 1548.1 | N24: 1100 | O24: 5827.4 | P24: 3713.3333 | Q24: =SUM(C24+E24+G24+I24+K24+M24+O24) -> 24755.6 | R24: =SUM(D24+F24+H24+J24+L24+N24+P24) -> 21560 | S24: 3120.8 | T24: 2000 | U24: =SUM(Q24+S24) -> 27876.4 | V24: =SUM(R24+T24) -> 23560 | W24: sonnig | X24: 30 | Y24: °C
A25: =SUM(A24+1) -> 19 | B25: Sa | C25: 1178.7 | D25: 2833.3333 | E25: 14715.4 | F25: 8666.6667 | G25: 2282 | H25: 1666.6667 | I25: 0 | J25: 993.33333 | K25: 1103.5 | L25: 2586.6667 | M25: 0 | N25: 1100 | O25: 6102.7 | P25: 3713.3333 | Q25: =SUM(C25+E25+G25+I25+K25+M25+O25) -> 25382.3 | R25: =SUM(D25+F25+H25+J25+L25+N25+P25) -> 21560 | S25: 7311.8 | T25: 2000 | U25: =SUM(Q25+S25) -> 32694.1 | V25: =SUM(R25+T25) -> 23560 | W25: bedeckt | X25: 28 | Y25: °C
A26: =SUM(A25+1) -> 20 | B26: So | C26: 2401.3 | D26: 2833.3333 | E26: 12551.1 | F26: 8666.6667 | G26: 1048.1 | H26: 1666.6667 | I26: 0 | J26: 993.33333 | K26: 4255.6 | L26: 2586.6667 | M26: 0 | N26: 1100 | O26: 2276.8 | P26: 3713.3333 | Q26: =SUM(C26+E26+G26+I26+K26+M26+O26) -> 22532.9 | R26: =SUM(D26+F26+H26+J26+L26+N26+P26) -> 21560 | S26: 3471 | T26: 2000 | U26: =SUM(Q26+S26) -> 26003.9 | V26: =SUM(R26+T26) -> 23560 | W26: sonnig, nachm. Gewitter | X26: 30 | Y26: °C
A27: KW | B27: =SUM(B19+1) -> 25 | C27: =SUM(C20:C26) -> 9456.7 | D27: =SUM(D20:D26) -> 19833.333 | E27: =SUM(E20:E26) -> 83110.3 | F27: =SUM(F20:F26) -> 60666.667 | G27: =SUM(G20:G26) -> 9058.4 | H27: =SUM(H20:H26) -> 11666.667 | I27: =SUM(I20:I26) -> 0 | J27: =SUM(J20:J26) -> 6953.3333 | ... V27: =SUM(V20:V26) -> 164920 | W27: Ø Temp | X27: =SUM(X20:X26)/7 -> 29.285714 | Y27: °C
A28: =SUM(A26+1) -> 21 | B28: Mo | C28: 3344 | D28: 2833.3333 | E28: 4263.2 | F28: 8666.6667 | G28: 515.5 | H28: 1666.6667 | I28: 0 | J28: 993.33333 | K28: 2724.6 | L28: 2586.6667 | M28: 0 | N28: 1100 | O28: 2482.3 | P28: 3713.3333 | Q28: =SUM(C28+E28+G28+I28+K28+M28+O28) -> 13329.6 | R28: =SUM(D28+F28+H28+J28+L28+N28+P28) -> 21560 | S28: 1168 | T28: 2000 | U28: =SUM(Q28+S28) -> 14497.6 | V28: =SUM(R28+T28) -> 23560 | W28: bewölkt | X28: 24 | Y28: °C
A29: =SUM(A28+1) -> 22 | B29: Di | C29: 2396.5 | D29: 2833.3333 | E29: 8413.1 | F29: 8666.6667 | G29: 214.9 | H29: 1666.6667 | I29: 0 | J29: 993.33333 | K29: 1286.7 | L29: 2586.6667 | M29: 1365 | N29: 1100 | O29: 2959.6 | P29: 3713.3333 | Q29: =SUM(C29+E29+G29+I29+K29+M29+O29) -> 16635.8 | R29: =SUM(D29+F29+H29+J29+L29+N29+P29) -> 21560 | S29: 319.2 | T29: 2000 | U29: =SUM(Q29+S29) -> 16955 | V29: =SUM(R29+T29) -> 23560 | W29: bewölkt | X29: 20 | Y29: °C
A30: =SUM(A29+1) -> 23 | B30: Mi | C30: 1777.4 | D30: 2833.3333 | E30: 6375.3 | F30: 8666.6667 | G30: 640.8 | H30: 1666.6667 | I30: 0 | J30: 993.33333 | K30: 615.3 | L30: 2586.6667 | M30: 595.7 | N30: 1100 | O30: 2305.8 | P30: 3713.3333 | Q30: =SUM(C30+E30+G30+I30+K30+M30+O30) -> 12310.3 | R30: =SUM(D30+F30+H30+J30+L30+N30+P30) -> 21560 | S30: 0 | T30: 2000 | U30: =SUM(Q30+S30) -> 12310.3 | V30: =SUM(R30+T30) -> 23560 | W30: Regen | X30: 20 | Y30: °C
A31: =SUM(A30+1) -> 24 | B31: Do | C31: 5996.2 | D31: 2833.3333 | E31: 3837.4 | F31: 8666.6667 | G31: 519.5 | H31: 1666.6667 | I31: 0 | J31: 993.33333 | K31: 4501.3 | L31: 2586.6667 | M31: 88 | N31: 1100 | O31: 2433.1 | P31: 3713.3333 | Q31: =SUM(C31+E31+G31+I31+K31+M31+O31) -> 17375.5 | R31: =SUM(D31+F31+H31+J31+L31+N31+P31) -> 21560 | S31: 0 | T31: 2000 | U31: =SUM(Q31+S31) -> 17375.5 | V31: =SUM(R31+T31) -> 23560 | W31: Regen | X31: 18 | Y31: °C
A32: =SUM(A31+1) -> 25 | B32: Fr | C32: 2743.6 | D32: 2833.3333 | E32: 7334.3 | F32: 8666.6667 | G32: 911.5 | H32: 1666.6667 | I32: 2593.8 | J32: 993.33333 | K32: 2453.5 | L32: 2586.6667 | M32: 0 | N32: 1100 | O32: 6265.9 | P32: 3713.3333 | Q32: =SUM(C32+E32+G32+I32+K32+M32+O32) -> 22302.6 | R32: =SUM(D32+F32+H32+J32+L32+N32+P32) -> 21560 | S32: 0 | T32: 2000 | U32: =SUM(Q32+S32) -> 22302.6 | V32: =SUM(R32+T32) -> 23560 | W32: bewölkt | X32: 20 | Y32: °C
A33: =SUM(A32+1) -> 26 | B33: Sa | C33: 6090.4 | D33: 2833.3333 | E33: 15988.1 | F33: 8666.6667 | G33: 2086.1 | H33: 1666.6667 | I33: 0 | J33: 993.33333 | K33: 2057.6 | L33: 2586.6667 | M33: 0 | N33: 1100 | O33: 7025.3 | P33: 3713.3333 | Q33: =SUM(C33+E33+G33+I33+K33+M33+O33) -> 33247.5 | R33: =SUM(D33+F33+H33+J33+L33+N33+P33) -> 21560 | S33: 1692.9 | T33: 2000 | U33: =SUM(Q33+S33) -> 34940.4 | V33: =SUM(R33+T33) -> 23560 | W33: sonnig | X33: 24 | Y33: °C
A34: =SUM(A33+1) -> 27 | B34: So | C34: 3392.6 | D34: 2833.3333 | E34: 16205.3 | F34: 8666.6667 | G34: 2475.6 | H34: 1666.6667 | I34: 0 | J34: 993.33333 | K34: 2899.8 | L34: 2586.6667 | M34: 0 | N34: 1100 | O34: 4225.1 | P34: 3713.3333 | Q34: =SUM(C34+E34+G34+I34+K34+M34+O34) -> 29198.4 | R34: =SUM(D34+F34+H34+J34+L34+N34+P34) -> 21560 | S34: 8690.9 | T34: 2000 | U34: =SUM(Q34+S34) -> 37889.3 | V34: =SUM(R34+T34) -> 23560 | W34: sonnig | X34: 29 | Y34: °C
A35: KW | B35: =SUM(B27+1) -> 26 | C35: =SUM(C28:C34) -> 25740.7 | D35: =SUM(D28:D34) -> 19833.333 | E35: =SUM(E28:E34) -> 62416.7 | F35: =SUM(F28:F34) -> 60666.667 | G35: =SUM(G28:G34) -> 7363.9 | H35: =SUM(H28:H34) -> 11666.667 | I35: =SUM(I28:I34) -> 2593.8 | J35: =SUM(J28:J34) -> 6953.3333 | ... V35: =SUM(V28:V34) -> 164920 | W35: Ø Temp | X35: =SUM(X28:X34)/7 -> 22.142857 | Y35: °C
A36: =SUM(A34+1) -> 28 | B36: Mo | C36: 2842.6 | D36: 2833.3333 | E36: 4475.7 | F36: 8666.6667 | G36: 591.2 | H36: 1666.6667 | I36: 0 | J36: 993.33333 | K36: 2344.3 | L36: 2586.6667 | M36: 0 | N36: 1100 | O36: 4765.7 | P36: 3713.3333 | Q36: =SUM(C36+E36+G36+I36+K36+M36+O36) -> 15019.5 | R36: =SUM(D36+F36+H36+J36+L36+N36+P36) -> 21560 | S36: 1094 | T36: 2000 | U36: =SUM(Q36+S36) -> 16113.5 | V36: =SUM(R36+T36) -> 23560 | W36: sonnig, Jahrhundert Hagel | X36: 28 | Y36: °C
A37: =SUM(A36+1) -> 29 | B37: Di | C37: 4713.6 | D37: 2833.3333 | E37: 2191.1 | F37: 8666.6667 | G37: 115.5 | H37: 1666.6667 | I37: 0 | J37: 993.33333 | K37: 4201.9 | L37: 2586.6667 | M37: 0 | N37: 1100 | O37: 5810.3 | P37: 3713.3333 | Q37: =SUM(C37+E37+G37+I37+K37+M37+O37) -> 17032.4 | R37: =SUM(D37+F37+H37+J37+L37+N37+P37) -> 21560 | S37: 0 | T37: 2000 | U37: =SUM(Q37+S37) -> 17032.4 | V37: =SUM(R37+T37) -> 23560 | W37: sonnig | X37: 20 | Y37: °C
A38: =SUM(A37+1) -> 30 | B38: Mi | C38: 4607.8 | D38: 2833.3333 | E38: 1338 | F38: 8666.6667 | G38: 207 | H38: 1666.6667 | I38: 0 | J38: 993.33333 | K38: 3604.5 | L38: 2586.6667 | M38: 0 | N38: 1100 | O38: 4666.72 | P38: 3713.3333 | Q38: =SUM(C38+E38+G38+I38+K38+M38+O38) -> 14424.02 | R38: =SUM(D38+F38+H38+J38+L38+N38+P38) -> 21560 | S38: 0 | T38: 2000 | U38: =SUM(Q38+S38) -> 14424.02 | V38: =SUM(R38+T38) -> 23560 | W38: wechselnd bewölkt | X38: 24 | Y38: °C
A39: KW | B39: =SUM(B35+1) -> 27 | C39: =SUM(C36:C38) -> 12164 | D39: =SUM(D36:D38) -> 8500 | E39: =SUM(E36:E38) -> 8004.8 | F39: =SUM(F36:F38) -> 26000 | G39: =SUM(G36:G38) -> 913.7 | H39: =SUM(H36:H38) -> 5000 | I39: =SUM(I36:I38) -> 0 | J39: =SUM(J36:J38) -> 2980 | ... V39: =SUM(V36:V38) -> 70680 | W39: Ø Temp | X39: =SUM(X36:X38)/3 -> 24 | Y39: °C
A40: Umsatz kumuliert | C40: =SUM(C11+C19+C27+C35+C39) -> 88729.7 | D40: =SUM(D11+D19+D27+D35+D39) -> 85000 | E40: =SUM(E11+E19+E27+E35+E39) -> 270969 | F40: =SUM(F11+F19+F27+F35+F39) -> 260000 | G40: =SUM(G11+G19+G27+G35+G39) -> 30298.2 | H40: =SUM(H11+H19+H27+H35+H39) -> 50000 | I40: =SUM(I11+I19+I27+I35+I39) -> 6526.8 | J40: =SUM(J11+J19+J27+J35+J39) -> 29800 | ... V40: =SUM(V11+V19+V27+V35+V39) -> 706800 | W40: Umsatz kumuliert
A41: Umsatz Forecast | C41: =IF(MONTH($H$1)<>MONTH(TODAY()),C40,SUM(C5:C10,C12:C18,C20:C26,C28:C34,C36:C38)/DAY(TODAY())*DAY(DATE(YEAR($H$1),MONTH($H$1)+1,1)-1)) -> 88729.7 | D41: =IF(MONTH($H$1)<>MONTH(TODAY()),D40,SUM(D5:D10,D12:D18,D20:D26,D28:D34,D36:D38)/DAY(TODAY())*DAY(DATE(YEAR($H$1),MONTH($H$1)+1,1)-1)) -> 85000 | E41: =IF(MONTH($H$1)<>MONTH(TODAY()),E40,SUM(E5:E10,E12:E18,E20:E26,E28:E34,E36:E38)/DAY(TODAY())*DAY(DATE(YEAR($H$1),MONTH($H$1)+1,1)-1)) -> 270969 | F41: =IF(MONTH($H$1)<>MONTH(TODAY()),F40,SUM(F5:F10,F12:F18,F20:F26,F28:F34,F36:F38)/DAY(TODAY())*DAY(DATE(YEAR($H$1),MONTH($H$1)+1,1)-1)) -> 260000 | G41: =IF(MONTH($H$1)<>MONTH(TODAY()),G40,SUM(G5:G10,G12:G18,G20:G26,G28:G34,G36:G38)/DAY(TODAY())*DAY(DATE(YEAR($H$1),MONTH($H$1)+1,1)-1)) -> 30298.2 | H41: =IF(MONTH($H$1)<>MONTH(TODAY()),H40,SUM(H5:H10,H12:H18,H20:H26,H28:H34,H36:H38)/DAY(TODAY())*DAY(DATE(YEAR($H$1),MONTH($H$1)+1,1)-1)) -> 50000 | I41: =IF(MONTH($H$1)<>MONTH(TODAY()),I40,SUM(I5:I10,I12:I18,I20:I26,I28:I34,I36:I38)/DAY(TODAY())*DAY(DATE(YEAR($H$1),MONTH($H$1)+1,1)-1)) -> 6526.8 | J41: =IF(MONTH($H$1)<>MONTH(TODAY()),J40,SUM(J5:J10,J12:J18,J20:J26,J28:J34,J36:J38)/DAY(TODAY())*DAY(DATE(YEAR($H$1),MONTH($H$1)+1,1)-1)) -> 29800 | ... T41: =IF(MONTH($H$1)<>MONTH(TODAY()),T40,SUM(T5:T10,T12:T18,T20:T26,T28:T34,T36:T38)/DAY(TODAY())*DAY(DATE(YEAR($H$1),MONTH($H$1)+1,1)-1)) -> 60000 | U41: =IF(MONTH($H$1)<>MONTH(TODAY()),U40,SUM(U5:U8,U10:U16,U18:U24,U26:U32,U34:U38)/DAY(TODAY())*DAY(DATE(YEAR($H$1),MONTH($H$1)+1,1)-1)) -> 661507.82 | V41: =IF(MONTH($H$1)<>MONTH(TODAY()),V40,SUM(V5:V8,V10:V16,V18:V24,V26:V32,V34:V38)/DAY(TODAY())*DAY(DATE(YEAR($H$1),MONTH($H$1)+1,1)-1)) -> 706800 | W41: Umsatz Forecast
A42: Umsatz pro Tag | C42: =C40/30 -> 2957.6567 | D42: =D40/30 -> 2833.3333 | E42: =E40/30 -> 9032.3 | F42: =F40/30 -> 8666.6667 | G42: =G40/30 -> 1009.94 | H42: =H40/30 -> 1666.6667 | I42: =I40/30 -> 217.56 | J42: =J40/30 -> 993.33333 | ... V42: =V40/30 -> 23560 | W42: Budget pro Tag
A43: Diff. zu Budget | C43: =SUM(C40-D40) -> 3729.7 | E43: =SUM(E40-F40) -> 10969 | G43: =SUM(G40-H40) -> -19701.8 | I43: =SUM(I40-J40) -> -23273.2 | K43: =SUM(K40-L40) -> -22083.8 | M43: =SUM(M40-N40) -> -13325.1 | O43: =SUM(O40-P40) -> 14922.82 | Q43: =SUM(Q40-R40) -> -48762.38 | S43: =SUM(S40-T40) -> 3470.2 | U43: =SUM(U40-V40) -> -45292.18
A44: Index | C44: =SUM(100/D40*C40) -> 104.38788 | E44: =SUM(100/F40*E40) -> 104.21885 | G44: =SUM(100/H40*G40) -> 60.5964 | I44: =SUM(100/J40*I40) -> 21.902013 | K44: =SUM(100/L40*K40) -> 71.541495 | M44: =SUM(100/N40*M40) -> 59.620909 | O44: =SUM(100/P40*O40) -> 113.39571 | Q44: =SUM(100/R40*Q40) -> 92.46098 | S44: =SUM(100/T40*S40) -> 105.78367 | U44: =SUM(100/V40*U40) -> 93.591938

Sheet 07_21
A1: Tagesumsätze | H1: 44378
C3: Restaurant | E3: Terrasse | G3: Lounge | I3: Pavillon | K3: Bankett | M3: Seminar | O3: Hotel | Q3: TOTAL Gesamtbetrieb ohne Seebad | S3: Seebad | U3: TOTAL Gesamtbetrieb mit Seebad | W3: Info's
C4: IST | D4: Budget | E4: IST | F4: Budget | G4: IST | H4: Budget | I4: IST | J4: Budget | K4: IST | L4: Budget | M4: IST | N4: Budget | O4: IST | P4: Budget | Q4: IST | R4: Budget | S4: IST | T4: Budget | U4: IST | V4: Budget | W4: Wetter | X4: Temp. | Z4: Bemerkung
A5: 1 | B5: Do | C5: 3300.5 | D5: 2903.2258 | E5: 5755.1 | F5: 10322.581 | G5: 949.7 | H5: 1612.9032 | I5: 0 | J5: 645.16129 | K5: 3939.9 | L5: 3045.1613 | M5: 1104 | N5: 387.09677 | O5: 3500.7 | P5: 4435.4839 | Q5: =SUM(C5+E5+G5+I5+K5+M5+O5) -> 18549.9 | R5: =SUM(D5+F5+H5+J5+L5+N5+P5) -> 23351.613 | S5: 0 | T5: 2419.3548 | U5: =SUM(Q5+S5) -> 18549.9 | V5: =SUM(R5+T5) -> 25770.968 | W5: wechselnd bewölkt | X5: 20 | Y5: °C
A6: =SUM(A5+1) -> 2 | B6: Fr | C6: 739.5 | D6: 2903.2258 | E6: 12442.4 | F6: 10322.581 | G6: 1004.5 | H6: 1612.9032 | I6: 0 | J6: 645.16129 | K6: 1218.9 | L6: 3045.1613 | M6: 360 | N6: 387.09677 | O6: 5907.4 | P6: 4435.4839 | Q6: =SUM(C6+E6+G6+I6+K6+M6+O6) -> 21672.7 | R6: =SUM(D6+F6+H6+J6+L6+N6+P6) -> 23351.613 | S6: 1374.1 | T6: 2419.3548 | U6: =SUM(Q6+S6) -> 23046.8 | V6: =SUM(R6+T6) -> 25770.968 | W6: ziemlich sonnig | X6: 23 | Y6: °C
A7: =SUM(A6+1) -> 3 | B7: Sa | C7: 4538.9 | D7: 2903.2258 | E7: 8813.8 | F7: 10322.581 | G7: 1676.9 | H7: 1612.9032 | I7: 4373.5 | J7: 645.16129 | K7: 4465.3 | L7: 3045.1613 | M7: 100 | N7: 387.09677 | O7: 5256.1 | P7: 4435.4839 | Q7: =SUM(C7+E7+G7+I7+K7+M7+O7) -> 29224.5 | R7: =SUM(D7+F7+H7+J7+L7+N7+P7) -> 23351.613 | S7: 1476.1 | T7: 2419.3548 | U7: =SUM(Q7+S7) -> 30700.6 | V7: =SUM(R7+T7) -> 25770.968 | W7: sonnig, Regen | X7: 20 | Y7: °C
A8: =SUM(A7+1) -> 4 | B8: So | C8: 5243.6 | D8: 2903.2258 | E8: 6382.8 | F8: 10322.581 | G8: 337.3 | H8: 1612.9032 | I8: 2850 | J8: 645.16129 | K8: 8208.8 | L8: 3045.1613 | M8: 0 | N8: 387.09677 | O8: 3927.3 | P8: 4435.4839 | Q8: =SUM(C8+E8+G8+I8+K8+M8+O8) -> 26949.8 | R8: =SUM(D8+F8+H8+J8+L8+N8+P8) -> 23351.613 | S8: 0 | T8: 2419.3548 | U8: =SUM(Q8+S8) -> 26949.8 | V8: =SUM(R8+T8) -> 25770.968 | W8: wechselnd bewölkt | X8: 20 | Y8: °C
A9: KW | B9: 27 | C9: =SUM(C5:C8) -> 13822.5 | D9: =SUM(D5:D8) -> 11612.903 | E9: =SUM(E5:E8) -> 33394.1 | F9: =SUM(F5:F8) -> 41290.323 | G9: =SUM(G5:G8) -> 3968.4 | H9: =SUM(H5:H8) -> 6451.6129 | I9: =SUM(I5:I8) -> 7223.5 | J9: =SUM(J5:J8) -> 2580.6452 | ... V9: =SUM(V5:V8) -> 103083.87 | W9: Ø Temp | X9: =SUM(X5:X8)/4 -> 20.75 | Y9: °C
A10: =SUM(A8+1) -> 5 | B10: Mo | C10: 904 | D10: 2903.2258 | E10: 11343.7 | F10: 10322.581 | G10: 912.5 | H10: 1612.9032 | I10: 0 | J10: 645.16129 | K10: 1307 | L10: 3045.1613 | M10: 75 | N10: 387.09677 | O10: 4309.3 | P10: 4435.4839 | Q10: =SUM(C10+E10+G10+I10+K10+M10+O10) -> 18851.5 | R10: =SUM(D10+F10+H10+J10+L10+N10+P10) -> 23351.613 | S10: 509.7 | T10: 2419.3548 | U10: =SUM(Q10+S10) -> 19361.2 | V10: =SUM(R10+T10) -> 25770.968 | W10: bewölkt | X10: 20 | Y10: °C
A11: =SUM(A10+1) -> 6 | B11: Di | C11: 3294.2 | D11: 2903.2258 | E11: 3795.7 | F11: 10322.581 | G11: 619 | H11: 1612.9032 | I11: 0 | J11: 645.16129 | K11: 1946.6 | L11: 3045.1613 | M11: 1301.1 | N11: 387.09677 | O11: 4418.5 | P11: 4435.4839 | Q11: =SUM(C11+E11+G11+I11+K11+M11+O11) -> 15375.1 | R11: =SUM(D11+F11+H11+J11+L11+N11+P11) -> 23351.613 | S11: 363 | T11: 2419.3548 | U11: =SUM(Q11+S11) -> 15738.1 | V11: =SUM(R11+T11) -> 25770.968 | W11: bewölkt | X11: 20 | Y11: °C
A12: =SUM(A11+1) -> 7 | B12: Mi | C12: 6598.4 | D12: 2903.2258 | E12: 2417.9 | F12: 10322.581 | G12: 176.3 | H12: 1612.9032 | I12: 0 | J12: 645.16129 | K12: 5927.4 | L12: 3045.1613 | M12: 549.4 | N12: 387.09677 | O12: 4656.1 | P12: 4435.4839 | Q12: =SUM(C12+E12+G12+I12+K12+M12+O12) -> 20325.5 | R12: =SUM(D12+F12+H12+J12+L12+N12+P12) -> 23351.613 | S12: 0 | T12: 2419.3548 | U12: =SUM(Q12+S12) -> 20325.5 | V12: =SUM(R12+T12) -> 25770.968 | W12: bewölkt | X12: 20 | Y12: °C
A13: =SUM(A12+1) -> 8 | B13: Do | C13: 6009.7 | D13: 2903.2258 | E13: 645 | F13: 10322.581 | G13: 82.9 | H13: 1612.9032 | I13: 0 | J13: 645.16129 | K13: 5752.9 | L13: 3045.1613 | M13: 0 | N13: 387.09677 | O13: 5089.5 | P13: 4435.4839 | Q13: =SUM(C13+E13+G13+I13+K13+M13+O13) -> 17580 | R13: =SUM(D13+F13+H13+J13+L13+N13+P13) -> 23351.613 | S13: 0 | T13: 2419.3548 | U13: =SUM(Q13+S13) -> 17580 | V13: =SUM(R13+T13) -> 25770.968 | W13: bewölkt | X13: 20 | Y13: °C
A14: =SUM(A13+1) -> 9 | B14: Fr | C14: 3056.5 | D14: 2903.2258 | E14: 10913 | F14: 10322.581 | G14: 862.1 | H14: 1612.9032 | I14: 0 | J14: 645.16129 | K14: 2315.1 | L14: 3045.1613 | M14: 0 | N14: 387.09677 | O14: 5991.7 | P14: 4435.4839 | Q14: =SUM(C14+E14+G14+I14+K14+M14+O14) -> 23138.4 | R14: =SUM(D14+F14+H14+J14+L14+N14+P14) -> 23351.613 | S14: 346.5 | T14: 2419.3548 | U14: =SUM(Q14+S14) -> 23484.9 | V14: =SUM(R14+T14) -> 25770.968 | W14: sonnig | X14: 24 | Y14: °C
A15: =SUM(A14+1) -> 10 | B15: Sa | C15: 3422.2 | D15: 2903.2258 | E15: 16379.1 | F15: 10322.581 | G15: 2082.5 | H15: 1612.9032 | I15: 2248 | J15: 645.16129 | K15: 6547.2 | L15: 3045.1613 | M15: 0 | N15: 387.09677 | O15: 5454.7 | P15: 4435.4839 | Q15: =SUM(C15+E15+G15+I15+K15+M15+O15) -> 36133.7 | R15: =SUM(D15+F15+H15+J15+L15+N15+P15) -> 23351.613 | S15: 3322.1 | T15: 2419.3548 | U15: =SUM(Q15+S15) -> 39455.8 | V15: =SUM(R15+T15) -> 25770.968 | W15: sonnig | X15: 24 | Y15: °C
A16: =SUM(A15+1) -> 11 | B16: So | C16: 3331 | D16: 2903.2258 | E16: 16172.4 | F16: 10322.581 | G16: 1936 | H16: 1612.9032 | I16: 600 | J16: 645.16129 | K16: 2413.1 | L16: 3045.1613 | M16: 75 | N16: 387.09677 | O16: 2324.3 | P16: 4435.4839 | Q16: =SUM(C16+E16+G16+I16+K16+M16+O16) -> 26851.8 | R16: =SUM(D16+F16+H16+J16+L16+N16+P16) -> 23351.613 | S16: 2905.6 | T16: 2419.3548 | U16: =SUM(Q16+S16) -> 29757.4 | V16: =SUM(R16+T16) -> 25770.968 | W16: ziemlich sonnig | X16: 23 | Y16: °C
A17: KW | B17: =SUM(B9+1) -> 28 | C17: =SUM(C10:C16) -> 26616 | D17: =SUM(D10:D16) -> 20322.581 | E17: =SUM(E10:E16) -> 61666.8 | F17: =SUM(F10:F16) -> 72258.065 | G17: =SUM(G10:G16) -> 6671.3 | H17: =SUM(H10:H16) -> 11290.323 | I17: =SUM(I10:I16) -> 2848 | J17: =SUM(J10:J16) -> 4516.129 | ... V17: =SUM(V10:V16) -> 180396.77 | W17: Ø Temp | X17: =SUM(X10:X16)/7 -> 21.571429 | Y17: °C
A18: =SUM(A16+1) -> 12 | B18: Mo | C18: 1248.2 | D18: 2903.2258 | E18: 11664.4 | F18: 10322.581 | G18: 1520.8 | H18: 1612.9032 | I18: 0 | J18: 645.16129 | K18: 225 | L18: 3045.1613 | M18: 0 | N18: 387.09677 | O18: 4780.7 | P18: 4435.4839 | Q18: =SUM(C18+E18+G18+I18+K18+M18+O18) -> 19439.1 | R18: =SUM(D18+F18+H18+J18+L18+N18+P18) -> 23351.613 | S18: 2235.7 | T18: 2419.3548 | U18: =SUM(Q18+S18) -> 21674.8 | V18: =SUM(R18+T18) -> 25770.968 | W18: sonnig | X18: 24 | Y18: °C
A19: =SUM(A18+1) -> 13 | B19: Di | C19: 6802.5 | D19: 2903.2258 | E19: 0 | F19: 10322.581 | G19: -12 | H19: 1612.9032 | I19: 0 | J19: 645.16129 | K19: 5503.1 | L19: 3045.1613 | M19: 0 | N19: 387.09677 | O19: 4936.5 | P19: 4435.4839 | Q19: =SUM(C19+E19+G19+I19+K19+M19+O19) -> 17230.1 | R19: =SUM(D19+F19+H19+J19+L19+N19+P19) -> 23351.613 | S19: 0 | T19: 2419.3548 | U19: =SUM(Q19+S19) -> 17230.1 | V19: =SUM(R19+T19) -> 25770.968 | W19: Regen | X19: 14 | Y19: °C | Z19: Hochwasser
A20: =SUM(A19+1) -> 14 | B20: Mi | C20: 4646.9 | D20: 2903.2258 | E20: 1944.3 | F20: 10322.581 | G20: 387.4 | H20: 1612.9032 | I20: 0 | J20: 645.16129 | K20: 5109.4 | L20: 3045.1613 | M20: 0 | N20: 387.09677 | O20: 4360.5 | P20: 4435.4839 | Q20: =SUM(C20+E20+G20+I20+K20+M20+O20) -> 16448.5 | R20: =SUM(D20+F20+H20+J20+L20+N20+P20) -> 23351.613 | S20: 0 | T20: 2419.3548 | U20: =SUM(Q20+S20) -> 16448.5 | V20: =SUM(R20+T20) -> 25770.968 | W20: Regen | X20: 18 | Y20: °C | Z20: Hochwasser
A21: =SUM(A20+1) -> 15 | B21: Do | C21: 6994.3 | D21: 2903.2258 | E21: 0 | F21: 10322.581 | G21: 53.4 | H21: 1612.9032 | I21: 0 | J21: 645.16129 | K21: 5364.1 | L21: 3045.1613 | M21: 0 | N21: 387.09677 | O21: 3009.9 | P21: 4435.4839 | Q21: =SUM(C21+E21+G21+I21+K21+M21+O21) -> 15421.7 | R21: =SUM(D21+F21+H21+J21+L21+N21+P21) -> 23351.613 | S21: 0 | T21: 2419.3548 | U21: =SUM(Q21+S21) -> 15421.7 | V21: =SUM(R21+T21) -> 25770.968 | W21: Regen | X21: 20 | Y21: °C | Z21: Hochwasser
A22: =SUM(A21+1) -> 16 | B22: Fr | C22: 7103.9 | D22: 2903.2258 | E22: 2889.2 | F22: 10322.581 | G22: 516 | H22: 1612.9032 | I22: 351.1 | J22: 645.16129 | K22: 4950.5 | L22: 3045.1613 | M22: 0 | N22: 387.09677 | O22: 4439.1 | P22: 4435.4839 | Q22: =SUM(C22+E22+G22+I22+K22+M22+O22) -> 20249.8 | R22: =SUM(D22+F22+H22+J22+L22+N22+P22) -> 23351.613 | S22: 0 | T22: 2419.3548 | U22: =SUM(Q22+S22) -> 20249.8 | V22: =SUM(R22+T22) -> 25770.968 | W22: Regen | X22: 22 | Y22: °C | Z22: Hochwasser
A23: =SUM(A22+1) -> 17 | B23: Sa | C23: 6967.6 | D23: 2903.2258 | E23: 3093.7 | F23: 10322.581 | G23: 584.1 | H23: 1612.9032 | I23: 0 | J23: 645.16129 | K23: 9716.7 | L23: 3045.1613 | M23: 75 | N23: 387.09677 | O23: 6472.8 | P23: 4435.4839 | Q23: =SUM(C23+E23+G23+I23+K23+M23+O23) -> 26909.9 | R23: =SUM(D23+F23+H23+J23+L23+N23+P23) -> 23351.613 | S23: 0 | T23: 2419.3548 | U23: =SUM(Q23+S23) -> 26909.9 | V23: =SUM(R23+T23) -> 25770.968 | W23: Regen | X23: 24 | Y23: °C | Z23: Hochwasser
A24: =SUM(A23+1) -> 18 | B24: So | C24: 1746.6 | D24: 2903.2258 | E24: 14939.9 | F24: 10322.581 | G24: 2269.6 | H24: 1612.9032 | I24: 0 | J24: 645.16129 | K24: 4658.2 | L24: 3045.1613 | M24: 0 | N24: 387.09677 | O24: 3985.6 | P24: 4435.4839 | Q24: =SUM(C24+E24+G24+I24+K24+M24+O24) -> 27599.9 | R24: =SUM(D24+F24+H24+J24+L24+N24+P24) -> 23351.613 | S24: 1044.3 | T24: 2419.3548 | U24: =SUM(Q24+S24) -> 28644.2 | V24: =SUM(R24+T24) -> 25770.968 | W24: sonnig | X24: 25 | Y24: °C
A25: KW | B25: =SUM(B17+1) -> 29 | C25: =SUM(C18:C24) -> 35510 | D25: =SUM(D18:D24) -> 20322.581 | E25: =SUM(E18:E24) -> 34531.5 | F25: =SUM(F18:F24) -> 72258.065 | G25: =SUM(G18:G24) -> 5319.3 | H25: =SUM(H18:H24) -> 11290.323 | I25: =SUM(I18:I24) -> 351.1 | J25: =SUM(J18:J24) -> 4516.129 | ... V25: =SUM(V18:V24) -> 180396.77 | W25: Ø Temp | X25: =SUM(X18:X24)/7 -> 21 | Y25: °C
A26: =SUM(A24+1) -> 19 | B26: Mo | C26: 1645 | D26: 2903.2258 | E26: 10568.1 | F26: 10322.581 | G26: 1435.2 | H26: 1612.9032 | I26: 0 | J26: 645.16129 | K26: 0 | L26: 3045.1613 | M26: 2945.2 | N26: 387.09677 | O26: 5692.2 | P26: 4435.4839 | Q26: =SUM(C26+E26+G26+I26+K26+M26+O26) -> 22285.7 | R26: =SUM(D26+F26+H26+J26+L26+N26+P26) -> 23351.613 | S26: 2700.1 | T26: 2419.3548 | U26: =SUM(Q26+S26) -> 24985.8 | V26: =SUM(R26+T26) -> 25770.968 | W26: sonnig | X26: 28 | Y26: °C
A27: =SUM(A26+1) -> 20 | B27: Di | C27: 1474.3 | D27: 2903.2258 | E27: 13204.1 | F27: 10322.581 | G27: 2410.3 | H27: 1612.9032 | I27: 0 | J27: 645.16129 | K27: 0 | L27: 3045.1613 | M27: 0 | N27: 387.09677 | O27: 5551.8 | P27: 4435.4839 | Q27: =SUM(C27+E27+G27+I27+K27+M27+O27) -> 22640.5 | R27: =SUM(D27+F27+H27+J27+L27+N27+P27) -> 23351.613 | S27: 4447.9 | T27: 2419.3548 | U27: =SUM(Q27+S27) -> 27088.4 | V27: =SUM(R27+T27) -> 25770.968 | W27: sonnig | X27: 30 | Y27: °C
A28: =SUM(A27+1) -> 21 | B28: Mi | C28: 3288 | D28: 2903.2258 | E28: 11870 | F28: 10322.581 | G28: 2103.4 | H28: 1612.9032 | I28: 0 | J28: 645.16129 | K28: 0 | L28: 3045.1613 | M28: 0 | N28: 387.09677 | O28: 5475 | P28: 4435.4839 | Q28: =SUM(C28+E28+G28+I28+K28+M28+O28) -> 22736.4 | R28: =SUM(D28+F28+H28+J28+L28+N28+P28) -> 23351.613 | S28: 4106.8 | T28: 2419.3548 | U28: =SUM(Q28+S28) -> 26843.2 | V28: =SUM(R28+T28) -> 25770.968 | W28: sonnig | X28: 30 | Y28: °C
A29: =SUM(A28+1) -> 22 | B29: Do | C29: 3028.1 | D29: 2903.2258 | E29: 14627.3 | F29: 10322.581 | G29: 1610.5 | H29: 1612.9032 | I29: 0 | J29: 645.16129 | K29: 0 | L29: 3045.1613 | M29: 0 | N29: 387.09677 | O29: 6311.5 | P29: 4435.4839 | Q29: =SUM(C29+E29+G29+I29+K29+M29+O29) -> 25577.4 | R29: =SUM(D29+F29+H29+J29+L29+N29+P29) -> 23351.613 | S29: 4773.8 | T29: 2419.3548 | U29: =SUM(Q29+S29) -> 30351.2 | V29: =SUM(R29+T29) -> 25770.968 | W29: sonnig | X29: 30 | Y29: °C
A30: =SUM(A29+1) -> 23 | B30: Fr | C30: 1860.2 | D30: 2903.2258 | E30: 15074.1 | F30: 10322.581 | G30: 2061.4 | H30: 1612.9032 | I30: 0 | J30: 645.16129 | K30: 6359.6 | L30: 3045.1613 | M30: 0 | N30: 387.09677 | O30: 5347.6 | P30: 4435.4839 | Q30: =SUM(C30+E30+G30+I30+K30+M30+O30) -> 30702.9 | R30: =SUM(D30+F30+H30+J30+L30+N30+P30) -> 23351.613 | S30: 5164.3 | T30: 2419.3548 | U30: =SUM(Q30+S30) -> 35867.2 | V30: =SUM(R30+T30) -> 25770.968 | W30: sonnig | X30: 30 | Y30: °C
A31: =SUM(A30+1) -> 24 | B31: Sa | C31: 4081.8 | D31: 2903.2258 | E31: 6395.6 | F31: 10322.581 | G31: 717.2 | H31: 1612.9032 | I31: 0 | J31: 645.16129 | K31: 2880.1 | L31: 3045.1613 | M31: 0 | N31: 387.09677 | O31: 6737 | P31: 4435.4839 | Q31: =SUM(C31+E31+G31+I31+K31+M31+O31) -> 20811.7 | R31: =SUM(D31+F31+H31+J31+L31+N31+P31) -> 23351.613 | S31: 424.4 | T31: 2419.3548 | U31: =SUM(Q31+S31) -> 21236.1 | V31: =SUM(R31+T31) -> 25770.968 | W31: regnerisch | X31: 28 | Y31: °C
A32: =SUM(A31+1) -> 25 | B32: So | C32: 5879.2 | D32: 2903.2258 | E32: 6587.7 | F32: 10322.581 | G32: 718.7 | H32: 1612.9032 | I32: 0 | J32: 645.16129 | K32: 4789.8 | L32: 3045.1613 | M32: 0 | N32: 387.09677 | O32: 4217.4 | P32: 4435.4839 | Q32: =SUM(C32+E32+G32+I32+K32+M32+O32) -> 22192.8 | R32: =SUM(D32+F32+H32+J32+L32+N32+P32) -> 23351.613 | S32: 0 | T32: 2419.3548 | U32: =SUM(Q32+S32) -> 22192.8 | V32: =SUM(R32+T32) -> 25770.968 | W32: Regen | X32: 26 | Y32: °C
A33: KW | B33: =SUM(B25+1) -> 30 | C33: =SUM(C26:C32) -> 21256.6 | D33: =SUM(D26:D32) -> 20322.581 | E33: =SUM(E26:E32) -> 78326.9 | F33: =SUM(F26:F32) -> 72258.065 | G33: =SUM(G26:G32) -> 11056.7 | H33: =SUM(H26:H32) -> 11290.323 | I33: =SUM(I26:I32) -> 0 | J33: =SUM(J26:J32) -> 4516.129 | ... V33: =SUM(V26:V32) -> 180396.77 | W33: Ø Temp | X33: =SUM(X26:X32)/7 -> 28.857143 | Y33: °C
A34: =SUM(A32+1) -> 26 | B34: Mo | C34: 3135.4 | D34: 2903.2258 | E34: 5234.6 | F34: 10322.581 | G34: 886.3 | H34: 1612.9032 | I34: 0 | J34: 645.16129 | K34: 2326.8 | L34: 3045.1613 | M34: 0 | N34: 387.09677 | O34: 5433.5 | P34: 4435.4839 | Q34: =SUM(C34+E34+G34+I34+K34+M34+O34) -> 17016.6 | R34: =SUM(D34+F34+H34+J34+L34+N34+P34) -> 23351.613 | S34: 67.1 | T34: 2419.3548 | U34: =SUM(Q34+S34) -> 17083.7 | V34: =SUM(R34+T34) -> 25770.968 | W34: gewittrig | X34: 26 | Y34: °C
A35: =SUM(A34+1) -> 27 | B35: Di | C35: 2822.3 | D35: 2903.2258 | E35: 6260.5 | F35: 10322.581 | G35: 740.8 | H35: 1612.9032 | I35: 0 | J35: 645.16129 | K35: 5144.7 | L35: 3045.1613 | M35: 0 | N35: 387.09677 | O35: 5726.3 | P35: 4435.4839 | Q35: =SUM(C35+E35+G35+I35+K35+M35+O35) -> 20694.6 | R35: =SUM(D35+F35+H35+J35+L35+N35+P35) -> 23351.613 | S35: 456.5 | T35: 2419.3548 | U35: =SUM(Q35+S35) -> 21151.1 | V35: =SUM(R35+T35) -> 25770.968 | W35: gewittrig | X35: 26 | Y35: °C
A36: =SUM(A35+1) -> 28 | B36: Mi | C36: 2926.2 | D36: 2903.2258 | E36: 7377.9 | F36: 10322.581 | G36: 429.7 | H36: 1612.9032 | I36: 0 | J36: 645.16129 | K36: 1438.7 | L36: 3045.1613 | M36: 0 | N36: 387.09677 | O36: 4925.4 | P36: 4435.4839 | Q36: =SUM(C36+E36+G36+I36+K36+M36+O36) -> 17097.9 | R36: =SUM(D36+F36+H36+J36+L36+N36+P36) -> 23351.613 | S36: 397.7 | T36: 2419.3548 | U36: =SUM(Q36+S36) -> 17495.6 | V36: =SUM(R36+T36) -> 25770.968 | W36: gewittrig | X36: 24 | Y36: °C
A37: =SUM(A36+1) -> 29 | B37: Do | C37: 4027.3 | D37: 2903.2258 | E37: 13806.3 | F37: 10322.581 | G37: 2096.5 | H37: 1612.9032 | I37: 0 | J37: 645.16129 | K37: 0 | L37: 3045.1613 | M37: 0 | N37: 387.09677 | O37: 5683 | P37: 4435.4839 | Q37: =SUM(C37+E37+G37+I37+K37+M37+O37) -> 25613.1 | R37: =SUM(D37+F37+H37+J37+L37+N37+P37) -> 23351.613 | S37: 2854 | T37: 2419.3548 | U37: =SUM(Q37+S37) -> 28467.1 | V37: =SUM(R37+T37) -> 25770.968 | W37: sonnig | X37: 26 | Y37: °C
A38: =SUM(A37+1) -> 30 | B38: Fr | C38: 3361.4 | D38: 2903.2258 | E38: 6776.7 | F38: 10322.581 | G38: 455.3 | H38: 1612.9032 | I38: 555.5 | J38: 645.16129 | K38: 7218.4 | L38: 3045.1613 | M38: 0 | N38: 387.09677 | O38: 5042.6 | P38: 4435.4839 | Q38: =SUM(C38+E38+G38+I38+K38+M38+O38) -> 23409.9 | R38: =SUM(D38+F38+H38+J38+L38+N38+P38) -> 23351.613 | S38: 542.9 | T38: 2419.3548 | U38: =SUM(Q38+S38) -> 23952.8 | V38: =SUM(R38+T38) -> 25770.968 | W38: Regen | X38: 22 | Y38: °C
A39: =SUM(A38+1) -> 31 | B39: Sa | C39: 3420.6 | D39: 2903.2258 | E39: 6939.7 | F39: 10322.581 | G39: 951.9 | H39: 1612.9032 | I39: 0 | J39: 645.16129 | K39: 4598.9 | L39: 3045.1613 | M39: 25 | N39: 387.09677 | O39: 6601.7 | P39: 4435.4839 | Q39: =SUM(C39+E39+G39+I39+K39+M39+O39) -> 22537.8 | R39: =SUM(D39+F39+H39+J39+L39+N39+P39) -> 23351.613 | S39: 226.6 | T39: 2419.3548 | U39: =SUM(Q39+S39) -> 22764.4 | V39: =SUM(R39+T39) -> 25770.968 | W39: bewölkt | X39: 21 | Y39: °C
A40: KW | B40: =SUM(B33+1) -> 31 | C40: =SUM(C34:C39) -> 19693.2 | D40: =SUM(D34:D39) -> 17419.355 | E40: =SUM(E34:E39) -> 46395.7 | F40: =SUM(F34:F39) -> 61935.484 | G40: =SUM(G34:G39) -> 5560.5 | H40: =SUM(H34:H39) -> 9677.4194 | I40: =SUM(I34:I39) -> 555.5 | J40: =SUM(J34:J39) -> 3870.9677 | ... V40: =SUM(V34:V39) -> 154625.81 | W40: Ø Temp | X40: =SUM(X34:X39)/6 -> 24.166667 | Y40: °C
A41: Umsatz kumuliert | C41: =SUM(C9+C17+C25+C33+C40) -> 116898.3 | D41: =SUM(D9+D17+D25+D33+D40) -> 90000 | E41: =SUM(E9+E17+E25+E33+E40) -> 254315 | F41: =SUM(F9+F17+F25+F33+F40) -> 320000 | G41: =SUM(G9+G17+G25+G33+G40) -> 32576.2 | H41: =SUM(H9+H17+H25+H33+H40) -> 50000 | I41: =SUM(I9+I17+I25+I33+I40) -> 10978.1 | J41: =SUM(J9+J17+J25+J33+J40) -> 20000 | ... V41: =SUM(V9+V17+V25+V33+V40) -> 798900 | W41: Umsatz kumuliert
A42: Umsatz Forecast | C42: =IF(MONTH($H$1)<>MONTH(TODAY()),C41,SUM(C5:C8,C10:C16,C18:C24,C26:C32,C34:C39)/DAY(TODAY())*DAY(DATE(YEAR($H$1),MONTH($H$1)+1,1)-1)) -> 116898.3 | D42: =IF(MONTH($H$1)<>MONTH(TODAY()),D41,SUM(D5:D8,D10:D16,D18:D24,D26:D32,D34:D39)/DAY(TODAY())*DAY(DATE(YEAR($H$1),MONTH($H$1)+1,1)-1)) -> 90000 | E42: =IF(MONTH($H$1)<>MONTH(TODAY()),E41,SUM(E5:E8,E10:E16,E18:E24,E26:E32,E34:E39)/DAY(TODAY())*DAY(DATE(YEAR($H$1),MONTH($H$1)+1,1)-1)) -> 254315 | F42: =IF(MONTH($H$1)<>MONTH(TODAY()),F41,SUM(F5:F8,F10:F16,F18:F24,F26:F32,F34:F39)/DAY(TODAY())*DAY(DATE(YEAR($H$1),MONTH($H$1)+1,1)-1)) -> 320000 | G42: =IF(MONTH($H$1)<>MONTH(TODAY()),G41,SUM(G5:G8,G10:G16,G18:G24,G26:G32,G34:G39)/DAY(TODAY())*DAY(DATE(YEAR($H$1),MONTH($H$1)+1,1)-1)) -> 32576.2 | H42: =IF(MONTH($H$1)<>MONTH(TODAY()),H41,SUM(H5:H8,H10:H16,H18:H24,H26:H32,H34:H39)/DAY(TODAY())*DAY(DATE(YEAR($H$1),MONTH($H$1)+1,1)-1)) -> 50000 | I42: =IF(MONTH($H$1)<>MONTH(TODAY()),I41,SUM(I5:I8,I10:I16,I18:I24,I26:I32,I34:I39)/DAY(TODAY())*DAY(DATE(YEAR($H$1),MONTH($H$1)+1,1)-1)) -> 10978.1 | J42: =IF(MONTH($H$1)<>MONTH(TODAY()),J41,SUM(J5:J8,J10:J16,J18:J24,J26:J32,J34:J39)/DAY(TODAY())*DAY(DATE(YEAR($H$1),MONTH($H$1)+1,1)-1)) -> 20000 | ... V42: =IF(MONTH($H$1)<>MONTH(TODAY()),V41,SUM(V5:V8,V10:V16,V18:V24,V26:V32,V34:V39)/DAY(TODAY())*DAY(DATE(YEAR($H$1),MONTH($H$1)+1,1)-1)) -> 798900 | W42: Umsatz Forecast
A43: Umsatz pro Tag | C43: =C41/31 -> 3770.9129 | D43: =D41/31 -> 2903.2258 | E43: =E41/31 -> 8203.7097 | F43: =F41/31 -> 10322.581 | G43: =G41/31 -> 1050.8452 | H43: =H41/31 -> 1612.9032 | I43: =I41/31 -> 354.13226 | J43: =J41/31 -> 645.16129 | ... V43: =V41/31 -> 25770.968 | W43: Budget pro Tag
A44: Diff. zu Budget | C44: =SUM(C41-D41) -> 26898.3 | E44: =SUM(E41-F41) -> -65685 | G44: =SUM(G41-H41) -> -17423.8 | I44: =SUM(I41-J41) -> -9021.9 | K44: =SUM(K41-L41) -> 19926.2 | M44: =SUM(M41-N41) -> -5390.3 | O44: =SUM(O41-P41) -> 18065.7 | Q44: =SUM(Q41-R41) -> -32630.8 | S44: =SUM(S41-T41) -> -35260.8 | U44: =SUM(U41-V41) -> -67891.6
A45: Index | C45: =SUM(100/D41*C41) -> 129.887 | E45: =SUM(100/F41*E41) -> 79.473438 | G45: =SUM(100/H41*G41) -> 65.1524 | I45: =SUM(100/J41*I41) -> 54.8905 | K45: =SUM(100/L41*K41) -> 121.10826 | M45: =SUM(100/N41*M41) -> 55.080833 | O45: =SUM(100/P41*O41) -> 113.13869 | Q45: =SUM(100/R41*Q41) -> 95.492361 | S45: =SUM(100/T41*S41) -> 52.9856 | U45: =SUM(100/V41*U41) -> 91.501865

Sheet 08_21
A1: Tagesumsätze | H1: 44409
C3: Restaurant | E3: Terrasse | G3: Lounge | I3: Pavillon | K3: Bankett | M3: Seminar | O3: Hotel | Q3: TOTAL Gesamtbetrieb ohne Seebad | S3: Seebad | U3: TOTAL Gesamtbetrieb mit Seebad | W3: Info's
C4: IST | D4: Budget | E4: IST | F4: Budget | G4: IST | H4: Budget | I4: IST | J4: Budget | K4: IST | L4: Budget | M4: IST | N4: Budget | O4: IST | P4: Budget | Q4: IST | R4: Budget | S4: IST | T4: Budget | U4: IST | V4: Budget | W4: Wetter | X4: Temp. | Z4: Bemerkung
A5: 1 | B5: So | C5: 7087.3 | D5: 2903.2258 | E5: 414.6 | F5: 10161.29 | G5: 292 | H5: 1612.9032 | I5: 0 | J5: 806.4516 | K5: 5603.8 | L5: 2954.8387 | M5: 0 | N5: 774.19354 | O5: 3930.4 | P5: 4116.129 | Q5: =SUM(C5+E5+G5+I5+K5+M5+O5) -> 17328.1 | R5: =SUM(D5+F5+H5+J5+L5+N5+P5) -> 23329.032 | S5: 0 | T5: 2419.3548 | U5: =SUM(Q5+S5) -> 17328.1 | V5: =SUM(R5+T5) -> 25748.387 | W5: Regen | X5: 20 | Y5: °C
A6: KW | B6: 31 | C6: =SUM(C5) -> 7087.3 | D6: =SUM(D5) -> 2903.2258 | E6: =SUM(E5) -> 414.6 | F6: =SUM(F5) -> 10161.29 | G6: =SUM(G5) -> 292 | H6: =SUM(H5) -> 1612.9032 | I6: =SUM(I5) -> 0 | J6: =SUM(J5) -> 806.4516 | ... V6: =SUM(V5) -> 25748.387 | W6: Ø Temp | X6: =SUM(X5)/1 -> 20 | Y6: °C
A7: =SUM(A5+1) -> 2 | B7: Mo | C7: 4304.8 | D7: 2903.2258 | E7: 8598.9 | F7: 10161.29 | G7: 825.9 | H7: 1612.9032 | I7: 0 | J7: 806.4516 | K7: 36.2 | L7: 2954.8387 | M7: 0 | N7: 774.19354 | O7: 4682.9 | P7: 4116.129 | Q7: =SUM(C7+E7+G7+I7+K7+M7+O7) -> 18448.7 | R7: =SUM(D7+F7+H7+J7+L7+N7+P7) -> 23329.032 | S7: 521.9 | T7: 2419.3548 | U7: =SUM(Q7+S7) -> 18970.6 | V7: =SUM(R7+T7) -> 25748.387 | W7: bewölkt | X7: 20 | Y7: °C
A8: =SUM(A7+1) -> 3 | B8: Di | C8: 3814.9 | D8: 2903.2258 | E8: 3598 | F8: 10161.29 | G8: 639.9 | H8: 1612.9032 | I8: 0 | J8: 806.4516 | K8: 4201.1 | L8: 2954.8387 | M8: 56.4 | N8: 774.19354 | O8: 6081.3 | P8: 4116.129 | Q8: =SUM(C8+E8+G8+I8+K8+M8+O8) -> 18391.6 | R8: =SUM(D8+F8+H8+J8+L8+N8+P8) -> 23329.032 | S8: 107.3 | T8: 2419.3548 | U8: =SUM(Q8+S8) -> 18498.9 | V8: =SUM(R8+T8) -> 25748.387 | W8: bewölkt | X8: 20 | Y8: °C
A9: =SUM(A8+1) -> 4 | B9: Mi | C9: 5386.5 | D9: 2903.2258 | E9: 86.1 | F9: 10161.29 | G9: 58 | H9: 1612.9032 | I9: 0 | J9: 806.4516 | K9: 2659.1 | L9: 2954.8387 | M9: 0 | N9: 774.19354 | O9: 4774.4 | P9: 4116.129 | Q9: =SUM(C9+E9+G9+I9+K9+M9+O9) -> 12964.1 | R9: =SUM(D9+F9+H9+J9+L9+N9+P9) -> 23329.032 | S9: 0 | T9: 2419.3548 | U9: =SUM(Q9+S9) -> 12964.1 | V9: =SUM(R9+T9) -> 25748.387 | W9: Regen | X9: 16 | Y9: °C
A10: =SUM(A9+1) -> 5 | B10: Do | C10: 3310.3 | D10: 2903.2258 | E10: 6919.1 | F10: 10161.29 | G10: 622.7 | H10: 1612.9032 | I10: 0 | J10: 806.4516 | K10: 345.2 | L10: 2954.8387 | M10: 0 | N10: 774.19354 | O10: 5115.7 | P10: 4116.129 | Q10: =SUM(C10+E10+G10+I10+K10+M10+O10) -> 16313 | R10: =SUM(D10+F10+H10+J10+L10+N10+P10) -> 23329.032 | S10: 0 | T10: 2419.3548 | U10: =SUM(Q10+S10) -> 16313 | V10: =SUM(R10+T10) -> 25748.387 | W10: bewölkt | X10: 20 | Y10: °C
A11: =SUM(A10+1) -> 6 | B11: Fr | C11: 5267.7 | D11: 2903.2258 | E11: 9508.7 | F11: 10161.29 | G11: 1857.3 | H11: 1612.9032 | I11: 1026 | J11: 806.4516 | K11: 2872.2 | L11: 2954.8387 | M11: 0 | N11: 774.19354 | O11: 5732.2 | P11: 4116.129 | Q11: =SUM(C11+E11+G11+I11+K11+M11+O11) -> 26264.1 | R11: =SUM(D11+F11+H11+J11+L11+N11+P11) -> 23329.032 | S11: 451 | T11: 2419.3548 | U11: =SUM(Q11+S11) -> 26715.1 | V11: =SUM(R11+T11) -> 25748.387 | W11: bewölkt | X11: 23 | Y11: °C
A12: =SUM(A11+1) -> 7 | B12: Sa | C12: 7389.3 | D12: 2903.2258 | E12: 1982.6 | F12: 10161.29 | G12: 418.5 | H12: 1612.9032 | I12: 321.5 | J12: 806.4516 | K12: 11327 | L12: 2954.8387 | M12: 575 | N12: 774.19354 | O12: 5763.9 | P12: 4116.129 | Q12: =SUM(C12+E12+G12+I12+K12+M12+O12) -> 27777.8 | R12: =SUM(D12+F12+H12+J12+L12+N12+P12) -> 23329.032 | S12: 21.3 | T12: 2419.3548 | U12: =SUM(Q12+S12) -> 27799.1 | V12: =SUM(R12+T12) -> 25748.387 | W12: wechselnd bewölkt | X12: 23 | Y12: °C
A13: =SUM(A12+1) -> 8 | B13: So | C13: 7760.2 | D13: 2903.2258 | E13: 6651.3 | F13: 10161.29 | G13: 1033.3 | H13: 1612.9032 | I13: 0 | J13: 806.4516 | K13: 6386.9 | L13: 2954.8387 | M13: 75 | N13: 774.19354 | O13: 4724.9 | P13: 4116.129 | Q13: =SUM(C13+E13+G13+I13+K13+M13+O13) -> 26631.6 | R13: =SUM(D13+F13+H13+J13+L13+N13+P13) -> 23329.032 | S13: 0 | T13: 2419.3548 | U13: =SUM(Q13+S13) -> 26631.6 | V13: =SUM(R13+T13) -> 25748.387 | W13: wechselnd bewölkt | X13: 20 | Y13: °C
A14: KW | B14: =SUM(B6+1) -> 32 | C14: =SUM(C7:C13) -> 37233.7 | D14: =SUM(D7:D13) -> 20322.581 | E14: =SUM(E7:E13) -> 37344.7 | F14: =SUM(F7:F13) -> 71129.032 | G14: =SUM(G7:G13) -> 5455.6 | H14: =SUM(H7:H13) -> 11290.323 | I14: =SUM(I7:I13) -> 1347.5 | J14: =SUM(J7:J13) -> 5645.1612 | ... V14: =SUM(V7:V13) -> 180238.71 | W14: Ø Temp | X14: =SUM(X7:X13)/7 -> 20.285714 | Y14: °C
A15: =SUM(A13+1) -> 9 | B15: Mo | C15: 1363.1 | D15: 2903.2258 | E15: 10715.9 | F15: 10161.29 | G15: 951.1 | H15: 1612.9032 | I15: 0 | J15: 806.4516 | K15: 0 | L15: 2954.8387 | M15: 0 | N15: 774.19354 | O15: 4010.8 | P15: 4116.129 | Q15: =SUM(C15+E15+G15+I15+K15+M15+O15) -> 17040.9 | R15: =SUM(D15+F15+H15+J15+L15+N15+P15) -> 23329.032 | S15: 385.6 | T15: 2419.3548 | U15: =SUM(Q15+S15) -> 17426.5 | V15: =SUM(R15+T15) -> 25748.387 | W15: sonnig | X15: 22 | Y15: °C
A16: =SUM(A15+1) -> 10 | B16: Di | C16: 2740.9 | D16: 2903.2258 | E16: 12061.7 | F16: 10161.29 | G16: 1736.9 | H16: 1612.9032 | I16: 0 | J16: 806.4516 | K16: 38 | L16: 2954.8387 | M16: 0 | N16: 774.19354 | O16: 6346.9 | P16: 4116.129 | Q16: =SUM(C16+E16+G16+I16+K16+M16+O16) -> 22924.4 | R16: =SUM(D16+F16+H16+J16+L16+N16+P16) -> 23329.032 | S16: 2819.8 | T16: 2419.3548 | U16: =SUM(Q16+S16) -> 25744.2 | V16: =SUM(R16+T16) -> 25748.387 | W16: sonnig | X16: 26 | Y16: °C
A17: =SUM(A16+1) -> 11 | B17: Mi | C17: 3348.1 | D17: 2903.2258 | E17: 12817.6 | F17: 10161.29 | G17: 1814.8 | H17: 1612.9032 | I17: 0 | J17: 806.4516 | K17: 2307.3 | L17: 2954.8387 | M17: 0 | N17: 774.19354 | O17: 6213.3 | P17: 4116.129 | Q17: =SUM(C17+E17+G17+I17+K17+M17+O17) -> 26501.1 | R17: =SUM(D17+F17+H17+J17+L17+N17+P17) -> 23329.032 | S17: 5571.3 | T17: 2419.3548 | U17: =SUM(Q17+S17) -> 32072.4 | V17: =SUM(R17+T17) -> 25748.387 | W17: sonnig | X17: 28 | Y17: °C
A18: =SUM(A17+1) -> 12 | B18: Do | C18: 3401.9 | D18: 2903.2258 | E18: 14539.2 | F18: 10161.29 | G18: 2289.6 | H18: 1612.9032 | I18: 0 | J18: 806.4516 | K18: 0 | L18: 2954.8387 | M18: 0 | N18: 774.19354 | O18: 5054.9 | P18: 4116.129 | Q18: =SUM(C18+E18+G18+I18+K18+M18+O18) -> 25285.6 | R18: =SUM(D18+F18+H18+J18+L18+N18+P18) -> 23329.032 | S18: 6337.8 | T18: 2419.3548 | U18: =SUM(Q18+S18) -> 31623.4 | V18: =SUM(R18+T18) -> 25748.387 | W18: sonnig | X18: 30 | Y18: °C
A19: =SUM(A18+1) -> 13 | B19: Fr | C19: 1720.6 | D19: 2903.2258 | E19: 13774 | F19: 10161.29 | G19: 1639.7 | H19: 1612.9032 | I19: 3750 | J19: 806.4516 | K19: 9578.2 | L19: 2954.8387 | M19: 0 | N19: 774.19354 | O19: 5822.5 | P19: 4116.129 | Q19: =SUM(C19+E19+G19+I19+K19+M19+O19) -> 36285 | R19: =SUM(D19+F19+H19+J19+L19+N19+P19) -> 23329.032 | S19: 4870.6 | T19: 2419.3548 | U19: =SUM(Q19+S19) -> 41155.6 | V19: =SUM(R19+T19) -> 25748.387 | W19: sonnig | X19: 30 | Y19: °C
A20: =SUM(A19+1) -> 14 | B20: Sa | C20: 3729.1 | D20: 2903.2258 | E20: 14694.8 | F20: 10161.29 | G20: 1489.2 | H20: 1612.9032 | I20: 5028 | J20: 806.4516 | K20: 6660.4 | L20: 2954.8387 | M20: 0 | N20: 774.19354 | O20: 5832.5 | P20: 4116.129 | Q20: =SUM(C20+E20+G20+I20+K20+M20+O20) -> 37434 | R20: =SUM(D20+F20+H20+J20+L20+N20+P20) -> 23329.032 | S20: 8188.2 | T20: 2419.3548 | U20: =SUM(Q20+S20) -> 45622.2 | V20: =SUM(R20+T20) -> 25748.387 | W20: sonnig | X20: 30 | Y20: °C
A21: =SUM(A20+1) -> 15 | B21: So | C21: 1788.6 | D21: 2903.2258 | E21: 16585.4 | F21: 10161.29 | G21: 2009.7 | H21: 1612.9032 | I21: 0 | J21: 806.4516 | K21: 1974.9 | L21: 2954.8387 | M21: 0 | N21: 774.19354 | O21: 4374.4 | P21: 4116.129 | Q21: =SUM(C21+E21+G21+I21+K21+M21+O21) -> 26733 | R21: =SUM(D21+F21+H21+J21+L21+N21+P21) -> 23329.032 | S21: 8494 | T21: 2419.3548 | U21: =SUM(Q21+S21) -> 35227 | V21: =SUM(R21+T21) -> 25748.387 | W21: sonnig | X21: 30 | Y21: °C
A22: KW | B22: =SUM(B14+1) -> 33 | C22: =SUM(C15:C21) -> 18092.3 | D22: =SUM(D15:D21) -> 20322.581 | E22: =SUM(E15:E21) -> 95188.6 | F22: =SUM(F15:F21) -> 71129.032 | G22: =SUM(G15:G21) -> 11931 | H22: =SUM(H15:H21) -> 11290.323 | I22: =SUM(I15:I21) -> 8778 | J22: =SUM(J15:J21) -> 5645.1612 | ... V22: =SUM(V15:V21) -> 180238.71 | W22: Ø Temp | X22: =SUM(X15:X21)/7 -> 28 | Y22: °C
A23: =SUM(A21+1) -> 16 | B23: Mo | C23: 4974.7 | D23: 2903.2258 | E23: 1949.7 | F23: 10161.29 | G23: 51.2 | H23: 1612.9032 | I23: 0 | J23: 806.4516 | K23: 5533.9 | L23: 2954.8387 | M23: 1772.2 | N23: 774.19354 | O23: 5280.3 | P23: 4116.129 | Q23: =SUM(C23+E23+G23+I23+K23+M23+O23) -> 19562 | R23: =SUM(D23+F23+H23+J23+L23+N23+P23) -> 23329.032 | S23: 0 | T23: 2419.3548 | U23: =SUM(Q23+S23) -> 19562 | V23: =SUM(R23+T23) -> 25748.387 | W23: Regen | X23: 18 | Y23: °C
A24: =SUM(A23+1) -> 17 | B24: Di | C24: 2794.3 | D24: 2903.2258 | E24: 8455.7 | F24: 10161.29 | G24: 834.5 | H24: 1612.9032 | I24: 0 | J24: 806.4516 | K24: 2322.4 | L24: 2954.8387 | M24: 1139.4 | N24: 774.19354 | O24: 5313.3 | P24: 4116.129 | Q24: =SUM(C24+E24+G24+I24+K24+M24+O24) -> 20859.6 | R24: =SUM(D24+F24+H24+J24+L24+N24+P24) -> 23329.032 | S24: 484.9 | T24: 2419.3548 | U24: =SUM(Q24+S24) -> 21344.5 | V24: =SUM(R24+T24) -> 25748.387 | W24: bewölkt | X24: 20 | Y24: °C
A25: =SUM(A24+1) -> 18 | B25: Mi | C25: 1140.2 | D25: 2903.2258 | E25: 10176.3 | F25: 10161.29 | G25: 914.3 | H25: 1612.9032 | I25: 0 | J25: 806.4516 | K25: 0 | L25: 2954.8387 | M25: 844.4 | N25: 774.19354 | O25: 5258.3 | P25: 4116.129 | Q25: =SUM(C25+E25+G25+I25+K25+M25+O25) -> 18333.5 | R25: =SUM(D25+F25+H25+J25+L25+N25+P25) -> 23329.032 | S25: 287.1 | T25: 2419.3548 | U25: =SUM(Q25+S25) -> 18620.6 | V25: =SUM(R25+T25) -> 25748.387 | W25: sonnig | X25: 20 | Y25: °C
A26: =SUM(A25+1) -> 19 | B26: Do | C26: 2233 | D26: 2903.2258 | E26: 12592.4 | F26: 10161.29 | G26: 777.6 | H26: 1612.9032 | I26: 0 | J26: 806.4516 | K26: 0 | L26: 2954.8387 | M26: 1297.6 | N26: 774.19354 | O26: 5177.6 | P26: 4116.129 | Q26: =SUM(C26+E26+G26+I26+K26+M26+O26) -> 22078.2 | R26: =SUM(D26+F26+H26+J26+L26+N26+P26) -> 23329.032 | S26: 223.1 | T26: 2419.3548 | U26: =SUM(Q26+S26) -> 22301.3 | V26: =SUM(R26+T26) -> 25748.387 | W26: bewölkt | X26: 20 | Y26: °C
A27: =SUM(A26+1) -> 20 | B27: Fr | C27: 1791.45 | D27: 2903.2258 | E27: 14570.7 | F27: 10161.29 | G27: 1240.3 | H27: 1612.9032 | I27: 3293 | J27: 806.4516 | K27: 10336.7 | L27: 2954.8387 | M27: 140.6 | N27: 774.19354 | O27: 4823.7 | P27: 4116.129 | Q27: =SUM(C27+E27+G27+I27+K27+M27+O27) -> 36196.45 | R27: =SUM(D27+F27+H27+J27+L27+N27+P27) -> 23329.032 | S27: 2438.7 | T27: 2419.3548 | U27: =SUM(Q27+S27) -> 38635.15 | V27: =SUM(R27+T27) -> 25748.387 | W27: bewölkt | X27: 20 | Y27: °C
A28: =SUM(A27+1) -> 21 | B28: Sa | C28: 4066.6 | D28: 2903.2258 | E28: 15246.4 | F28: 10161.29 | G28: 2695.1 | H28: 1612.9032 | I28: 4265 | J28: 806.4516 | K28: 603.1 | L28: 2954.8387 | M28: 427 | N28: 774.19354 | O28: 6675.3 | P28: 4116.129 | Q28: =SUM(C28+E28+G28+I28+K28+M28+O28) -> 33978.5 | R28: =SUM(D28+F28+H28+J28+L28+N28+P28) -> 23329.032 | S28: 7434.5 | T28: 2419.3548 | U28: =SUM(Q28+S28) -> 41413 | V28: =SUM(R28+T28) -> 25748.387 | W28: sonnig | X28: 27 | Y28: °C
A29: =SUM(A28+1) -> 22 | B29: So | C29: 3193.4 | D29: 2903.2258 | E29: 8953.4 | F29: 10161.29 | G29: 887.4 | H29: 1612.9032 | I29: 0 | J29: 806.4516 | K29: 4950.8 | L29: 2954.8387 | M29: 0 | N29: 774.19354 | O29: 3098.2 | P29: 4116.129 | Q29: =SUM(C29+E29+G29+I29+K29+M29+O29) -> 21083.2 | R29: =SUM(D29+F29+H29+J29+L29+N29+P29) -> 23329.032 | S29: 0 | T29: 2419.3548 | U29: =SUM(Q29+S29) -> 21083.2 | V29: =SUM(R29+T29) -> 25748.387 | W29: Regen | X29: 20 | Y29: °C
A30: KW | B30: =SUM(B22+1) -> 34 | C30: =SUM(C23:C29) -> 20193.65 | D30: =SUM(D23:D29) -> 20322.581 | E30: =SUM(E23:E29) -> 71944.6 | F30: =SUM(F23:F29) -> 71129.032 | G30: =SUM(G23:G29) -> 7400.4 | H30: =SUM(H23:H29) -> 11290.323 | I30: =SUM(I23:I29) -> 7558 | J30: =SUM(J23:J29) -> 5645.1612 | ... V30: =SUM(V23:V29) -> 180238.71 | W30: Ø Temp | X30: =SUM(X23:X29)/7 -> 20.714286 | Y30: °C
A31: =SUM(A29+1) -> 23 | B31: Mo | C31: 1972.4 | D31: 2903.2258 | E31: 9447.3 | F31: 10161.29 | G31: 1083.6 | H31: 1612.9032 | I31: 673 | J31: 806.4516 | K31: 0 | L31: 2954.8387 | M31: 4800.1 | N31: 774.19354 | O31: 3353.2 | P31: 4116.129 | Q31: =SUM(C31+E31+G31+I31+K31+M31+O31) -> 21329.6 | R31: =SUM(D31+F31+H31+J31+L31+N31+P31) -> 23329.032 | S31: 486.5 | T31: 2419.3548 | U31: =SUM(Q31+S31) -> 21816.1 | V31: =SUM(R31+T31) -> 25748.387 | W31: sonnig | X31: 22 | Y31: °C
A32: =SUM(A31+1) -> 24 | B32: Di | C32: 4790.7 | D32: 2903.2258 | E32: 2885.8 | F32: 10161.29 | G32: 474.3 | H32: 1612.9032 | I32: 0 | J32: 806.4516 | K32: 2590.5 | L32: 2954.8387 | M32: 2233.4 | N32: 774.19354 | O32: 5846.3 | P32: 4116.129 | Q32: =SUM(C32+E32+G32+I32+K32+M32+O32) -> 18821 | R32: =SUM(D32+F32+H32+J32+L32+N32+P32) -> 23329.032 | S32: 0 | T32: 2419.3548 | U32: =SUM(Q32+S32) -> 18821 | V32: =SUM(R32+T32) -> 25748.387 | W32: bewölkt | X32: 20 | Y32: °C
A33: =SUM(A32+1) -> 25 | B33: Mi | C33: 3562.7 | D33: 2903.2258 | E33: 2359.3 | F33: 10161.29 | G33: 450.1 | H33: 1612.9032 | I33: 0 | J33: 806.4516 | K33: 1741.4 | L33: 2954.8387 | M33: 3292.6 | N33: 774.19354 | O33: 4224.9 | P33: 4116.129 | Q33: =SUM(C33+E33+G33+I33+K33+M33+O33) -> 15631 | R33: =SUM(D33+F33+H33+J33+L33+N33+P33) -> 23329.032 | S33: 0 | T33: 2419.3548 | U33: =SUM(Q33+S33) -> 15631 | V33: =SUM(R33+T33) -> 25748.387 | W33: bewölkt | X33: 20 | Y33: °C
A34: =SUM(A33+1) -> 26 | B34: Do | C34: 3841.2 | D34: 2903.2258 | E34: 6764.3 | F34: 10161.29 | G34: 757.6 | H34: 1612.9032 | I34: 8157.8 | J34: 806.4516 | K34: 1304.6 | L34: 2954.8387 | M34: 1665.1 | N34: 774.19354 | O34: 4608.8 | P34: 4116.129 | Q34: =SUM(C34+E34+G34+I34+K34+M34+O34) -> 27099.4 | R34: =SUM(D34+F34+H34+J34+L34+N34+P34) -> 23329.032 | S34: 363.4 | T34: 2419.3548 | U34: =SUM(Q34+S34) -> 27462.8 | V34: =SUM(R34+T34) -> 25748.387 | W34: sonnig | X34: 22 | Y34: °C
A35: =SUM(A34+1) -> 27 | B35: Fr | C35: 4125.1 | D35: 2903.2258 | E35: 8452.9 | F35: 10161.29 | G35: 796.2 | H35: 1612.9032 | I35: 729 | J35: 806.4516 | K35: 10300 | L35: 2954.8387 | M35: 791.6 | N35: 774.19354 | O35: 6299.7 | P35: 4116.129 | Q35: =SUM(C35+E35+G35+I35+K35+M35+O35) -> 31494.5 | R35: =SUM(D35+F35+H35+J35+L35+N35+P35) -> 23329.032 | S35: 135 | T35: 2419.3548 | U35: =SUM(Q35+S35) -> 31629.5 | V35: =SUM(R35+T35) -> 25748.387 | W35: bewölkt | X35: 20 | Y35: °C
A36: =SUM(A35+1) -> 28 | B36: Sa | C36: 6753.8 | D36: 2903.2258 | E36: 2892.7 | F36: 10161.29 | G36: 506.7 | H36: 1612.9032 | I36: 6957.7 | J36: 806.4516 | K36: 12448.4 | L36: 2954.8387 | M36: 75 | N36: 774.19354 | O36: 5610 | P36: 4116.129 | Q36: =SUM(C36+E36+G36+I36+K36+M36+O36) -> 35244.3 | R36: =SUM(D36+F36+H36+J36+L36+N36+P36) -> 23329.032 | S36: 0 | T36: 2419.3548 | U36: =SUM(Q36+S36) -> 35244.3 | V36: =SUM(R36+T36) -> 25748.387 | W36: bewölkt | X36: 18 | Y36: °C
A37: =SUM(A36+1) -> 29 | B37: So | C37: 8685.9 | D37: 2903.2258 | E37: 1248.7 | F37: 10161.29 | G37: 397.3 | H37: 1612.9032 | I37: 0 | J37: 806.4516 | K37: 7950.7 | L37: 2954.8387 | M37: 0 | N37: 774.19354 | O37: 5044.1 | P37: 4116.129 | Q37: =SUM(C37+E37+G37+I37+K37+M37+O37) -> 23326.7 | R37: =SUM(D37+F37+H37+J37+L37+N37+P37) -> 23329.032 | S37: 0 | T37: 2419.3548 | U37: =SUM(Q37+S37) -> 23326.7 | V37: =SUM(R37+T37) -> 25748.387 | W37: bewölkt | X37: 17 | Y37: °C
A38: KW | B38: =SUM(B30+1) -> 35 | C38: =SUM(C31:C37) -> 33731.8 | D38: =SUM(D31:D37) -> 20322.581 | E38: =SUM(E31:E37) -> 34051 | F38: =SUM(F31:F37) -> 71129.032 | G38: =SUM(G31:G37) -> 4465.8 | H38: =SUM(H31:H37) -> 11290.323 | I38: =SUM(I31:I37) -> 16517.5 | J38: =SUM(J31:J37) -> 5645.1612 | ... V38: =SUM(V31:V37) -> 180238.71 | W38: Ø Temp | X38: =SUM(X31:X37)/7 -> 19.857143 | Y38: °C
A39: =SUM(A37+1) -> 30 | B39: Mo | C39: 5089.4 | D39: 2903.2258 | E39: 1277.7 | F39: 10161.29 | G39: 168.5 | H39: 1612.9032 | I39: 0 | J39: 806.4516 | K39: 2247.8 | L39: 2954.8387 | M39: 2620.4 | N39: 774.19354 | O39: 3372.6 | P39: 4116.129 | Q39: =SUM(C39+E39+G39+I39+K39+M39+O39) -> 14776.4 | R39: =SUM(D39+F39+H39+J39+L39+N39+P39) -> 23329.032 | S39: 0 | T39: 2419.3548 | U39: =SUM(Q39+S39) -> 14776.4 | V39: =SUM(R39+T39) -> 25748.387 | W39: bewölkt | X39: 22 | Y39: °C
A40: =SUM(A39+1) -> 31 | B40: Di | C40: 3758.9 | D40: 2903.2258 | E40: 4548.5 | F40: 10161.29 | G40: 330.7 | H40: 1612.9032 | I40: 0 | J40: 806.4516 | K40: 3326.8 | L40: 2954.8387 | M40: 976.6 | N40: 774.19354 | O40: 3546.6 | P40: 4116.129 | Q40: =SUM(C40+E40+G40+I40+K40+M40+O40) -> 16488.1 | R40: =SUM(D40+F40+H40+J40+L40+N40+P40) -> 23329.032 | S40: 33 | T40: 2419.3548 | U40: =SUM(Q40+S40) -> 16521.1 | V40: =SUM(R40+T40) -> 25748.387 | W40: bewölkt | X40: 22 | Y40: °C
A41: KW | B41: =SUM(B38+1) -> 36 | C41: =SUM(C39:C40) -> 8848.3 | D41: =SUM(D39:D40) -> 5806.4516 | E41: =SUM(E39:E40) -> 5826.2 | F41: =SUM(F39:F40) -> 20322.581 | G41: =SUM(G39:G40) -> 499.2 | H41: =SUM(H39:H40) -> 3225.8064 | I41: =SUM(I39:I40) -> 0 | J41: =SUM(J39:J40) -> 1612.9032 | ... V41: =SUM(V39:V40) -> 51496.774 | W41: Ø Temp | X41: =SUM(X39:X40)/2 -> 22 | Y41: °C
A42: Umsatz kumuliert | C42: =SUM(C6+C14+C22+C30+C38+C41) -> 125187.05 | D42: =SUM(D6+D14+D22+D30+D38+D41) -> 90000 | E42: =SUM(E6+E14+E22+E30+E38+E41) -> 244769.7 | F42: =SUM(F6+F14+F22+F30+F38+F41) -> 315000 | G42: =SUM(G6+G14+G22+G30+G38+G41) -> 30044 | H42: =SUM(H6+H14+H22+H30+H38+H41) -> 50000 | I42: =SUM(I6+I14+I22+I30+I38+I41) -> 34201 | J42: =SUM(J6+J14+J22+J30+J38+J41) -> 25000 | ... V42: =SUM(V6+V14+V22+V30+V38+V41) -> 798200 | W42: Umsatz kumuliert
A43: Umsatz Forecast | C43: =IF(MONTH($H$1)<>MONTH(TODAY()),C42,SUM(C5,C7:C13,C15:C21,C23:C29,C31:C37,C39:C40)/DAY(TODAY())*DAY(DATE(YEAR($H$1),MONTH($H$1)+1,1)-1)) -> 125187.05 | D43: =IF(MONTH($H$1)<>MONTH(TODAY()),D42,SUM(D5,D7:D13,D15:D21,D23:D29,D31:D37,D39:D40)/DAY(TODAY())*DAY(DATE(YEAR($H$1),MONTH($H$1)+1,1)-1)) -> 90000 | E43: =IF(MONTH($H$1)<>MONTH(TODAY()),E42,SUM(E5,E7:E13,E15:E21,E23:E29,E31:E37,E39:E40)/DAY(TODAY())*DAY(DATE(YEAR($H$1),MONTH($H$1)+1,1)-1)) -> 244769.7 | F43: =IF(MONTH($H$1)<>MONTH(TODAY()),F42,SUM(F5,F7:F13,F15:F21,F23:F29,F31:F37,F39:F40)/DAY(TODAY())*DAY(DATE(YEAR($H$1),MONTH($H$1)+1,1)-1)) -> 315000 | G43: =IF(MONTH($H$1)<>MONTH(TODAY()),G42,SUM(G5,G7:G13,G15:G21,G23:G29,G31:G37,G39:G40)/DAY(TODAY())*DAY(DATE(YEAR($H$1),MONTH($H$1)+1,1)-1)) -> 30044 | H43: =IF(MONTH($H$1)<>MONTH(TODAY()),H42,SUM(H5,H7:H13,H15:H21,H23:H29,H31:H37,H39:H40)/DAY(TODAY())*DAY(DATE(YEAR($H$1),MONTH($H$1)+1,1)-1)) -> 50000 | I43: =IF(MONTH($H$1)<>MONTH(TODAY()),I42,SUM(I5,I7:I13,I15:I21,I23:I29,I31:I37,I39:I40)/DAY(TODAY())*DAY(DATE(YEAR($H$1),MONTH($H$1)+1,1)-1)) -> 34201 | J43: =IF(MONTH($H$1)<>MONTH(TODAY()),J42,SUM(J5,J7:J13,J15:J21,J23:J29,J31:J37,J39:J40)/DAY(TODAY())*DAY(DATE(YEAR($H$1),MONTH($H$1)+1,1)-1)) -> 25000 | ... V43: =IF(MONTH($H$1)<>MONTH(TODAY()),V42,SUM(V5,V7:V13,V15:V21,V23:V29,V31:V37,V39:V40)/DAY(TODAY())*DAY(DATE(YEAR($H$1),MONTH($H$1)+1,1)-1)) -> 798200 | W43: Umsatz Forecast
A44: Umsatz pro Tag | C44: =C42/31 -> 4038.2919 | D44: =D42/31 -> 2903.2258 | E44: =E42/31 -> 7895.7968 | F44: =F42/31 -> 10161.29 | G44: =G42/31 -> 969.16129 | H44: =H42/31 -> 1612.9032 | I44: =I42/31 -> 1103.2581 | J44: =J42/31 -> 806.4516 | ... V44: =V42/31 -> 25748.387 | W44: Budget pro Tag
A45: Diff. zu Budget | C45: =SUM(C42-D42) -> 35187.05 | E45: =SUM(E42-F42) -> -70230.3 | G45: =SUM(G42-H42) -> -19956 | I45: =SUM(I42-J42) -> 9201.0004 | K45: =SUM(K42-L42) -> 28047.4 | M45: =SUM(M42-N42) -> -1217.5997 | O45: =SUM(O42-P42) -> 28393.9 | Q45: =SUM(Q42-R42) -> 9425.4515 | S45: =SUM(S42-T42) -> -25344.999 | U45: =SUM(U42-V42) -> -15919.547
A46: Index | C46: =SUM(100/D42*C42) -> 139.09672 | E46: =SUM(100/F42*E42) -> 77.704667 | G46: =SUM(100/H42*G42) -> 60.088 | I46: =SUM(100/J42*I42) -> 136.804 | K46: =SUM(100/L42*K42) -> 130.61943 | M46: =SUM(100/N42*M42) -> 94.926668 | O46: =SUM(100/P42*O42) -> 122.25227 | Q46: =SUM(100/R42*Q42) -> 101.3033 | S46: =SUM(100/T42*S42) -> 66.206668 | U46: =SUM(100/V42*U42) -> 98.005569

Sheet 09_21
A1: Tagesumsätze | H1: 44440
C3: Restaurant | E3: Terrasse | G3: Lounge | I3: Pavillon | K3: Bankett | M3: Seminar | O3: Hotel | Q3: TOTAL Gesamtbetrieb ohne Seebad | S3: Seebad | U3: TOTAL Gesamtbetrieb mit Seebad | W3: Info's
C4: IST | D4: Budget | E4: IST | F4: Budget | G4: IST | H4: Budget | I4: IST | J4: Budget | K4: IST | L4: Budget | M4: IST | N4: Budget | O4: IST | P4: Budget | Q4: IST | R4: Budget | S4: IST | T4: Budget | U4: IST | V4: Budget | W4: Wetter | X4: Temp. | Z4: Bemerkung
A5: 1 | B5: Mi | C5: 2007.8 | D5: 5000 | E5: 9213.6 | F5: 5000 | G5: 1008.5 | H5: 833.33333 | I5: 0 | J5: 1000 | K5: 1508.4 | L5: 3000 | M5: 1012 | N5: 833.33333 | O5: 4398.1 | P5: 3286.6667 | Q5: =SUM(C5+E5+G5+I5+K5+M5+O5) -> 19148.4 | R5: =SUM(D5+F5+H5+J5+L5+N5+P5) -> 18953.333 | S5: 605.7 | T5: 500 | U5: =SUM(Q5+S5) -> 19754.1 | V5: =SUM(R5+T5) -> 19453.333 | W5: sonnig | X5: 20 | Y5: °C
A6: =SUM(A5+1) -> 2 | B6: Do | C6: 1733.5 | D6: 5000 | E6: 12101.5 | F6: 5000 | G6: 1685.5 | H6: 833.33333 | I6: 0 | J6: 1000 | K6: 0 | L6: 3000 | M6: 1272 | N6: 833.33333 | O6: 1809 | P6: 3286.6667 | Q6: =SUM(C6+E6+G6+I6+K6+M6+O6) -> 18601.5 | R6: =SUM(D6+F6+H6+J6+L6+N6+P6) -> 18953.333 | S6: 1099.2 | T6: 500 | U6: =SUM(Q6+S6) -> 19700.7 | V6: =SUM(R6+T6) -> 19453.333 | W6: sonnig | X6: 22 | Y6: °C
A7: =SUM(A6+1) -> 3 | B7: Fr | C7: 1919.6 | D7: 5000 | E7: 12655.9 | F7: 5000 | G7: 943.2 | H7: 833.33333 | I7: 381 | J7: 1000 | K7: 6379.2 | L7: 3000 | M7: 1159.8 | N7: 833.33333 | O7: 5785.2 | P7: 3286.6667 | Q7: =SUM(C7+E7+G7+I7+K7+M7+O7) -> 29223.9 | R7: =SUM(D7+F7+H7+J7+L7+N7+P7) -> 18953.333 | S7: 1501 | T7: 500 | U7: =SUM(Q7+S7) -> 30724.9 | V7: =SUM(R7+T7) -> 19453.333 | W7: sonnig | X7: 22 | Y7: °C
A8: =SUM(A7+1) -> 4 | B8: Sa | C8: 2457.2 | D8: 5000 | E8: 16269.3 | F8: 5000 | G8: 2110.7 | H8: 833.33333 | I8: 3958.8 | J8: 1000 | K8: 8271.5 | L8: 3000 | M8: 100 | N8: 833.33333 | O8: 6939.3 | P8: 3286.6667 | Q8: =SUM(C8+E8+G8+I8+K8+M8+O8) -> 40106.8 | R8: =SUM(D8+F8+H8+J8+L8+N8+P8) -> 18953.333 | S8: 2500.8 | T8: 500 | U8: =SUM(Q8+S8) -> 42607.6 | V8: =SUM(R8+T8) -> 19453.333 | W8: sonnig | X8: 24 | Y8: °C
A9: =SUM(A8+1) -> 5 | B9: So | C9: 3582.4 | D9: 5000 | E9: 16284.1 | F9: 5000 | G9: 1995.5 | H9: 833.33333 | I9: 0 | J9: 1000 | K9: 3498.9 | L9: 3000 | M9: 0 | N9: 833.33333 | O9: 3355.6 | P9: 3286.6667 | Q9: =SUM(C9+E9+G9+I9+K9+M9+O9) -> 28716.5 | R9: =SUM(D9+F9+H9+J9+L9+N9+P9) -> 18953.333 | S9: 5601.8 | T9: 500 | U9: =SUM(Q9+S9) -> 34318.3 | V9: =SUM(R9+T9) -> 19453.333 | W9: sonnig | X9: 26 | Y9: °C
A10: KW | B10: 36 | C10: =SUM(C5:C9) -> 11700.5 | D10: =SUM(D5:D9) -> 25000 | E10: =SUM(E5:E9) -> 66524.4 | F10: =SUM(F5:F9) -> 25000 | G10: =SUM(G5:G9) -> 7743.4 | H10: =SUM(H5:H9) -> 4166.6667 | I10: =SUM(I5:I9) -> 4339.8 | J10: =SUM(J5:J9) -> 5000 | ... V10: =SUM(V5:V9) -> 97266.667 | W10: Ø Temp | X10: =SUM(X5:X9)/5 -> 22.8 | Y10: °C
A11: =SUM(A9+1) -> 6 | B11: Mo | C11: 739.9 | D11: 5000 | E11: 10269.1 | F11: 5000 | G11: 1094.5 | H11: 833.33333 | I11: 0 | J11: 1000 | K11: 0 | L11: 3000 | M11: 78 | N11: 833.33333 | O11: 4784.1 | P11: 3286.6667 | Q11: =SUM(C11+E11+G11+I11+K11+M11+O11) -> 16965.6 | R11: =SUM(D11+F11+H11+J11+L11+N11+P11) -> 18953.333 | S11: 2238.9 | T11: 500 | U11: =SUM(Q11+S11) -> 19204.5 | V11: =SUM(R11+T11) -> 19453.333 | W11: sonnig | X11: 25 | Y11: °C
A12: =SUM(A11+1) -> 7 | B12: Di | C12: 1186.7 | D12: 5000 | E12: 11394.1 | F12: 5000 | G12: 1532.3 | H12: 833.33333 | I12: 0 | J12: 1000 | K12: 1194.3 | L12: 3000 | M12: 0 | N12: 833.33333 | O12: 4804.9 | P12: 3286.6667 | Q12: =SUM(C12+E12+G12+I12+K12+M12+O12) -> 20112.3 | R12: =SUM(D12+F12+H12+J12+L12+N12+P12) -> 18953.333 | S12: 1597.5 | T12: 500 | U12: =SUM(Q12+S12) -> 21709.8 | V12: =SUM(R12+T12) -> 19453.333 | W12: sonnig | X12: 24 | Y12: °C
A13: =SUM(A12+1) -> 8 | B13: Mi | C13: 3112.1 | D13: 5000 | E13: 13848.7 | F13: 5000 | G13: 1284.4 | H13: 833.33333 | I13: 0 | J13: 1000 | K13: 1524.8 | L13: 3000 | M13: 0 | N13: 833.33333 | O13: 3935.8 | P13: 3286.6667 | Q13: =SUM(C13+E13+G13+I13+K13+M13+O13) -> 23705.8 | R13: =SUM(D13+F13+H13+J13+L13+N13+P13) -> 18953.333 | S13: 2717.2 | T13: 500 | U13: =SUM(Q13+S13) -> 26423 | V13: =SUM(R13+T13) -> 19453.333 | W13: sonnig | X13: 25 | Y13: °C
A14: =SUM(A13+1) -> 9 | B14: Do | C14: 3395.2 | D14: 5000 | E14: 5916.2 | F14: 5000 | G14: 469.5 | H14: 833.33333 | I14: 0 | J14: 1000 | K14: 50.5 | L14: 3000 | M14: 150 | N14: 833.33333 | O14: 3725.4 | P14: 3286.6667 | Q14: =SUM(C14+E14+G14+I14+K14+M14+O14) -> 13706.8 | R14: =SUM(D14+F14+H14+J14+L14+N14+P14) -> 18953.333 | S14: 48 | T14: 500 | U14: =SUM(Q14+S14) -> 13754.8 | V14: =SUM(R14+T14) -> 19453.333 | W14: bewölkt | X14: 24 | Y14: °C
A15: =SUM(A14+1) -> 10 | B15: Fr | C15: 5604.3 | D15: 5000 | E15: 2966.8 | F15: 5000 | G15: 319.4 | H15: 833.33333 | I15: 1024 | J15: 1000 | K15: 4010.4 | L15: 3000 | M15: 902.1 | N15: 833.33333 | O15: 4282.6 | P15: 3286.6667 | Q15: =SUM(C15+E15+G15+I15+K15+M15+O15) -> 19109.6 | R15: =SUM(D15+F15+H15+J15+L15+N15+P15) -> 18953.333 | S15: 0 | T15: 500 | U15: =SUM(Q15+S15) -> 19109.6 | V15: =SUM(R15+T15) -> 19453.333 | W15: Regen | X15: 20 | Y15: °C
A16: =SUM(A15+1) -> 11 | B16: Sa | C16: 6564.7 | D16: 5000 | E16: 13752.1 | F16: 5000 | G16: 887.4 | H16: 833.33333 | I16: 1157.9 | J16: 1000 | K16: 4410 | L16: 3000 | M16: 155 | N16: 833.33333 | O16: 6867.6 | P16: 3286.6667 | Q16: =SUM(C16+E16+G16+I16+K16+M16+O16) -> 33794.7 | R16: =SUM(D16+F16+H16+J16+L16+N16+P16) -> 18953.333 | S16: 879.5 | T16: 500 | U16: =SUM(Q16+S16) -> 34674.2 | V16: =SUM(R16+T16) -> 19453.333 | W16: sonnig | X16: 24 | Y16: °C
A17: =SUM(A16+1) -> 12 | B17: So | C17: 2813.3 | D17: 5000 | E17: 15598.4 | F17: 5000 | G17: 2002.8 | H17: 833.33333 | I17: 0 | J17: 1000 | K17: 1360 | L17: 3000 | M17: 0 | N17: 833.33333 | O17: 3355.3 | P17: 3286.6667 | Q17: =SUM(C17+E17+G17+I17+K17+M17+O17) -> 25129.8 | R17: =SUM(D17+F17+H17+J17+L17+N17+P17) -> 18953.333 | S17: 1386.5 | T17: 500 | U17: =SUM(Q17+S17) -> 26516.3 | V17: =SUM(R17+T17) -> 19453.333 | W17: sonnig | X17: 24 | Y17: °C
A18: KW | B18: =SUM(B10+1) -> 37 | C18: =SUM(C11:C17) -> 23416.2 | D18: =SUM(D11:D17) -> 35000 | E18: =SUM(E11:E17) -> 73745.4 | F18: =SUM(F11:F17) -> 35000 | G18: =SUM(G11:G17) -> 7590.3 | H18: =SUM(H11:H17) -> 5833.3333 | I18: =SUM(I11:I17) -> 2181.9 | J18: =SUM(J11:J17) -> 7000 | ... V18: =SUM(V11:V17) -> 136173.33 | W18: Ø Temp | X18: =SUM(X11:X17)/7 -> 23.714286 | Y18: °C
A19: =SUM(A17+1) -> 13 | B19: Mo | C19: 279.1 | D19: 5000 | E19: 9810.9 | F19: 5000 | G19: 1421 | H19: 833.33333 | I19: 0 | J19: 1000 | K19: 0 | L19: 3000 | M19: 0 | N19: 833.33333 | O19: 3437.1 | P19: 3286.6667 | Q19: =SUM(C19+E19+G19+I19+K19+M19+O19) -> 14948.1 | R19: =SUM(D19+F19+H19+J19+L19+N19+P19) -> 18953.333 | S19: 1741.5 | T19: 500 | U19: =SUM(Q19+S19) -> 16689.6 | V19: =SUM(R19+T19) -> 19453.333 | W19: sonnig | X19: 22 | Y19: °C
A20: =SUM(A19+1) -> 14 | B20: Di | C20: 803 | D20: 5000 | E20: 10071.9 | F20: 5000 | G20: 590.2 | H20: 833.33333 | I20: 0 | J20: 1000 | K20: 702.7 | L20: 3000 | M20: 0 | N20: 833.33333 | O20: 3226.8 | P20: 3286.6667 | Q20: =SUM(C20+E20+G20+I20+K20+M20+O20) -> 15394.6 | R20: =SUM(D20+F20+H20+J20+L20+N20+P20) -> 18953.333 | S20: 1048.3 | T20: 500 | U20: =SUM(Q20+S20) -> 16442.9 | V20: =SUM(R20+T20) -> 19453.333 | W20: sonnig | X20: 20 | Y20: °C
A21: =SUM(A20+1) -> 15 | B21: Mi | C21: 2800.9 | D21: 5000 | E21: 749 | F21: 5000 | G21: 157.9 | H21: 833.33333 | I21: 0 | J21: 1000 | K21: 0 | L21: 3000 | M21: 6088.2 | N21: 833.33333 | O21: 2592.4 | P21: 3286.6667 | Q21: =SUM(C21+E21+G21+I21+K21+M21+O21) -> 12388.4 | R21: =SUM(D21+F21+H21+J21+L21+N21+P21) -> 18953.333 | S21: 0 | T21: 500 | U21: =SUM(Q21+S21) -> 12388.4 | V21: =SUM(R21+T21) -> 19453.333 | W21: leichter Regen | X21: 20 | Y21: °C
A22: =SUM(A21+1) -> 16 | B22: Do | C22: 4039.5 | D22: 5000 | E22: 1201.8 | F22: 5000 | G22: 221.2 | H22: 833.33333 | I22: 0 | J22: 1000 | K22: 1524.5 | L22: 3000 | M22: 5290.3 | N22: 833.33333 | O22: 3174.2 | P22: 3286.6667 | Q22: =SUM(C22+E22+G22+I22+K22+M22+O22) -> 15451.5 | R22: =SUM(D22+F22+H22+J22+L22+N22+P22) -> 18953.333 | S22: 0 | T22: 500 | U22: =SUM(Q22+S22) -> 15451.5 | V22: =SUM(R22+T22) -> 19453.333 | W22: leichter Regen | X22: 20 | Y22: °C
A23: =SUM(A22+1) -> 17 | B23: Fr | C23: 4976.6 | D23: 5000 | E23: 7857.1 | F23: 5000 | G23: 937.1 | H23: 833.33333 | I23: 5412 | J23: 1000 | K23: 7092.2 | L23: 3000 | M23: 1077.1 | N23: 833.33333 | O23: 5030 | P23: 3286.6667 | Q23: =SUM(C23+E23+G23+I23+K23+M23+O23) -> 32382.1 | R23: =SUM(D23+F23+H23+J23+L23+N23+P23) -> 18953.333 | S23: 300.5 | T23: 500 | U23: =SUM(Q23+S23) -> 32682.6 | V23: =SUM(R23+T23) -> 19453.333 | W23: sonnig | X23: 20 | Y23: °C
A24: =SUM(A23+1) -> 18 | B24: Sa | C24: 3462.1 | D24: 5000 | E24: 9730.1 | F24: 5000 | G24: 780.2 | H24: 833.33333 | I24: 209.5 | J24: 1000 | K24: 9280.4 | L24: 3000 | M24: 0 | N24: 833.33333 | O24: 5365.9 | P24: 3286.6667 | Q24: =SUM(C24+E24+G24+I24+K24+M24+O24) -> 28828.2 | R24: =SUM(D24+F24+H24+J24+L24+N24+P24) -> 18953.333 | S24: 718.2 | T24: 500 | U24: =SUM(Q24+S24) -> 29546.4 | V24: =SUM(R24+T24) -> 19453.333 | W24: sonnig | X24: 20 | Y24: °C
A25: =SUM(A24+1) -> 19 | B25: So | C25: 6748.1 | D25: 5000 | E25: 0 | F25: 5000 | G25: 0 | H25: 833.33333 | I25: 0 | J25: 1000 | K25: 3101.5 | L25: 3000 | M25: 75 | N25: 833.33333 | O25: 2459.8 | P25: 3286.6667 | Q25: =SUM(C25+E25+G25+I25+K25+M25+O25) -> 12384.4 | R25: =SUM(D25+F25+H25+J25+L25+N25+P25) -> 18953.333 | S25: 0 | T25: 500 | U25: =SUM(Q25+S25) -> 12384.4 | V25: =SUM(R25+T25) -> 19453.333 | W25: Regen | X25: 15 | Y25: °C
A26: KW | B26: =SUM(B18+1) -> 38 | C26: =SUM(C19:C25) -> 23109.3 | D26: =SUM(D19:D25) -> 35000 | E26: =SUM(E19:E25) -> 39420.8 | F26: =SUM(F19:F25) -> 35000 | G26: =SUM(G19:G25) -> 4107.6 | H26: =SUM(H19:H25) -> 5833.3333 | I26: =SUM(I19:I25) -> 5621.5 | J26: =SUM(J19:J25) -> 7000 | ... V26: =SUM(V19:V25) -> 136173.33 | W26: Ø Temp | X26: =SUM(X19:X25)/7 -> 19.571429 | Y26: °C
A27: =SUM(A25+1) -> 20 | B27: Mo | C27: 3650.6 | D27: 5000 | E27: 826 | F27: 5000 | G27: 65 | H27: 833.33333 | I27: 0 | J27: 1000 | K27: 2290.6 | L27: 3000 | M27: 2521.5 | N27: 833.33333 | O27: 1241 | P27: 3286.6667 | Q27: =SUM(C27+E27+G27+I27+K27+M27+O27) -> 10594.7 | R27: =SUM(D27+F27+H27+J27+L27+N27+P27) -> 18953.333 | S27: 0 | T27: 500 | U27: =SUM(Q27+S27) -> 10594.7 | V27: =SUM(R27+T27) -> 19453.333 | W27: bewölkt | X27: 18 | Y27: °C
A28: =SUM(A27+1) -> 21 | B28: Di | C28: 4407.5 | D28: 5000 | E28: 2483.7 | F28: 5000 | G28: 726.2 | H28: 833.33333 | I28: 0 | J28: 1000 | K28: 0 | L28: 3000 | M28: 3398 | N28: 833.33333 | O28: 2156 | P28: 3286.6667 | Q28: =SUM(C28+E28+G28+I28+K28+M28+O28) -> 13171.4 | R28: =SUM(D28+F28+H28+J28+L28+N28+P28) -> 18953.333 | S28: 0 | T28: 500 | U28: =SUM(Q28+S28) -> 13171.4 | V28: =SUM(R28+T28) -> 19453.333 | W28: ziemlich sonnig | X28: 17 | Y28: °C
A29: =SUM(A28+1) -> 22 | B29: Mi | C29: 3701.6 | D29: 5000 | E29: 862.8 | F29: 5000 | G29: 661 | H29: 833.33333 | I29: 0 | J29: 1000 | K29: 0 | L29: 3000 | M29: 4647.6 | N29: 833.33333 | O29: 2145.3 | P29: 3286.6667 | Q29: =SUM(C29+E29+G29+I29+K29+M29+O29) -> 12018.3 | R29: =SUM(D29+F29+H29+J29+L29+N29+P29) -> 18953.333 | S29: 0 | T29: 500 | U29: =SUM(Q29+S29) -> 12018.3 | V29: =SUM(R29+T29) -> 19453.333 | W29: sonnig | X29: 17 | Y29: °C
A30: =SUM(A29+1) -> 23 | B30: Do | C30: 3026.7 | D30: 5000 | E30: 5266.3 | F30: 5000 | G30: 766.8 | H30: 833.33333 | I30: 0 | J30: 1000 | K30: 0 | L30: 3000 | M30: 1323.6 | N30: 833.33333 | O30: 4520.6 | P30: 3286.6667 | Q30: =SUM(C30+E30+G30+I30+K30+M30+O30) -> 14904 | R30: =SUM(D30+F30+H30+J30+L30+N30+P30) -> 18953.333 | S30: 130.6 | T30: 500 | U30: =SUM(Q30+S30) -> 15034.6 | V30: =SUM(R30+T30) -> 19453.333 | W30: sonnig | X30: 18 | Y30: °C
A31: =SUM(A30+1) -> 24 | B31: Fr | C31: 3458.6 | D31: 5000 | E31: 9808.7 | F31: 5000 | G31: 1836.8 | H31: 833.33333 | I31: 2204.8 | J31: 1000 | K31: 11124.7 | L31: 3000 | M31: 904.1 | N31: 833.33333 | O31: 5848.7 | P31: 3286.6667 | Q31: =SUM(C31+E31+G31+I31+K31+M31+O31) -> 35186.4 | R31: =SUM(D31+F31+H31+J31+L31+N31+P31) -> 18953.333 | S31: 695 | T31: 500 | U31: =SUM(Q31+S31) -> 35881.4 | V31: =SUM(R31+T31) -> 19453.333 | W31: sonnig | X31: 21 | Y31: °C
A32: =SUM(A31+1) -> 25 | B32: Sa | C32: 5335.8 | D32: 5000 | E32: 12859.9 | F32: 5000 | G32: 1550.4 | H32: 833.33333 | I32: 4168 | J32: 1000 | K32: 7734.9 | L32: 3000 | M32: 0 | N32: 833.33333 | O32: 6467.9 | P32: 3286.6667 | Q32: =SUM(C32+E32+G32+I32+K32+M32+O32) -> 38116.9 | R32: =SUM(D32+F32+H32+J32+L32+N32+P32) -> 18953.333 | S32: 956 | T32: 500 | U32: =SUM(Q32+S32) -> 39072.9 | V32: =SUM(R32+T32) -> 19453.333 | W32: sonnig | X32: 22 | Y32: °C
A33: =SUM(A32+1) -> 26 | B33: So | C33: 6437.3 | D33: 5000 | E33: 2913.5 | F33: 5000 | G33: 322.7 | H33: 833.33333 | I33: 0 | J33: 1000 | K33: 3055.4 | L33: 3000 | M33: 0 | N33: 833.33333 | O33: 2884.2 | P33: 3286.6667 | Q33: =SUM(C33+E33+G33+I33+K33+M33+O33) -> 15613.1 | R33: =SUM(D33+F33+H33+J33+L33+N33+P33) -> 18953.333 | S33: 0 | T33: 500 | U33: =SUM(Q33+S33) -> 15613.1 | V33: =SUM(R33+T33) -> 19453.333 | W33: bewölkt | X33: 18 | Y33: °C
A34: KW | B34: =SUM(B26+1) -> 39 | C34: =SUM(C27:C33) -> 30018.1 | D34: =SUM(D27:D33) -> 35000 | E34: =SUM(E27:E33) -> 35020.9 | F34: =SUM(F27:F33) -> 35000 | G34: =SUM(G27:G33) -> 5928.9 | H34: =SUM(H27:H33) -> 5833.3333 | I34: =SUM(I27:I33) -> 6372.8 | J34: =SUM(J27:J33) -> 7000 | ... V34: =SUM(V27:V33) -> 136173.33 | W34: Ø Temp | X34: =SUM(X27:X33)/7 -> 18.714286 | Y34: °C
A35: =SUM(A33+1) -> 27 | B35: Mo | C35: 2475.4 | D35: 5000 | E35: 5362.6 | F35: 5000 | G35: 394.6 | H35: 833.33333 | I35: 0 | J35: 1000 | K35: 0 | L35: 3000 | M35: 4197.7 | N35: 833.33333 | O35: 2386.1 | P35: 3286.6667 | Q35: =SUM(C35+E35+G35+I35+K35+M35+O35) -> 14816.4 | R35: =SUM(D35+F35+H35+J35+L35+N35+P35) -> 18953.333 | S35: 310 | T35: 500 | U35: =SUM(Q35+S35) -> 15126.4 | V35: =SUM(R35+T35) -> 19453.333 | W35: sonnig | X35: 20 | Y35: °C
A36: =SUM(A35+1) -> 28 | B36: Di | C36: 4629.9 | D36: 5000 | E36: 1289.9 | F36: 5000 | G36: 179 | H36: 833.33333 | I36: 0 | J36: 1000 | K36: 0 | L36: 3000 | M36: 1643.9 | N36: 833.33333 | O36: 4683.6 | P36: 3286.6667 | Q36: =SUM(C36+E36+G36+I36+K36+M36+O36) -> 12426.3 | R36: =SUM(D36+F36+H36+J36+L36+N36+P36) -> 18953.333 | S36: 0 | T36: 500 | U36: =SUM(Q36+S36) -> 12426.3 | V36: =SUM(R36+T36) -> 19453.333 | W36: bewölkt | X36: 18 | Y36: °C
A37: =SUM(A36+1) -> 29 | B37: Mi | C37: 3979.5 | D37: 5000 | E37: 1674.7 | F37: 5000 | G37: 383.9 | H37: 833.33333 | I37: 0 | J37: 1000 | K37: 0 | L37: 3000 | M37: 732 | N37: 833.33333 | O37: 2664.5 | P37: 3286.6667 | Q37: =SUM(C37+E37+G37+I37+K37+M37+O37) -> 9434.6 | R37: =SUM(D37+F37+H37+J37+L37+N37+P37) -> 18953.333 | S37: 0 | T37: 500 | U37: =SUM(Q37+S37) -> 9434.6 | V37: =SUM(R37+T37) -> 19453.333 | W37: sonnig | X37: 19 | Y37: °C
A38: =SUM(A37+1) -> 30 | B38: Do | C38: 3699.5 | D38: 5000 | E38: 3428.6 | F38: 5000 | G38: 520.8 | H38: 833.33333 | I38: 0 | J38: 1000 | K38: 0 | L38: 3000 | M38: 364.7 | N38: 833.33333 | O38: 1514.4 | P38: 3286.6667 | Q38: =SUM(C38+E38+G38+I38+K38+M38+O38) -> 9528 | R38: =SUM(D38+F38+H38+J38+L38+N38+P38) -> 18953.333 | S38: 202.3 | T38: 500 | U38: =SUM(Q38+S38) -> 9730.3 | V38: =SUM(R38+T38) -> 19453.333 | W38: sonnig | X38: 16 | Y38: °C
A39: KW | B39: =SUM(B34+1) -> 40 | C39: =SUM(C35:C38) -> 14784.3 | D39: =SUM(D35:D38) -> 20000 | E39: =SUM(E35:E38) -> 11755.8 | F39: =SUM(F35:F38) -> 20000 | G39: =SUM(G35:G38) -> 1478.3 | H39: =SUM(H35:H38) -> 3333.3333 | I39: =SUM(I35:I38) -> 0 | J39: =SUM(J35:J38) -> 4000 | ... V39: =SUM(V35:V38) -> 77813.333 | W39: Ø Temp | X39: =SUM(X35:X38)/4 -> 18.25 | Y39: °C
A40: Umsatz kumuliert | C40: =SUM(C10+C18+C26+C34+C39) -> 103028.4 | D40: =SUM(D10+D18+D26+D34+D39) -> 150000 | E40: =SUM(E10+E18+E26+E34+E39) -> 226467.3 | F40: =SUM(F10+F18+F26+F34+F39) -> 150000 | G40: =SUM(G10+G18+G26+G34+G39) -> 26848.5 | H40: =SUM(H10+H18+H26+H34+H39) -> 25000 | I40: =SUM(I10+I18+I26+I34+I39) -> 18516 | J40: =SUM(J10+J18+J26+J34+J39) -> 30000 | ... V40: =SUM(V10+V18+V26+V34+V39) -> 583600 | W40: Umsatz kumuliert
A41: Umsatz Forecast | C41: =IF(MONTH($H$1)<>MONTH(TODAY()),C40,SUM(C5:C9,C11:C17,C19:C25,C27:C33,C35:C38)/DAY(TODAY())*DAY(DATE(YEAR($H$1),MONTH($H$1)+1,1)-1)) -> 103028.4 | D41: =IF(MONTH($H$1)<>MONTH(TODAY()),D40,SUM(D5:D9,D11:D17,D19:D25,D27:D33,D35:D38)/DAY(TODAY())*DAY(DATE(YEAR($H$1),MONTH($H$1)+1,1)-1)) -> 150000 | E41: =IF(MONTH($H$1)<>MONTH(TODAY()),E40,SUM(E5:E9,E11:E17,E19:E25,E27:E33,E35:E38)/DAY(TODAY())*DAY(DATE(YEAR($H$1),MONTH($H$1)+1,1)-1)) -> 226467.3 | F41: =IF(MONTH($H$1)<>MONTH(TODAY()),F40,SUM(F5:F9,F11:F17,F19:F25,F27:F33,F35:F38)/DAY(TODAY())*DAY(DATE(YEAR($H$1),MONTH($H$1)+1,1)-1)) -> 150000 | G41: =IF(MONTH($H$1)<>MONTH(TODAY()),G40,SUM(G5:G9,G11:G17,G19:G25,G27:G33,G35:G38)/DAY(TODAY())*DAY(DATE(YEAR($H$1),MONTH($H$1)+1,1)-1)) -> 26848.5 | H41: =IF(MONTH($H$1)<>MONTH(TODAY()),H40,SUM(H5:H9,H11:H17,H19:H25,H27:H33,H35:H38)/DAY(TODAY())*DAY(DATE(YEAR($H$1),MONTH($H$1)+1,1)-1)) -> 25000 | I41: =IF(MONTH($H$1)<>MONTH(TODAY()),I40,SUM(I5:I9,I11:I17,I19:I25,I27:I33,I35:I38)/DAY(TODAY())*DAY(DATE(YEAR($H$1),MONTH($H$1)+1,1)-1)) -> 18516 | J41: =IF(MONTH($H$1)<>MONTH(TODAY()),J40,SUM(J5:J9,J11:J17,J19:J25,J27:J33,J35:J38)/DAY(TODAY())*DAY(DATE(YEAR($H$1),MONTH($H$1)+1,1)-1)) -> 30000 | ... V41: =IF(MONTH($H$1)<>MONTH(TODAY()),V40,SUM(V5:V9,V11:V17,V19:V25,V27:V33,V35:V38)/DAY(TODAY())*DAY(DATE(YEAR($H$1),MONTH($H$1)+1,1)-1)) -> 583600 | W41: Umsatz Forecast
A42: Umsatz pro Tag | C42: =C40/30 -> 3434.28 | D42: =D40/30 -> 5000 | E42: =E40/30 -> 7548.91 | F42: =F40/30 -> 5000 | G42: =G40/30 -> 894.95 | H42: =H40/30 -> 833.33333 | I42: =I40/30 -> 617.2 | J42: =J40/30 -> 1000 | ... V42: =V40/30 -> 19453.333 | W42: Budget pro Tag
A43: Diff. zu Budget | C43: =SUM(C40-D40) -> -46971.6 | E43: =SUM(E40-F40) -> 76467.3 | G43: =SUM(G40-H40) -> 1848.5001 | I43: =SUM(I40-J40) -> -11484 | K43: =SUM(K40-L40) -> -11885.1 | M43: =SUM(M40-N40) -> 12092.6 | O43: =SUM(O40-P40) -> 17241.4 | Q43: =SUM(Q40-R40) -> 37309.1 | S43: =SUM(S40-T40) -> 11278.5 | U43: =SUM(U40-V40) -> 48587.6
A44: Index | C44: =SUM(100/D40*C40) -> 68.6856 | E44: =SUM(100/F40*E40) -> 150.9782 | G44: =SUM(100/H40*G40) -> 107.394 | I44: =SUM(100/J40*I40) -> 61.72 | K44: =SUM(100/L40*K40) -> 86.794333 | M44: =SUM(100/N40*M40) -> 148.3704 | O44: =SUM(100/P40*O40) -> 117.48621 | Q44: =SUM(100/R40*Q40) -> 106.56157 | S44: =SUM(100/T40*S40) -> 175.19 | U44: =SUM(100/V40*U40) -> 108.3255

Sheet 10_21
A1: Tagesumsätze | H1: 44470
C3: Restaurant | E3: Terrasse | G3: Lounge | I3: Pavillon | K3: Bankett | M3: Seminar | O3: Hotel | Q3: TOTAL Gesamtbetrieb ohne Seebad | S3: Seebad | U3: TOTAL Gesamtbetrieb mit Seebad | W3: Info's
C4: IST | D4: Budget | E4: IST | F4: Budget | G4: IST | H4: Budget | I4: IST | J4: Budget | K4: IST | L4: Budget | M4: IST | N4: Budget | O4: IST | P4: Budget | Q4: IST | R4: Budget | S4: IST | T4: Budget | U4: IST | V4: Budget | W4: Wetter | X4: Temp. | Z4: Bemerkung
A5: 1 | B5: Fr | C5: 4611.1 | D5: 4354.8387 | E5: 6119.2 | F5: 1612.9032 | G5: 638.5 | H5: 483.87097 | I5: 2827.2 | K5: 6838.4 | L5: 1612.9032 | M5: -132 | N5: 806.45161 | O5: 3666.2 | P5: 1824.1935 | Q5: =SUM(C5+E5+G5+I5+K5+M5+O5) -> 24568.6 | R5: =SUM(D5+F5+H5+J5+L5+N5+P5) -> 10695.161 | S5: 232.1 | U5: =SUM(Q5+S5) -> 24800.7 | V5: =SUM(R5+T5) -> 10695.161 | W5: sonnig | X5: 20 | Y5: °C
A6: =SUM(A5+1) -> 2 | B6: Sa | C6: 3675.2 | D6: 4354.8387 | E6: 6888.3 | F6: 1612.9032 | G6: 1119.8 | H6: 483.87097 | I6: 405.5 | K6: 6227 | L6: 1612.9032 | M6: 0 | N6: 806.45161 | O6: 4534 | P6: 1824.1935 | Q6: =SUM(C6+E6+G6+I6+K6+M6+O6) -> 22849.8 | R6: =SUM(D6+F6+H6+J6+L6+N6+P6) -> 10695.161 | S6: 304.5 | U6: =SUM(Q6+S6) -> 23154.3 | V6: =SUM(R6+T6) -> 10695.161 | W6: sonnig | X6: 20 | Y6: °C
A7: =SUM(A6+1) -> 3 | B7: So | C7: 4560.8 | D7: 4354.8387 | E7: 6273.9 | F7: 1612.9032 | G7: 561.7 | H7: 483.87097 | I7: 0 | K7: 0 | L7: 1612.9032 | M7: 0 | N7: 806.45161 | O7: 1928 | P7: 1824.1935 | Q7: =SUM(C7+E7+G7+I7+K7+M7+O7) -> 13324.4 | R7: =SUM(D7+F7+H7+J7+L7+N7+P7) -> 10695.161 | S7: 188.7 | U7: =SUM(Q7+S7) -> 13513.1 | V7: =SUM(R7+T7) -> 10695.161 | W7: ziemlich sonnig | X7: 20 | Y7: °C
A8: KW | B8: 40 | C8: =SUM(C5:C7) -> 12847.1 | D8: =SUM(D5:D7) -> 13064.516 | E8: =SUM(E5:E7) -> 19281.4 | F8: =SUM(F5:F7) -> 4838.7097 | G8: =SUM(G5:G7) -> 2320 | H8: =SUM(H5:H7) -> 1451.6129 | I8: =SUM(I5:I7) -> 3232.7 | J8: =SUM(J5:J7) -> 0 | ... V8: =SUM(V5:V7) -> 32085.484 | W8: Ø Temp | X8: =SUM(X5:X7)/3 -> 20 | Y8: °C
A9: =SUM(A7+1) -> 4 | B9: Mo | C9: 3698.2 | D9: 4354.8387 | E9: 65.5 | F9: 1612.9032 | G9: 44.6 | H9: 483.87097 | I9: 0 | K9: 3031.4 | L9: 1612.9032 | M9: 0 | N9: 806.45161 | O9: 1536 | P9: 1824.1935 | Q9: =SUM(C9+E9+G9+I9+K9+M9+O9) -> 8375.7 | R9: =SUM(D9+F9+H9+J9+L9+N9+P9) -> 10695.161 | U9: =SUM(Q9+S9) -> 8375.7 | V9: =SUM(R9+T9) -> 10695.161 | W9: Regen | X9: 13 | Y9: °C
A10: =SUM(A9+1) -> 5 | B10: Di | C10: 5021.7 | D10: 4354.8387 | E10: 223.5 | F10: 1612.9032 | G10: 295.4 | H10: 483.87097 | I10: 0 | K10: 0 | L10: 1612.9032 | M10: 0 | N10: 806.45161 | O10: 2227 | P10: 1824.1935 | Q10: =SUM(C10+E10+G10+I10+K10+M10+O10) -> 7767.6 | R10: =SUM(D10+F10+H10+J10+L10+N10+P10) -> 10695.161 | U10: =SUM(Q10+S10) -> 7767.6 | V10: =SUM(R10+T10) -> 10695.161 | W10: Regen | X10: 13 | Y10: °C
A11: =SUM(A10+1) -> 6 | B11: Mi | C11: 3643.3 | D11: 4354.8387 | E11: 81.6 | F11: 1612.9032 | G11: 32.6 | H11: 483.87097 | I11: 0 | K11: 0 | L11: 1612.9032 | M11: 3996.1 | N11: 806.45161 | O11: 2842.2 | P11: 1824.1935 | Q11: =SUM(C11+E11+G11+I11+K11+M11+O11) -> 10595.8 | R11: =SUM(D11+F11+H11+J11+L11+N11+P11) -> 10695.161 | U11: =SUM(Q11+S11) -> 10595.8 | V11: =SUM(R11+T11) -> 10695.161 | W11: bewölkt | X11: 12 | Y11: °C
A12: =SUM(A11+1) -> 7 | B12: Do | C12: 3901.1 | D12: 4354.8387 | E12: 312 | F12: 1612.9032 | G12: 99.9 | H12: 483.87097 | I12: 0 | K12: 1909 | L12: 1612.9032 | M12: 1788.1 | N12: 806.45161 | O12: 830.8 | P12: 1824.1935 | Q12: 8940.9 | R12: =SUM(D12+F12+H12+J12+L12+N12+P12) -> 10695.161 | U12: =SUM(Q12+S12) -> 8940.9 | V12: =SUM(R12+T12) -> 10695.161 | W12: bewölkt | X12: 12 | Y12: °C
A13: =SUM(A12+1) -> 8 | B13: Fr | C13: 6360 | D13: 4354.8387 | E13: 143.4 | F13: 1612.9032 | G13: 181.5 | H13: 483.87097 | I13: 3830 | K13: 6747.1 | L13: 1612.9032 | M13: 346 | N13: 806.45161 | O13: 4066.2 | P13: 1824.1935 | Q13: =SUM(C13+E13+G13+I13+K13+M13+O13) -> 21674.2 | R13: =SUM(D13+F13+H13+J13+L13+N13+P13) -> 10695.161 | U13: =SUM(Q13+S13) -> 21674.2 | V13: =SUM(R13+T13) -> 10695.161 | W13: Hochnebel | X13: 14 | Y13: °C
A14: =SUM(A13+1) -> 9 | B14: Sa | C14: 7273.1 | D14: 4354.8387 | E14: 227.1 | F14: 1612.9032 | G14: 321.4 | H14: 483.87097 | I14: 3090 | K14: 9005.5 | L14: 1612.9032 | M14: 75 | N14: 806.45161 | O14: 4684.2 | P14: 1824.1935 | Q14: =SUM(C14+E14+G14+I14+K14+M14+O14) -> 24676.3 | R14: =SUM(D14+F14+H14+J14+L14+N14+P14) -> 10695.161 | U14: =SUM(Q14+S14) -> 24676.3 | V14: =SUM(R14+T14) -> 10695.161 | W14: Hochnebel | X14: 12 | Y14: °C
A15: =SUM(A14+1) -> 10 | B15: So | C15: 7004.8 | D15: 4354.8387 | E15: 2056.8 | F15: 1612.9032 | G15: 417.6 | H15: 483.87097 | I15: 0 | K15: 4562.3 | L15: 1612.9032 | M15: 0 | N15: 806.45161 | O15: 2440.9 | P15: 1824.1935 | Q15: =SUM(C15+E15+G15+I15+K15+M15+O15) -> 16482.4 | R15: =SUM(D15+F15+H15+J15+L15+N15+P15) -> 10695.161 | U15: =SUM(Q15+S15) -> 16482.4 | V15: =SUM(R15+T15) -> 10695.161 | W15: Hochnebel | X15: 12 | Y15: °C
A16: KW | B16: =SUM(B8+1) -> 41 | C16: =SUM(C9:C15) -> 36902.2 | D16: =SUM(D9:D15) -> 30483.871 | E16: =SUM(E9:E15) -> 3109.9 | F16: =SUM(F9:F15) -> 11290.323 | G16: =SUM(G9:G15) -> 1393 | H16: =SUM(H9:H15) -> 3387.0968 | I16: =SUM(I9:I15) -> 6920 | J16: =SUM(J9:J15) -> 0 | ... V16: =SUM(V9:V15) -> 74866.129 | W16: Ø Temp | X16: =SUM(X9:X15)/7 -> 12.571429 | Y16: °C
A17: =SUM(A15+1) -> 11 | B17: Mo | C17: 4190.4 | D17: 4354.8387 | E17: 1580.1 | F17: 1612.9032 | G17: 336.7 | H17: 483.87097 | I17: 0 | K17: 595.9 | L17: 1612.9032 | M17: 0 | N17: 806.45161 | O17: 2936.9 | P17: 1824.1935 | Q17: =SUM(C17+E17+G17+I17+K17+M17+O17) -> 9640 | R17: =SUM(D17+F17+H17+J17+L17+N17+P17) -> 10695.161 | U17: =SUM(Q17+S17) -> 9640 | V17: =SUM(R17+T17) -> 10695.161 | W17: sonnig | X17: 12 | Y17: °C
A18: =SUM(A17+1) -> 12 | B18: Di | C18: 6121 | D18: 4354.8387 | E18: 21.7 | F18: 1612.9032 | G18: 54.2 | H18: 483.87097 | I18: 0 | K18: 42 | L18: 1612.9032 | M18: 0 | N18: 806.45161 | O18: 2556.8 | P18: 1824.1935 | Q18: =SUM(C18+E18+G18+I18+K18+M18+O18) -> 8795.7 | R18: =SUM(D18+F18+H18+J18+L18+N18+P18) -> 10695.161 | U18: =SUM(Q18+S18) -> 8795.7 | V18: =SUM(R18+T18) -> 10695.161 | W18: hochnebel | X18: 11 | Y18: °C
A19: =SUM(A18+1) -> 13 | B19: Mi | C19: 5358.2 | D19: 4354.8387 | E19: 135.8 | F19: 1612.9032 | G19: 129.2 | H19: 483.87097 | I19: 0 | K19: 216.7 | L19: 1612.9032 | M19: 0 | N19: 806.45161 | O19: 2391.4 | P19: 1824.1935 | Q19: =SUM(C19+E19+G19+I19+K19+M19+O19) -> 8231.3 | R19: =SUM(D19+F19+H19+J19+L19+N19+P19) -> 10695.161 | U19: =SUM(Q19+S19) -> 8231.3 | V19: =SUM(R19+T19) -> 10695.161 | W19: regen/bewölkt | X19: 12 | Y19: °C
A20: =SUM(A19+1) -> 14 | B20: Do | C20: 4945.6 | D20: 4354.8387 | E20: 1755.5 | F20: 1612.9032 | G20: 433.7 | H20: 483.87097 | I20: 0 | K20: 1719.1 | L20: 1612.9032 | M20: 0 | N20: 806.45161 | O20: 3754.9 | P20: 1824.1935 | Q20: =SUM(C20+E20+G20+I20+K20+M20+O20) -> 12608.8 | R20: =SUM(D20+F20+H20+J20+L20+N20+P20) -> 10695.161 | U20: =SUM(Q20+S20) -> 12608.8 | V20: =SUM(R20+T20) -> 10695.161 | W20: hochnebel/sonne | X20: 12 | Y20: °C
A21: =SUM(A20+1) -> 15 | B21: Fr | C21: 5397 | D21: 4354.8387 | E21: 2631.2 | F21: 1612.9032 | G21: 716.1 | H21: 483.87097 | I21: 0 | K21: 3276.5 | L21: 1612.9032 | N21: 806.45161 | O21: 4052.4 | P21: 1824.1935 | Q21: =SUM(C21+E21+G21+I21+K21+M21+O21) -> 16073.2 | R21: =SUM(D21+F21+H21+J21+L21+N21+P21) -> 10695.161 | U21: =SUM(Q21+S21) -> 16073.2 | V21: =SUM(R21+T21) -> 10695.161 | W21: hochnebel/sonne | X21: 14 | Y21: °C
A22: =SUM(A21+1) -> 16 | B22: Sa | C22: 6945.2 | D22: 4354.8387 | E22: 2699.9 | F22: 1612.9032 | G22: 533.5 | H22: 483.87097 | I22: 0 | K22: 7621.1 | L22: 1612.9032 | M22: 75 | N22: 806.45161 | O22: 5482.8 | P22: 1824.1935 | Q22: =SUM(C22+E22+G22+I22+K22+M22+O22) -> 23357.5 | R22: =SUM(D22+F22+H22+J22+L22+N22+P22) -> 10695.161 | U22: =SUM(Q22+S22) -> 23357.5 | V22: =SUM(R22+T22) -> 10695.161 | W22: nebel/sonne | X22: 13 | Y22: °C
A23: =SUM(A22+1) -> 17 | B23: So | C23: 6803.9 | D23: 4354.8387 | E23: 4824.7 | F23: 1612.9032 | G23: 810 | H23: 483.87097 | I23: 0 | K23: 2389.3 | L23: 1612.9032 | M23: 0 | N23: 806.45161 | O23: 3311.1 | P23: 1824.1935 | Q23: =SUM(C23+E23+G23+I23+K23+M23+O23) -> 18139 | R23: =SUM(D23+F23+H23+J23+L23+N23+P23) -> 10695.161 | U23: =SUM(Q23+S23) -> 18139 | V23: =SUM(R23+T23) -> 10695.161 | W23: nebel/sonne | X23: 16 | Y23: °C
A24: KW | B24: =SUM(B16+1) -> 42 | C24: =SUM(C17:C23) -> 39761.3 | D24: =SUM(D17:D23) -> 30483.871 | E24: =SUM(E17:E23) -> 13648.9 | F24: =SUM(F17:F23) -> 11290.323 | G24: =SUM(G17:G23) -> 3013.4 | H24: =SUM(H17:H23) -> 3387.0968 | I24: =SUM(I17:I23) -> 0 | J24: =SUM(J17:J23) -> 0 | ... V24: =SUM(V17:V23) -> 74866.129 | W24: Ø Temp | X24: =SUM(X17:X23)/7 -> 12.857143 | Y24: °C
A25: =SUM(A23+1) -> 18 | B25: Mo | C25: 3967.1 | D25: 4354.8387 | E25: 3634.3 | F25: 1612.9032 | G25: 383.8 | H25: 483.87097 | I25: 0 | K25: 1220.9 | L25: 1612.9032 | M25: 0 | N25: 806.45161 | O25: 4372.9 | P25: 1824.1935 | Q25: =SUM(C25+E25+G25+I25+K25+M25+O25) -> 13579 | R25: =SUM(D25+F25+H25+J25+L25+N25+P25) -> 10695.161 | U25: =SUM(Q25+S25) -> 13579 | V25: =SUM(R25+T25) -> 10695.161 | W25: sonnig | X25: 17 | Y25: °C
A26: =SUM(A25+1) -> 19 | B26: Di | C26: 6487.1 | D26: 4354.8387 | E26: 901.4 | F26: 1612.9032 | G26: 18.8 | H26: 483.87097 | I26: 0 | K26: 670 | L26: 1612.9032 | M26: 1168.2 | N26: 806.45161 | O26: 4848 | P26: 1824.1935 | Q26: =SUM(C26+E26+G26+I26+K26+M26+O26) -> 14093.5 | R26: =SUM(D26+F26+H26+J26+L26+N26+P26) -> 10695.161 | U26: =SUM(Q26+S26) -> 14093.5 | V26: =SUM(R26+T26) -> 10695.161 | W26: sonnig | X26: 19 | Y26: °C
A27: =SUM(A26+1) -> 20 | B27: Mi | C27: 4035.3 | D27: 4354.8387 | E27: 3257.8 | F27: 1612.9032 | G27: 339 | H27: 483.87097 | I27: 0 | K27: 530 | L27: 1612.9032 | M27: 120.8 | N27: 806.45161 | O27: 3781 | P27: 1824.1935 | Q27: =SUM(C27+E27+G27+I27+K27+M27+O27) -> 12063.9 | R27: =SUM(D27+F27+H27+J27+L27+N27+P27) -> 10695.161 | U27: =SUM(Q27+S27) -> 12063.9 | V27: =SUM(R27+T27) -> 10695.161 | W27: sonnig | X27: 18 | Y27: °C
A28: =SUM(A27+1) -> 21 | B28: Do | C28: 4101 | D28: 4354.8387 | E28: 202.6 | F28: 1612.9032 | G28: 358.2 | H28: 483.87097 | I28: 0 | K28: 1161 | L28: 1612.9032 | M28: 2056.3 | N28: 806.45161 | O28: 1477.8 | P28: 1824.1935 | Q28: =SUM(C28+E28+G28+I28+K28+M28+O28) -> 9356.9 | R28: =SUM(D28+F28+H28+J28+L28+N28+P28) -> 10695.161 | U28: =SUM(Q28+S28) -> 9356.9 | V28: =SUM(R28+T28) -> 10695.161 | W28: sonnig | X28: 18 | Y28: °C
A29: =SUM(A28+1) -> 22 | B29: Fr | C29: 5129.8 | D29: 4354.8387 | E29: 165.3 | F29: 1612.9032 | G29: 0 | H29: 483.87097 | I29: 0 | K29: 3761.3 | L29: 1612.9032 | M29: 702.9 | N29: 806.45161 | O29: 1688.5 | P29: 1824.1935 | Q29: =SUM(C29+E29+G29+I29+K29+M29+O29) -> 11447.8 | R29: =SUM(D29+F29+H29+J29+L29+N29+P29) -> 10695.161 | U29: =SUM(Q29+S29) -> 11447.8 | V29: =SUM(R29+T29) -> 10695.161 | W29: Regen | X29: 10 | Y29: °C
A30: =SUM(A29+1) -> 23 | B30: Sa | C30: 5361.8 | D30: 4354.8387 | E30: 2671.9 | F30: 1612.9032 | G30: 554.4 | H30: 483.87097 | I30: 0 | K30: 4436.9 | L30: 1612.9032 | M30: 1274.1 | N30: 806.45161 | O30: 3646.6 | P30: 1824.1935 | Q30: =SUM(C30+E30+G30+I30+K30+M30+O30) -> 17945.7 | R30: =SUM(D30+F30+H30+J30+L30+N30+P30) -> 10695.161 | U30: =SUM(Q30+S30) -> 17945.7 | V30: =SUM(R30+T30) -> 10695.161 | W30: sonnig | X30: 10 | Y30: °C
A31: =SUM(A30+1) -> 24 | B31: So | C31: 6961 | D31: 4354.8387 | E31: 3254.2 | F31: 1612.9032 | G31: 720.9 | H31: 483.87097 | I31: 0 | K31: 5377.1 | L31: 1612.9032 | M31: 0 | N31: 806.45161 | O31: 1823.1 | P31: 1824.1935 | Q31: =SUM(C31+E31+G31+I31+K31+M31+O31) -> 18136.3 | R31: =SUM(D31+F31+H31+J31+L31+N31+P31) -> 10695.161 | U31: =SUM(Q31+S31) -> 18136.3 | V31: =SUM(R31+T31) -> 10695.161 | W31: sonnig | X31: 16 | Y31: °C
A32: KW | B32: =SUM(B24+1) -> 43 | C32: =SUM(C25:C31) -> 36043.1 | D32: =SUM(D25:D31) -> 30483.871 | E32: =SUM(E25:E31) -> 14087.5 | F32: =SUM(F25:F31) -> 11290.323 | G32: =SUM(G25:G31) -> 2375.1 | H32: =SUM(H25:H31) -> 3387.0968 | I32: =SUM(I25:I31) -> 0 | J32: =SUM(J25:J31) -> 0 | ... V32: =SUM(V25:V31) -> 74866.129 | W32: Ø Temp | X32: =SUM(X25:X31)/7 -> 15.428571 | Y32: °C
A33: =SUM(A31+1) -> 25 | B33: Mo | C33: 4646.5 | D33: 4354.8387 | E33: 1720.7 | F33: 1612.9032 | G33: 262.6 | H33: 483.87097 | I33: 0 | K33: 3425.2 | L33: 1612.9032 | M33: 27 | N33: 806.45161 | O33: 1006.3 | P33: 1824.1935 | Q33: =SUM(C33+E33+G33+I33+K33+M33+O33) -> 11088.3 | R33: =SUM(D33+F33+H33+J33+L33+N33+P33) -> 10695.161 | U33: =SUM(Q33+S33) -> 11088.3 | V33: =SUM(R33+T33) -> 10695.161 | W33: sonnig | X33: 13 | Y33: °C
A34: =SUM(A33+1) -> 26 | B34: Di | C34: 4770.4 | D34: 4354.8387 | E34: 154.4 | F34: 1612.9032 | G34: 89.6 | H34: 483.87097 | I34: 0 | K34: 370.1 | L34: 1612.9032 | M34: 4113.3 | N34: 806.45161 | O34: 2151.3 | P34: 1824.1935 | Q34: =SUM(C34+E34+G34+I34+K34+M34+O34) -> 11649.1 | R34: =SUM(D34+F34+H34+J34+L34+N34+P34) -> 10695.161 | U34: =SUM(Q34+S34) -> 11649.1 | V34: =SUM(R34+T34) -> 10695.161 | W34: leichte Regenschauer | X34: 13 | Y34: °C
A35: =SUM(A34+1) -> 27 | B35: Mi | C35: 5750.4 | D35: 4354.8387 | E35: 263.6 | F35: 1612.9032 | G35: 146 | H35: 483.87097 | I35: 0 | K35: 115.6 | L35: 1612.9032 | M35: 1046.8 | N35: 806.45161 | O35: 2407.5 | P35: 1824.1935 | Q35: =SUM(C35+E35+G35+I35+K35+M35+O35) -> 9729.9 | R35: =SUM(D35+F35+H35+J35+L35+N35+P35) -> 10695.161 | U35: =SUM(Q35+S35) -> 9729.9 | V35: =SUM(R35+T35) -> 10695.161 | W35: nebel/sonne | X35: 12 | Y35: °C
A36: =SUM(A35+1) -> 28 | B36: Do | C36: 4162.4 | D36: 4354.8387 | E36: 424.5 | F36: 1612.9032 | G36: 234.5 | H36: 483.87097 | I36: 0 | K36: 45.4 | L36: 1612.9032 | M36: 679.2 | N36: 806.45161 | O36: 3974.3 | P36: 1824.1935 | Q36: =SUM(C36+E36+G36+I36+K36+M36+O36) -> 9520.3 | R36: =SUM(D36+F36+H36+J36+L36+N36+P36) -> 10695.161 | U36: =SUM(Q36+S36) -> 9520.3 | V36: =SUM(R36+T36) -> 10695.161 | W36: nebel/sonne | X36: 13 | Y36: °C
A37: =SUM(A36+1) -> 29 | B37: Fr | C37: 5143.6 | D37: 4354.8387 | E37: 955.3 | F37: 1612.9032 | G37: 403.5 | H37: 483.87097 | I37: 0 | K37: 2323.6 | L37: 1612.9032 | M37: 1563.7 | N37: 806.45161 | O37: 1860.6 | P37: 1824.1935 | Q37: =SUM(C37+E37+G37+I37+K37+M37+O37) -> 12250.3 | R37: =SUM(D37+F37+H37+J37+L37+N37+P37) -> 10695.161 | U37: =SUM(Q37+S37) -> 12250.3 | V37: =SUM(R37+T37) -> 10695.161 | W37: nebel/sonne | X37: 12 | Y37: °C
A38: =SUM(A37+1) -> 30 | B38: Sa | C38: 6923.9 | D38: 4354.8387 | E38: 10.6 | F38: 1612.9032 | G38: 19.5 | H38: 483.87097 | I38: 0 | K38: 2542.3 | L38: 1612.9032 | M38: 601.2 | N38: 806.45161 | O38: 3673.7 | P38: 1824.1935 | Q38: =SUM(C38+E38+G38+I38+K38+M38+O38) -> 13771.2 | R38: =SUM(D38+F38+H38+J38+L38+N38+P38) -> 10695.161 | U38: =SUM(Q38+S38) -> 13771.2 | V38: =SUM(R38+T38) -> 10695.161 | W38: bewölkt | X38: 8 | Y38: °C
A39: =SUM(A38+1) -> 31 | B39: So | C39: 8936 | D39: 4354.8387 | E39: 3823.2 | F39: 1612.9032 | G39: 826.5 | H39: 483.87097 | I39: 0 | K39: 2950.5 | L39: 1612.9032 | M39: -25 | N39: 806.45161 | O39: 2537.92 | P39: 1824.1935 | Q39: =SUM(C39+E39+G39+I39+K39+M39+O39) -> 19049.12 | R39: =SUM(D39+F39+H39+J39+L39+N39+P39) -> 10695.161 | U39: =SUM(Q39+S39) -> 19049.12 | V39: =SUM(R39+T39) -> 10695.161 | W39: sonnig | X39: 16 | Y39: °C
A40: KW | B40: =SUM(B32+1) -> 44 | C40: =SUM(C33:C39) -> 40333.2 | D40: =SUM(D33:D39) -> 30483.871 | E40: =SUM(E33:E39) -> 7352.3 | F40: =SUM(F33:F39) -> 11290.323 | G40: =SUM(G33:G39) -> 1982.2 | H40: =SUM(H33:H39) -> 3387.0968 | I40: =SUM(I33:I39) -> 0 | J40: =SUM(J33:J39) -> 0 | ... V40: =SUM(V33:V39) -> 74866.129 | W40: Ø Temp | X40: =SUM(X33:X39)/7 -> 12.428571 | Y40: °C
A41: Umsatz kumuliert | C41: =SUM(C8+C16+C24+C32+C40) -> 165886.9 | D41: =SUM(D8+D16+D24+D32+D40) -> 135000 | E41: =SUM(E8+E16+E24+E32+E40) -> 57480 | F41: =SUM(F8+F16+F24+F32+F40) -> 50000 | G41: =SUM(G8+G16+G24+G32+G40) -> 11083.7 | H41: =SUM(H8+H16+H24+H32+H40) -> 15000 | I41: =SUM(I8+I16+I24+I32+I40) -> 10152.7 | J41: =SUM(J8+J16+J24+J32+J40) -> 0 | ... V41: =SUM(V8+V16+V24+V32+V40) -> 331550 | W41: Umsatz kumuliert
A42: Umsatz Forecast | C42: =IF(MONTH($H$1)<>MONTH(TODAY()),C41,SUM(C5:C7,C9:C15,C17:C23,C25:C31,C33:C39)/DAY(TODAY())*DAY(DATE(YEAR($H$1),MONTH($H$1)+1,1)-1)) -> 165886.9 | D42: =IF(MONTH($H$1)<>MONTH(TODAY()),D41,SUM(D5:D7,D9:D15,D17:D23,D25:D31,D33:D39)/DAY(TODAY())*DAY(DATE(YEAR($H$1),MONTH($H$1)+1,1)-1)) -> 135000 | E42: =IF(MONTH($H$1)<>MONTH(TODAY()),E41,SUM(E5:E7,E9:E15,E17:E23,E25:E31,E33:E39)/DAY(TODAY())*DAY(DATE(YEAR($H$1),MONTH($H$1)+1,1)-1)) -> 57480 | F42: =IF(MONTH($H$1)<>MONTH(TODAY()),F41,SUM(F5:F7,F9:F15,F17:F23,F25:F31,F33:F39)/DAY(TODAY())*DAY(DATE(YEAR($H$1),MONTH($H$1)+1,1)-1)) -> 50000 | G42: =IF(MONTH($H$1)<>MONTH(TODAY()),G41,SUM(G5:G7,G9:G15,G17:G23,G25:G31,G33:G39)/DAY(TODAY())*DAY(DATE(YEAR($H$1),MONTH($H$1)+1,1)-1)) -> 11083.7 | H42: =IF(MONTH($H$1)<>MONTH(TODAY()),H41,SUM(H5:H7,H9:H15,H17:H23,H25:H31,H33:H39)/DAY(TODAY())*DAY(DATE(YEAR($H$1),MONTH($H$1)+1,1)-1)) -> 15000 | I42: =IF(MONTH($H$1)<>MONTH(TODAY()),I41,SUM(I5:I7,I9:I15,I17:I23,I25:I31,I33:I39)/DAY(TODAY())*DAY(DATE(YEAR($H$1),MONTH($H$1)+1,1)-1)) -> 10152.7 | J42: =IF(MONTH($H$1)<>MONTH(TODAY()),J41,SUM(J5:J7,J9:J15,J17:J23,J25:J31,J33:J39)/DAY(TODAY())*DAY(DATE(YEAR($H$1),MONTH($H$1)+1,1)-1)) -> 0 | ... V42: =IF(MONTH($H$1)<>MONTH(TODAY()),V41,SUM(V5:V7,V9:V15,V17:V23,V25:V31,V33:V39)/DAY(TODAY())*DAY(DATE(YEAR($H$1),MONTH($H$1)+1,1)-1)) -> 331550 | W42: Umsatz Forecast
A43: Umsatz pro Tag | C43: =C41/31 -> 5351.1903 | D43: =D41/31 -> 4354.8387 | E43: =E41/31 -> 1854.1935 | F43: =F41/31 -> 1612.9032 | G43: =G41/31 -> 357.53871 | H43: =H41/31 -> 483.87097 | I43: =I41/31 -> 327.50645 | J43: =J41/31 -> 0 | ... V43: =V41/31 -> 10695.161 | W43: Budget pro Tag
A44: Diff. zu Budget | C44: =SUM(C41-D41) -> 30886.9 | E44: =SUM(E41-F41) -> 7480 | G44: =SUM(G41-H41) -> -3916.3 | I44: =SUM(I41-J41) -> 10152.7 | K44: =SUM(K41-L41) -> 33111.2 | M44: =SUM(M41-N41) -> -5523.3 | O44: =SUM(O41-P41) -> 35941.32 | Q44: =SUM(Q41-R41) -> 108232.52 | S44: =SUM(S41-T41) -> 725.3 | U44: =SUM(U41-V41) -> 108957.82
A45: Index | C45: =SUM(100/D41*C41) -> 122.87919 | E45: =SUM(100/F41*E41) -> 114.96 | G45: =SUM(100/H41*G41) -> 73.891333 | I45: =SUM(100/J41*I41) -> #DIV/0! | K45: =SUM(100/L41*K41) -> 166.2224 | M45: =SUM(100/N41*M41) -> 77.9068 | O45: =SUM(100/P41*O41) -> 163.55671 | Q45: =SUM(100/R41*Q41) -> 132.6444 | S45: =SUM(100/T41*S41) -> #DIV/0! | U45: =SUM(100/V41*U41) -> 132.86316

Sheet 11_21
A1: Tagesumsätze | H1: 44501
C3: Restaurant | E3: Terrasse | G3: Lounge | I3: Pavillon | K3: Bankett | M3: Seminar | O3: Hotel | Q3: TOTAL Gesamtbetrieb ohne Seebad | S3: Seebad | U3: TOTAL Gesamtbetrieb mit Seebad | W3: Info's
C4: IST | D4: Budget | E4: IST | F4: Budget | G4: IST | H4: Budget | I4: IST | J4: Budget | K4: IST | L4: Budget | M4: IST | N4: Budget | O4: IST | P4: Budget | Q4: IST | R4: Budget | S4: IST | T4: Budget | U4: IST | V4: Budget | W4: Wetter | X4: Temp. | Z4: Bemerkung
A5: 1 | B5: Mo | C5: 4462.7 | D5: 4500 | E5: 20.2 | F5: 166.66666 | G5: 0 | H5: 66.66666 | I5: 0 | K5: 828.7 | L5: 1500 | M5: 0 | N5: 1500 | O5: 462.4 | P5: 1881.6667 | Q5: =SUM(C5+E5+G5+I5+K5+M5+O5) -> 5774 | R5: =SUM(D5+F5+H5+J5+L5+N5+P5) -> 9615 | S5: 0 | U5: =SUM(Q5+S5) -> 5774 | V5: =SUM(R5+T5) -> 9615 | W5: Regen | X5: 8 | Y5: °C
A6: =SUM(A5+1) -> 2 | B6: Di | C6: 3533.8 | D6: 4500 | E6: 79.7 | F6: 166.66666 | G6: 167.6 | H6: 66.66666 | I6: 0 | K6: 0 | L6: 1500 | M6: 23 | N6: 1500 | O6: 1568.8 | P6: 1881.6667 | Q6: =SUM(C6+E6+G6+I6+K6+M6+O6) -> 5372.9 | R6: =SUM(D6+F6+H6+J6+L6+N6+P6) -> 9615 | S6: 0 | U6: =SUM(Q6+S6) -> 5372.9 | V6: =SUM(R6+T6) -> 9615 | W6: Regen | X6: 10 | Y6: °C
A7: =SUM(A6+1) -> 3 | B7: Mi | C7: 3874 | D7: 4500 | E7: 0 | F7: 166.66666 | G7: 0 | H7: 66.66666 | I7: 0 | K7: 0 | L7: 1500 | M7: 943.3 | N7: 1500 | O7: 1878.8 | P7: 1881.6667 | Q7: =SUM(C7+E7+G7+I7+K7+M7+O7) -> 6696.1 | R7: =SUM(D7+F7+H7+J7+L7+N7+P7) -> 9615 | S7: 0 | U7: =SUM(Q7+S7) -> 6696.1 | V7: =SUM(R7+T7) -> 9615 | W7: Regen | X7: 7 | Y7: °C
A8: =SUM(A7+1) -> 4 | B8: Do | C8: 2688.9 | D8: 4500 | E8: 0 | F8: 166.66666 | G8: 25 | H8: 66.66666 | I8: 0 | K8: 0 | L8: 1500 | M8: 7074.8 | N8: 1500 | O8: 1323.1 | P8: 1881.6667 | Q8: =SUM(C8+E8+G8+I8+K8+M8+O8) -> 11111.8 | R8: =SUM(D8+F8+H8+J8+L8+N8+P8) -> 9615 | S8: 0 | U8: =SUM(Q8+S8) -> 11111.8 | V8: =SUM(R8+T8) -> 9615 | W8: sonnig | X8: 10 | Y8: °C
A9: =SUM(A8+1) -> 5 | B9: Fr | C9: 4390.4 | D9: 4500 | E9: 43.5 | F9: 166.66666 | G9: 33.7 | H9: 66.66666 | I9: 0 | K9: 1219.5 | L9: 1500 | M9: 1891.8 | N9: 1500 | O9: 1041.8 | P9: 1881.6667 | Q9: =SUM(C9+E9+G9+I9+K9+M9+O9) -> 8620.7 | R9: =SUM(D9+F9+H9+J9+L9+N9+P9) -> 9615 | S9: 0 | U9: =SUM(Q9+S9) -> 8620.7 | V9: =SUM(R9+T9) -> 9615 | W9: bewölkt | X9: 10 | Y9: °C
A10: =SUM(A9+1) -> 6 | B10: Sa | C10: 7931.6 | D10: 4500 | E10: 92.5 | F10: 166.66666 | G10: 111.7 | H10: 66.66666 | I10: 0 | K10: 4278.7 | L10: 1500 | M10: 0 | N10: 1500 | O10: 821 | P10: 1881.6667 | Q10: =SUM(C10+E10+G10+I10+K10+M10+O10) -> 13235.5 | R10: =SUM(D10+F10+H10+J10+L10+N10+P10) -> 9615 | S10: 0 | U10: =SUM(Q10+S10) -> 13235.5 | V10: =SUM(R10+T10) -> 9615 | W10: ziemlich sonnig | X10: 6 | Y10: °C
A11: =SUM(A10+1) -> 7 | B11: So | C11: 6907.4 | D11: 4500 | E11: 3084.3 | F11: 166.66666 | G11: 623.6 | H11: 66.66666 | I11: 0 | K11: 3578.6 | L11: 1500 | M11: 0 | N11: 1500 | O11: 38 | P11: 1881.6667 | Q11: =SUM(C11+E11+G11+I11+K11+M11+O11) -> 14231.9 | R11: =SUM(D11+F11+H11+J11+L11+N11+P11) -> 9615 | S11: 0 | U11: =SUM(Q11+S11) -> 14231.9 | V11: =SUM(R11+T11) -> 9615 | W11: sonnig | X11: 10 | Y11: °C
A12: KW | B12: 45 | C12: =SUM(C5:C11) -> 33788.8 | D12: =SUM(D5:D11) -> 31500 | E12: =SUM(E5:E11) -> 3320.2 | F12: =SUM(F5:F11) -> 1166.6666 | G12: =SUM(G5:G11) -> 961.6 | H12: =SUM(H5:H11) -> 466.66662 | I12: =SUM(I5:I11) -> 0 | J12: =SUM(J5:J11) -> 0 | ... V12: =SUM(V5:V11) -> 67305 | W12: Ø Temp | X12: =SUM(X5:X11)/7 -> 8.7142857 | Y12: °C
A13: =SUM(A11+1) -> 8 | B13: Mo | C13: 2248.9 | D13: 4500 | E13: 0 | F13: 166.66666 | G13: 9.2 | H13: 66.66666 | I13: 0 | K13: 0 | L13: 1500 | M13: 0 | N13: 1500 | O13: 433.4 | P13: 1881.6667 | Q13: =SUM(C13+E13+G13+I13+K13+M13+O13) -> 2691.5 | R13: =SUM(D13+F13+H13+J13+L13+N13+P13) -> 9615 | S13: 0 | U13: =SUM(Q13+S13) -> 2691.5 | V13: =SUM(R13+T13) -> 9615 | W13: bewölkt | X13: 8 | Y13: °C
A14: =SUM(A13+1) -> 9 | B14: Di | C14: 3694 | D14: 4500 | E14: 0 | F14: 166.66666 | G14: 0 | H14: 66.66666 | I14: 0 | K14: 0 | L14: 1500 | M14: 4295.6 | N14: 1500 | O14: 2390.7 | P14: 1881.6667 | Q14: =SUM(C14+E14+G14+I14+K14+M14+O14) -> 10380.3 | R14: =SUM(D14+F14+H14+J14+L14+N14+P14) -> 9615 | S14: 0 | U14: =SUM(Q14+S14) -> 10380.3 | V14: =SUM(R14+T14) -> 9615 | W14: bewölkt | X14: 8 | Y14: °C
A15: =SUM(A14+1) -> 10 | B15: Mi | C15: 3759 | D15: 4500 | E15: 9.2 | F15: 166.66666 | G15: 0 | H15: 66.66666 | I15: 0 | K15: 0 | L15: 1500 | M15: 1589.9 | N15: 1500 | O15: 2943.2 | P15: 1881.6667 | Q15: =SUM(C15+E15+G15+I15+K15+M15+O15) -> 8301.3 | R15: =SUM(D15+F15+H15+J15+L15+N15+P15) -> 9615 | S15: 0 | U15: =SUM(Q15+S15) -> 8301.3 | V15: =SUM(R15+T15) -> 9615 | W15: bewölkt | X15: 8 | Y15: °C
A16: =SUM(A15+1) -> 11 | B16: Do | C16: 4236.1 | D16: 4500 | E16: 402.5 | F16: 166.66666 | G16: 54.5 | H16: 66.66666 | I16: 0 | K16: 132 | L16: 1500 | M16: 0 | N16: 1500 | O16: 2026.1 | P16: 1881.6667 | Q16: =SUM(C16+E16+G16+I16+K16+M16+O16) -> 6851.2 | R16: =SUM(D16+F16+H16+J16+L16+N16+P16) -> 9615 | S16: 0 | U16: =SUM(Q16+S16) -> 6851.2 | V16: =SUM(R16+T16) -> 9615 | W16: sonnig | X16: 8 | Y16: °C
A17: =SUM(A16+1) -> 12 | B17: Fr | C17: 5175.2 | D17: 4500 | E17: 0 | F17: 166.66666 | G17: 0 | H17: 66.66666 | I17: 0 | K17: 1668.2 | L17: 1500 | M17: 5740.5 | N17: 1500 | O17: 2317.2 | P17: 1881.6667 | Q17: =SUM(C17+E17+G17+I17+K17+M17+O17) -> 14901.1 | R17: =SUM(D17+F17+H17+J17+L17+N17+P17) -> 9615 | S17: 0 | U17: =SUM(Q17+S17) -> 14901.1 | V17: =SUM(R17+T17) -> 9615 | W17: Nebel | X17: 8 | Y17: °C
A18: =SUM(A17+1) -> 13 | B18: Sa | C18: 5973.8 | D18: 4500 | E18: 0 | F18: 166.66666 | G18: 22.8 | H18: 66.66666 | I18: 0 | K18: 3506.4 | L18: 1500 | M18: 1522.7 | N18: 1500 | O18: 2038.9 | P18: 1881.6667 | Q18: =SUM(C18+E18+G18+I18+K18+M18+O18) -> 13064.6 | R18: =SUM(D18+F18+H18+J18+L18+N18+P18) -> 9615 | S18: 0 | U18: =SUM(Q18+S18) -> 13064.6 | V18: =SUM(R18+T18) -> 9615 | W18: Nebel | X18: 8 | Y18: °C
A19: =SUM(A18+1) -> 14 | B19: So | C19: 6051.2 | D19: 4500 | E19: 0 | F19: 166.66666 | G19: 9.6 | H19: 66.66666 | I19: 0 | K19: 4566 | L19: 1500 | M19: 0 | N19: 1500 | O19: 727 | P19: 1881.6667 | Q19: =SUM(C19+E19+G19+I19+K19+M19+O19) -> 11353.8 | R19: =SUM(D19+F19+H19+J19+L19+N19+P19) -> 9615 | S19: 0 | U19: =SUM(Q19+S19) -> 11353.8 | V19: =SUM(R19+T19) -> 9615 | W19: Regen | X19: 7 | Y19: °C
A20: KW | B20: =SUM(B12+1) -> 46 | C20: =SUM(C13:C19) -> 31138.2 | D20: =SUM(D13:D19) -> 31500 | E20: =SUM(E13:E19) -> 411.7 | F20: =SUM(F13:F19) -> 1166.6666 | G20: =SUM(G13:G19) -> 96.1 | H20: =SUM(H13:H19) -> 466.66662 | I20: =SUM(I13:I19) -> 0 | J20: =SUM(J13:J19) -> 0 | ... V20: =SUM(V13:V19) -> 67305 | W20: Ø Temp | X20: =SUM(X13:X19)/7 -> 7.8571429 | Y20: °C
A21: =SUM(A19+1) -> 15 | B21: Mo | C21: 1665.9 | D21: 4500 | E21: 0 | F21: 166.66666 | G21: 0 | H21: 66.66666 | I21: 0 | K21: 0 | L21: 1500 | M21: 1237.9 | N21: 1500 | O21: 1293.9 | P21: 1881.6667 | Q21: =SUM(C21+E21+G21+I21+K21+M21+O21) -> 4197.7 | R21: =SUM(D21+F21+H21+J21+L21+N21+P21) -> 9615 | S21: 0 | U21: =SUM(Q21+S21) -> 4197.7 | V21: =SUM(R21+T21) -> 9615 | W21: Nebel | X21: 8 | Y21: °C
A22: =SUM(A21+1) -> 16 | B22: Di | C22: 2680.5 | D22: 4500 | E22: 0 | F22: 166.66666 | G22: 0 | H22: 66.66666 | I22: 0 | K22: 0 | L22: 1500 | M22: 0 | N22: 1500 | O22: 2612.3 | P22: 1881.6667 | Q22: =SUM(C22+E22+G22+I22+K22+M22+O22) -> 5292.8 | R22: =SUM(D22+F22+H22+J22+L22+N22+P22) -> 9615 | S22: 0 | U22: =SUM(Q22+S22) -> 5292.8 | V22: =SUM(R22+T22) -> 9615 | W22: Nebel | X22: 8 | Y22: °C
A23: =SUM(A22+1) -> 17 | B23: Mi | C23: 4887.9 | D23: 4500 | E23: 0 | F23: 166.66666 | G23: 0 | H23: 66.66666 | I23: 0 | K23: 51.4 | L23: 1500 | M23: 2872.8 | N23: 1500 | O23: 2843.4 | P23: 1881.6667 | Q23: =SUM(C23+E23+G23+I23+K23+M23+O23) -> 10655.5 | R23: =SUM(D23+F23+H23+J23+L23+N23+P23) -> 9615 | S23: 0 | U23: =SUM(Q23+S23) -> 10655.5 | V23: =SUM(R23+T23) -> 9615 | W23: bewölkt | X23: 8 | Y23: °C
A24: =SUM(A23+1) -> 18 | B24: Do | C24: 4199.8 | D24: 4500 | E24: 0 | F24: 166.66666 | G24: 25.5 | H24: 66.66666 | I24: 0 | K24: 1253.65 | L24: 1500 | M24: 2340.9 | N24: 1500 | O24: 1913.4 | P24: 1881.6667 | Q24: =SUM(C24+E24+G24+I24+K24+M24+O24) -> 9733.25 | R24: =SUM(D24+F24+H24+J24+L24+N24+P24) -> 9615 | S24: 0 | U24: =SUM(Q24+S24) -> 9733.25 | V24: =SUM(R24+T24) -> 9615 | W24: bewölkt | X24: 6 | Y24: °C
A25: =SUM(A24+1) -> 19 | B25: Fr | C25: 5449.5 | D25: 4500 | E25: 0 | F25: 166.66666 | G25: 12.1 | H25: 66.66666 | I25: 0 | K25: 1908.8 | L25: 1500 | M25: 977.6 | N25: 1500 | O25: 1174.8 | P25: 1881.6667 | Q25: =SUM(C25+E25+G25+I25+K25+M25+O25) -> 9522.8 | R25: =SUM(D25+F25+H25+J25+L25+N25+P25) -> 9615 | S25: 0 | U25: =SUM(Q25+S25) -> 9522.8 | V25: =SUM(R25+T25) -> 9615 | W25: bewölkt | X25: 5 | Y25: °C
A26: =SUM(A25+1) -> 20 | B26: Sa | C26: 6244.7 | D26: 4500 | E26: 0 | F26: 166.66666 | G26: 23.5 | H26: 66.66666 | I26: 0 | K26: 2602.6 | L26: 1500 | M26: 0 | N26: 1500 | O26: 3334.5 | P26: 1881.6667 | Q26: =SUM(C26+E26+G26+I26+K26+M26+O26) -> 12205.3 | R26: =SUM(D26+F26+H26+J26+L26+N26+P26) -> 9615 | S26: 0 | U26: =SUM(Q26+S26) -> 12205.3 | V26: =SUM(R26+T26) -> 9615 | W26: bewölkt | X26: 5 | Y26: °C
A27: =SUM(A26+1) -> 21 | B27: So | C27: 7352.7 | D27: 4500 | E27: 0 | F27: 166.66666 | G27: 0 | H27: 66.66666 | I27: 0 | K27: 2383 | L27: 1500 | M27: 0 | N27: 1500 | O27: 1040.3 | P27: 1881.6667 | Q27: =SUM(C27+E27+G27+I27+K27+M27+O27) -> 10776 | R27: =SUM(D27+F27+H27+J27+L27+N27+P27) -> 9615 | S27: 0 | U27: =SUM(Q27+S27) -> 10776 | V27: =SUM(R27+T27) -> 9615 | W27: bewölkt | X27: 5 | Y27: °C
A28: KW | B28: =SUM(B20+1) -> 47 | C28: =SUM(C21:C27) -> 32481 | D28: =SUM(D21:D27) -> 31500 | E28: =SUM(E21:E27) -> 0 | F28: =SUM(F21:F27) -> 1166.6666 | G28: =SUM(G21:G27) -> 61.1 | H28: =SUM(H21:H27) -> 466.66662 | I28: =SUM(I21:I27) -> 0 | J28: =SUM(J21:J27) -> 0 | ... V28: =SUM(V21:V27) -> 67305 | W28: Ø Temp | X28: =SUM(X21:X27)/7 -> 6.4285714 | Y28: °C
A29: =SUM(A27+1) -> 22 | B29: Mo | C29: 2416.3 | D29: 4500 | E29: 0 | F29: 166.66666 | G29: 0 | H29: 66.66666 | I29: 0 | K29: 286 | L29: 1500 | M29: 0 | N29: 1500 | O29: 1800.3 | P29: 1881.6667 | Q29: =SUM(C29+E29+G29+I29+K29+M29+O29) -> 4502.6 | R29: =SUM(D29+F29+H29+J29+L29+N29+P29) -> 9615 | S29: 0 | U29: =SUM(Q29+S29) -> 4502.6 | V29: =SUM(R29+T29) -> 9615 | W29: bewölkt | X29: 4 | Y29: °C
A30: =SUM(A29+1) -> 23 | B30: Di | C30: 6043.1 | D30: 4500 | E30: 0 | F30: 166.66666 | G30: 62.1 | H30: 66.66666 | I30: 0 | K30: 3795.8 | L30: 1500 | M30: 1526.3 | N30: 1500 | O30: 3094.4 | P30: 1881.6667 | Q30: =SUM(C30+E30+G30+I30+K30+M30+O30) -> 14521.7 | R30: =SUM(D30+F30+H30+J30+L30+N30+P30) -> 9615 | S30: 0 | U30: =SUM(Q30+S30) -> 14521.7 | V30: =SUM(R30+T30) -> 9615 | W30: bewölkt | X30: 4 | Y30: °C
A31: =SUM(A30+1) -> 24 | B31: Mi | C31: 5963 | D31: 4500 | E31: 0 | F31: 166.66666 | G31: 10 | H31: 66.66666 | I31: 0 | K31: 0 | L31: 1500 | M31: 648 | N31: 1500 | O31: 2789.9 | P31: 1881.6667 | Q31: =SUM(C31+E31+G31+I31+K31+M31+O31) -> 9410.9 | R31: =SUM(D31+F31+H31+J31+L31+N31+P31) -> 9615 | S31: 0 | U31: =SUM(Q31+S31) -> 9410.9 | V31: =SUM(R31+T31) -> 9615 | W31: bewölkt | X31: 4 | Y31: °C
A32: =SUM(A31+1) -> 25 | B32: Do | C32: 2965.5 | D32: 4500 | E32: 0 | F32: 166.66666 | G32: 0 | H32: 66.66666 | I32: 0 | K32: 0 | L32: 1500 | M32: 5528.6 | N32: 1500 | O32: 1105.1 | P32: 1881.6667 | Q32: =SUM(C32+E32+G32+I32+K32+M32+O32) -> 9599.2 | R32: =SUM(D32+F32+H32+J32+L32+N32+P32) -> 9615 | S32: 0 | U32: =SUM(Q32+S32) -> 9599.2 | V32: =SUM(R32+T32) -> 9615 | W32: bewölkt | X32: 3 | Y32: °C
A33: =SUM(A32+1) -> 26 | B33: Fr | C33: 6465 | D33: 4500 | E33: 0 | F33: 166.66666 | G33: 32.4 | H33: 66.66666 | I33: 0 | K33: 2171.9 | L33: 1500 | M33: 3317.05 | N33: 1500 | O33: 571.5 | P33: 1881.6667 | Q33: =SUM(C33+E33+G33+I33+K33+M33+O33) -> 12557.85 | R33: =SUM(D33+F33+H33+J33+L33+N33+P33) -> 9615 | S33: 0 | U33: =SUM(Q33+S33) -> 12557.85 | V33: =SUM(R33+T33) -> 9615 | W33: bewölkt | X33: 3 | Y33: °C
A34: =SUM(A33+1) -> 27 | B34: Sa | C34: 6971.4 | D34: 4500 | E34: 0 | F34: 166.66666 | G34: 0 | H34: 66.66666 | I34: 0 | K34: 5842.5 | L34: 1500 | M34: 0 | N34: 1500 | O34: 2332.8 | P34: 1881.6667 | Q34: =SUM(C34+E34+G34+I34+K34+M34+O34) -> 15146.7 | R34: =SUM(D34+F34+H34+J34+L34+N34+P34) -> 9615 | S34: 0 | U34: =SUM(Q34+S34) -> 15146.7 | V34: =SUM(R34+T34) -> 9615 | W34: bewölkt | X34: 3 | Y34: °C
A35: =SUM(A34+1) -> 28 | B35: So | C35: 4825 | D35: 4500 | E35: 0 | F35: 166.66666 | G35: 0 | H35: 66.66666 | I35: 0 | K35: 1032 | L35: 1500 | M35: 0 | N35: 1500 | O35: 107.55 | P35: 1881.6667 | Q35: =SUM(C35+E35+G35+I35+K35+M35+O35) -> 5964.55 | R35: =SUM(D35+F35+H35+J35+L35+N35+P35) -> 9615 | S35: 0 | U35: =SUM(Q35+S35) -> 5964.55 | V35: =SUM(R35+T35) -> 9615 | W35: Schneeschauer | X35: 0 | Y35: °C
A36: KW | B36: =SUM(B28+1) -> 48 | C36: =SUM(C29:C35) -> 35649.3 | D36: =SUM(D29:D35) -> 31500 | E36: =SUM(E29:E35) -> 0 | F36: =SUM(F29:F35) -> 1166.6666 | G36: =SUM(G29:G35) -> 104.5 | H36: =SUM(H29:H35) -> 466.66662 | I36: =SUM(I29:I35) -> 0 | J36: =SUM(J29:J35) -> 0 | ... V36: =SUM(V29:V35) -> 67305 | W36: Ø Temp | X36: =SUM(X29:X35)/7 -> 3 | Y36: °C
A37: =SUM(A35+1) -> 29 | B37: Mo | C37: 2180.3 | D37: 4500 | E37: 0 | F37: 166.66666 | G37: 0 | H37: 66.66666 | I37: 0 | K37: 9.2 | L37: 1500 | M37: 0 | N37: 1500 | O37: 493.4 | P37: 1881.6667 | Q37: =SUM(C37+E37+G37+I37+K37+M37+O37) -> 2682.9 | R37: =SUM(D37+F37+H37+J37+L37+N37+P37) -> 9615 | S37: 0 | U37: =SUM(Q37+S37) -> 2682.9 | V37: =SUM(R37+T37) -> 9615 | W37: Schneeschauer | X37: 0 | Y37: °C
A38: =SUM(A37+1) -> 30 | B38: Di | C38: 3879.1 | D38: 4500 | E38: 0 | F38: 166.66666 | G38: 0 | H38: 66.66666 | I38: 0 | K38: 147.9 | L38: 1500 | M38: 41.4 | N38: 1500 | O38: 1859.4 | P38: 1881.6667 | Q38: =SUM(C38+E38+G38+I38+K38+M38+O38) -> 5927.8 | R38: =SUM(D38+F38+H38+J38+L38+N38+P38) -> 9615 | S38: 0 | U38: =SUM(Q38+S38) -> 5927.8 | V38: =SUM(R38+T38) -> 9615 | W38: bewölkt | X38: 2 | Y38: °C
A39: KW | B39: =SUM(B36+1) -> 49 | C39: =SUM(C37:C38) -> 6059.4 | D39: =SUM(D37:D38) -> 9000 | E39: =SUM(E37:E38) -> 0 | F39: =SUM(F37:F38) -> 333.33332 | G39: =SUM(G37:G38) -> 0 | H39: =SUM(H37:H38) -> 133.33332 | I39: =SUM(I37:I38) -> 0 | J39: =SUM(J37:J38) -> 0 | ... V39: =SUM(V37:V38) -> 19230 | W39: Ø Temp | X39: =SUM(X37:X38)/2 -> 1 | Y39: °C
A40: Umsatz kumuliert | C40: =SUM(C12+C20+C28+C36+C39) -> 139116.7 | D40: =SUM(D12+D20+D28+D36+D39) -> 135000 | E40: =SUM(E12+E20+E28+E36+E39) -> 3731.9 | F40: =SUM(F12+F20+F28+F36+F39) -> 4999.9998 | G40: =SUM(G12+G20+G28+G36+G39) -> 1223.3 | H40: =SUM(H12+H20+H28+H36+H39) -> 1999.9998 | I40: =SUM(I12+I20+I28+I36+I39) -> 0 | J40: =SUM(J12+J20+J28+J36+J39) -> 0 | ... V40: =SUM(V12+V20+V28+V36+V39) -> 288450 | W40: Umsatz kumuliert
A41: Umsatz Forecast | C41: =IF(MONTH($H$1)<>MONTH(TODAY()),C40,SUM(C5:C11,C13:C19,C21:C27,C29:C35,C37:C38)/DAY(TODAY())*DAY(DATE(YEAR($H$1),MONTH($H$1)+1,1)-1)) -> 189704.59 | D41: =IF(MONTH($H$1)<>MONTH(TODAY()),D40,SUM(D5:D11,D13:D19,D21:D27,D29:D35,D37:D38)/DAY(TODAY())*DAY(DATE(YEAR($H$1),MONTH($H$1)+1,1)-1)) -> 184090.91 | E41: =IF(MONTH($H$1)<>MONTH(TODAY()),E40,SUM(E5:E11,E13:E19,E21:E27,E29:E35,E37:E38)/DAY(TODAY())*DAY(DATE(YEAR($H$1),MONTH($H$1)+1,1)-1)) -> 5088.9545 | F41: =IF(MONTH($H$1)<>MONTH(TODAY()),F40,SUM(F5:F11,F13:F19,F21:F27,F29:F35,F37:F38)/DAY(TODAY())*DAY(DATE(YEAR($H$1),MONTH($H$1)+1,1)-1)) -> 6818.1815 | G41: =IF(MONTH($H$1)<>MONTH(TODAY()),G40,SUM(G5:G11,G13:G19,G21:G27,G29:G35,G37:G38)/DAY(TODAY())*DAY(DATE(YEAR($H$1),MONTH($H$1)+1,1)-1)) -> 1668.1364 | H41: =IF(MONTH($H$1)<>MONTH(TODAY()),H40,SUM(H5:H11,H13:H19,H21:H27,H29:H35,H37:H38)/DAY(TODAY())*DAY(DATE(YEAR($H$1),MONTH($H$1)+1,1)-1)) -> 2727.2725 | I41: =IF(MONTH($H$1)<>MONTH(TODAY()),I40,SUM(I5:I11,I13:I19,I21:I27,I29:I35,I37:I38)/DAY(TODAY())*DAY(DATE(YEAR($H$1),MONTH($H$1)+1,1)-1)) -> 0 | J41: =IF(MONTH($H$1)<>MONTH(TODAY()),J40,SUM(J5:J11,J13:J19,J21:J27,J29:J35,J37:J38)/DAY(TODAY())*DAY(DATE(YEAR($H$1),MONTH($H$1)+1,1)-1)) -> 0 | ... V41: =IF(MONTH($H$1)<>MONTH(TODAY()),V40,SUM(V5:V11,V13:V19,V21:V27,V29:V35,V37:V38)/DAY(TODAY())*DAY(DATE(YEAR($H$1),MONTH($H$1)+1,1)-1)) -> 393340.91 | W41: Umsatz Forecast
A42: Umsatz pro Tag | C42: =C40/31 -> 4487.6355 | D42: =D40/31 -> 4354.8387 | E42: =E40/31 -> 120.38387 | F42: =F40/31 -> 161.29032 | G42: =G40/31 -> 39.46129 | H42: =H40/31 -> 64.516123 | I42: =I40/31 -> 0 | J42: =J40/31 -> 0 | ... V42: =V40/31 -> 9304.8387 | W42: Budget pro Tag
A43: Diff. zu Budget | C43: =SUM(C40-D40) -> 4116.7 | E43: =SUM(E40-F40) -> -1268.0998 | G43: =SUM(G40-H40) -> -776.6998 | I43: =SUM(I40-J40) -> 0 | K43: =SUM(K40-L40) -> -3737.15 | M43: =SUM(M40-N40) -> -3427.85 | O43: =SUM(O40-P40) -> -8072.6498 | Q43: =SUM(Q40-R40) -> -13165.749 | S43: =SUM(S40-T40) -> 0 | U43: =SUM(U40-V40) -> -13165.749
A44: Index | C44: =SUM(100/D40*C40) -> 103.04941 | E44: =SUM(100/F40*E40) -> 74.638003 | G44: =SUM(100/H40*G40) -> 61.165006 | I44: =SUM(100/J40*I40) -> #DIV/0! | K44: =SUM(100/L40*K40) -> 91.695222 | M44: =SUM(100/N40*M40) -> 92.382556 | O44: =SUM(100/P40*O40) -> 85.699469 | Q44: =SUM(100/R40*Q40) -> 95.435691 | S44: =SUM(100/T40*S40) -> #DIV/0! | U44: =SUM(100/V40*U40) -> 95.435691

Sheet 12_21
A1: Tagesumsätze | H1: 44531
C3: Restaurant | E3: Terrasse | G3: Lounge | I3: Pavillon | K3: Bankett | M3: Seminar | O3: Hotel | Q3: TOTAL Gesamtbetrieb ohne Seebad | S3: Seebad | U3: TOTAL Gesamtbetrieb mit Seebad | W3: Info's
C4: IST | D4: Budget | E4: IST | F4: Budget | G4: IST | H4: Budget | I4: IST | J4: Budget | K4: IST | L4: Budget | M4: IST | N4: Budget | O4: IST | P4: Budget | Q4: IST | R4: Budget | S4: IST | T4: Budget | U4: IST | V4: Budget | W4: Wetter | X4: Temp. | Z4: Bemerkung
A5: 1 | B5: Mi | C5: 5453.8 | D5: 4838.7097 | E5: 0 | F5: 32.25806 | G5: 0 | H5: 32.25806 | I5: 0 | K5: 0 | L5: 1903.2258 | M5: 0 | N5: 483.87096 | O5: 1255.4 | P5: 1464.5161 | Q5: =SUM(C5+E5+G5+I5+K5+M5+O5) -> 6709.2 | R5: =SUM(D5+F5+H5+J5+L5+N5+P5) -> 8754.8387 | S5: 0 | U5: =SUM(Q5+S5) -> 6709.2 | V5: =SUM(R5+T5) -> 8754.8387 | W5: bewölkt | X5: 0 | Y5: °C
A6: =SUM(A5+1) -> 2 | B6: Do | C6: 4078.7 | D6: 4838.7097 | E6: 0 | F6: 32.25806 | G6: 0 | H6: 32.25806 | I6: 0 | K6: 3835.7 | L6: 1903.2258 | M6: 370.5 | N6: 483.87096 | O6: 536.2 | P6: 1464.5161 | Q6: =SUM(C6+E6+G6+I6+K6+M6+O6) -> 8821.1 | R6: =SUM(D6+F6+H6+J6+L6+N6+P6) -> 8754.8387 | S6: 0 | U6: =SUM(Q6+S6) -> 8821.1 | V6: =SUM(R6+T6) -> 8754.8387 | W6: Schneefall | X6: 0 | Y6: °C
